Workbook

Sheet Capacidades
A1: Gestión de Dirección Empresarial
A2: Gestión de Políticas
A3: Gestión de Entidades Empresariales
A4: Gestión de Riesgos
A5: Gestión Financiera
A6: Gestión de Incidentes de Fraude
A7: Gestión de Iniciativas
A8: Gestión de Inversionistas
A9: Gestión de Acuerdos y Contratos con Clientes
A10: Gestión de Instrumentos Financieros
A11: Gestión de Planes Financieros
A12: Gestión de Portafolios de Inversión
... A47: Gestión de Integración e Interoperabilidad

Sheet Tribus
A1: TRIBU | B1: ACRONIMOS
A2: TRIBU ADMINISTRACION DE CREDITO | B2: tac | D2: =CONCATENATE(B2,"-middleware") -> tac-middleware | I2: =CONCATENATE("- "";A2,""") -> - ";A2,"
A3: TRIBU CANALES | B3: tca | D3: =CONCATENATE(B3,"-middleware") -> tca-middleware
A4: COE DATOS & ANALITICA | B4: cda | D4: =CONCATENATE(B4,"-middleware") -> cda-middleware
A5: TRIBU EMPRESAS | B5: tem | D5: =CONCATENATE(B5,"-middleware") -> tem-middleware
A6: TRIBU MEDIOS DE PAGO | B6: tmp | D6: =CONCATENATE(B6,"-middleware") -> tmp-middleware
A7: TRIBU PRODUCTOS | B7: tpr | D7: =CONCATENATE(B7,"-middleware") -> tpr-middleware
A8: TRIBU SEGMENTOS Y NEGOCIOS DIGITALES | B8: tnd | D8: =CONCATENATE(B8,"-middleware") -> tnd-middleware
A9: AREA MICROFINANZAS | B9: tmi | D9: =CONCATENATE(B9,"-middleware") -> tmi-middleware
A10: COE CIBERSEGURIDAD | B10: csg | D10: =CONCATENATE(B10,"-middleware") -> csg-middleware
A11: COE EXPERIENCIA | D11: =CONCATENATE(B11,"-middleware") -> -middleware
A12: COE LACE | D12: =CONCATENATE(B12,"-middleware") -> -middleware
A13: CHAPTER ARQUITECTURA | D13: =CONCATENATE(B13,"-middleware") -> -middleware
A14: TRIBU INFRAESTRUCTURA | D14: =CONCATENATE(B14,"-middleware") -> -middleware
A15: CONTROL_TI | D15: =CONCATENATE(B15,"-middleware") -> -middleware
A16: TRIBU AREAS DE APOYO | B16: taa | D16: =CONCATENATE(B16,"-middleware") -> taa-middleware
A17: TORRES Y SERVICIOS | D17: =CONCATENATE(B17,"-middleware") -> -middleware
A18: AREA REMESAS | B18: trm | D18: =CONCATENATE(B18,"-middleware") -> trm-middleware
A19: TRIBU CORES Y TRANSACCIONES | B19: tct | D19: =CONCATENATE(B19,"-middleware") -> tct-middleware
A20: COE DE TRANSFORMACIÓN DE PROCESOS Y AUTOMATIZACION | B20: cee | D20: =CONCATENATE(B20,"-middleware") -> cee-middleware | F20: bzp-middleware
A21: AREA TECNOLOGIA TI | D21: =CONCATENATE(B21,"-middleware") -> -middleware
A22: CASH MANAGEMENT | D22: =CONCATENATE(B22,"-middleware") -> -middleware
A23: COE ENGINEERING | D23: =CONCATENATE(B23,"-middleware") -> -middleware
A24: DEUDA TECNICA | D24: =CONCATENATE(B24,"-middleware") -> -middleware
A25: MODELO DE ATENCION | D25: =CONCATENATE(B25,"-middleware") -> -middleware
A26: TRIBU INTEGRACIONES Y NUEVAS CAPACIDADES | B26: tia | D26: =CONCATENATE(B26,"-middleware") -> tia-middleware
A27: POR ASIGNAR | D27: =CONCATENATE(B27,"-middleware") -> -middleware
A28: ECOSISTEMA | D28: =CONCATENATE(B28,"-middleware") -> -middleware
A29: Gerencia Proyectos Especiales | D29: =CONCATENATE(B29,"-middleware") -> -middleware
A30: GERENCIA ARQUITECTURA USUARIO FINAL | D30: =CONCATENATE(B30,"-middleware") -> -middleware
A31: GERENCIA SEGURIDAD APLICADA | D31: =CONCATENATE(B31,"-middleware") -> -middleware
A32: GERENCIA SRE | D32: =CONCATENATE(B32,"-middleware") -> -middleware
A33: TRIBU_DE_UNA | D33: =CONCATENATE(B33,"-middleware") -> -middleware

Sheet Puertos
A1: MULTIPROTOCOL GATEWAY | B1: PUERTOS HTTP | C1: PUERTOS HTTPS | D1: PROTOCOLO
A2: MPG_HTTPS_External_Services | B2: 7195 | C2: 9443 | D2: SOAP
A3: MPG_IIB_HTTP_SERVICES | B3: 7180 | C3: 7181 | D3: SOAP
A4: MPG_IIB_SANDBOX | B4: 7182 | C4: 7183 | D4: SOAP
A5: MPG_IIB_SANDBOX_BIMO | B5: 7190 | C5: 7191 | D5: SOAP
A6: MPG_IIB_TFGENERICO | B6: 7184 | C6: 7185 | D6: SOAP
A7: MPG_PSMDW_HTTP_SERVICES | B7: 9180 | C7: 9181 | D7: SOAP
A8: MPGW_BATCH_SOAP_TECNICOS | B8: 8935 | D8: SOAP
A9: MPGW_ESB_JSON_BALANCEO_TECNICOS | B9: 8937 | D9: REST
A10: MPGW_ESB_JSON_BALANCEO_TECNICOS | B10: 18937 | D10: REST
A11: MPGW_ESB_MQ_LOGS_JSON_TECNICOS | B11: 8936 | D11: REST
A12: MPGW_ESB_MQ_LOGS_TECNICOS | B12: 8933 | D12: REST
A13: MPGW_ESB_REST_TECNICOS | C13: 8932 | D13: REST
A14: MPGW_ESB_SOAP_BALANCEO_TECNICOS | B14: 8934 | D14: SOAP
A15: MPGW_ESB_SOAP_BALANCEO_TECNICOS | B15: 8939 | D15: SOAP
A16: MPGW_ESB_SOAP_TECNICOS | B16: 8931 | C16: 8531 | D16: SOAP
A17: MPGW_EXT_XML_WATCHLIST | C17: 7635 | D17: SOAP
A18: MPGW_EXT_SOAP_WATCHLIST | C18: 7634 | D18: SOAP
A19: MPGW_EXT_REST_WATCHLIST | C19: 7633 | D19: REST
A20: MPGW_ESB_SOAP_SOPORTE | B20: 8901 | C20: 8501 | D20: SOAP
A21: MPGW_ESB_REST_SOPORTE | C21: 8902 | D21: REST
A22: MPGW_AYS_REST_BANRED | C22: 8904 | D22: REST
A23: MPGW_ESB_REST_ADMINISTRACION | C23: 8982 | D23: REST
A24: MPGW_ESB_SOAP_ADMINISTRACION | B24: 8981 | D24: SOAP
A25: MPGW_ESB_REST_PAGOS | C25: 8972 | D25: REST
A26: MPGW_ESB_SOAP_PAGOS | B26: 8971 | D26: SOAP
A27: MPGW_ESB_REST_PRODUCTOS | C27: 8922 | D27: REST
A28: MPGW_ESB_SOAP_PRODUCTOS | B28: 8921 | D28: SOAP
A29: MPGW_ESB_REST_REGLAS | C29: 8962 | D29: REST
A30: MPGW_ESB_SOAP_REGLAS | C30: 8561 | D30: SOAP
A31: MPGW_ESB_SOAP_REGLAS | B31: 8961 | D31: SOAP
A32: MPGW_ESB_REST_SEGURIDAD | C32: 8952 | D32: REST
A33: MPGW_ESB_SOAP_SEGURIDAD | C33: 8551 | D33: SOAP
A34: MPGW_ESB_SOAP_SEGURIDAD | B34: 8951 | D34: SOAP
A35: MPGW_ESB_AAA_SOAP_SEGURIDAD | B35: 8953 | D35: SOAP
A36: MPGW_ESB_REST_TRANSFERENCIAS | C36: 8942 | D36: REST
A37: MPGW_ESB_SOAP_TRANSFERENCIAS | C37: 8541 | D37: SOAP
A38: MPGW_ESB_SOAP_TRANSFERENCIAS | B38: 8941 | D38: SOAP
A39: MPGW_ESB_REST_CLIENTES | C39: 8912 | D39: REST
A40: MPGW_ESB_SOAP_CLIENTES | B40: 8911 | C40: 8511 | D40: SOAP

Sheet Matriz a proveedor
B2: Datos a enviar al proveedor
B3: Nombre actual
B4: Descripción
B5: Nombre migrado
B6: Criticidad
B7: URL IcePanel
B8: URL WSDL
B9: URL Repositorio
B10: Protocolos
B11: Consumidores
B12: Tribu onwer

Sheet Criterios de complejidad
A1: Criterio | B1: Baja | C1: Media | D1: Alta | E1: Observación | F1: Fuente
A2: Integraciones | B2: 1 sistema | C2: 2-3 sistemas | D2: Más de 3 sistemas | E2: Cuantos backend consume el servicio? | F2: Codigo / Dynatrace
A3: Protocolos | B3: Solo SOAP o solo REST | C3: SOAP + REST o JMS | D3: Múltiples protocolos (REST, SOAP, FTP, MQ, etc.) | E3: Por cuantos protocolos es consumido el servicio? | F3: Dynatrace
A4: Transformaciones de datos | B4: Mínimas o nulas (0-1) | C4: Mapeos simples (JSON ↔ XML) Persistencia Datos (2-3) Cifrado o Encriptacion | D4: XSLT complejos, múltiples formatos Persistencia Datos (>3) Cifrado y Encriptacion | E4: Realiza transformaciones de data para consumo de algun backend?? | F4: Codigo
A5: Cache | B5: Ninguno | C5: Parcialmente | D5: Persistencia compleja | E5: Maneja guardado de información en cache obtenida desde algun backend? | F5: Codigo
A6: Volumen de datos | B6: < 50 K | C6: 50 K - 1M | D6: > 1 M | E6: Obtener numero de transacciones del servicio en dia mas transaccional desde dynatrace (recomendado quincena o fin de mes) | F6: Dynatrace
A7: Impacto en otros servicios | B7: Independiente (ORQ) (puede ser probado por la app) | C7: Afecta algunos servicios omni (WS) | D7: Altamente acoplado, impacto transversal (Servicio Generico) | E7: Es un servicio transversal o genérico? | F7: Baja para todos
A8: Consumidores | B8: 1 consumidor | C8: 2 -3 consumidores | D8: mas de 3 consumidores | E8: Cuantas aplicaciones consumen el servicio? | F8: Dynatrace / Logs
A9: Interacción con proveedores externos | B9: Ninguno | C9: 1 proveedor | D9: 2 o mas proveedores | E9: El servicio es consumido o consume algun servicio de proveedor? Banred, interdin, otros | F9: Dynatrace / Código
A10: Metodos que expone | B10: 1 metodo | C10: 2 -3 metodos | D10: Más de 3 metodos | E10: Metodos que expone el servicio | F10: Dynatrace / Código

Sheet Validacion de servicios
A1: Servicio | B1: Nuevo nombre | C1: Descripción / Funcionalidad | D1: TRIBU | E1: ACRONIMO | F1: Tecnologia | G1: Tipo | H1: Estado del análisis | I1: Estado del servicio | J1: Integraciones / Consume | K1: Tecnologia del backend | L1: Tecnologia para despliegue de servicio migrado | M1: # Integraciones | N1: Peso | O1: Protocolos de consumo | P1: # Protocolos | Q1: Peso | R1: Transformaciones de datos | S1: # de transformaciones | T1: Peso | U1: Cache Adicional al config | V1: Archivo o servicio de donde obtiene informacion para cache | W1: Peso | X1: Volumen de datos / Request | Y1: Volumen de datos / Response time | Z1: TPM promedio (rango 2 horas) | AA1: TPM hora pico (rango 2 horas) | AB1: Peso | AC1: Impacto en otros servicios | AD1: Peso | AE1: Tribu consumidor | AF1: Consumidores / Servicios | AG1: Consumidores / Sitios | AH1: # de consumidores | AI1: Peso | AJ1: Interacción con proveedores externos | AK1: Peso | AL1: Metodos que expone | AM1: Peso | AN1: Peso del servicio | AO1: Complejidad del servicio | AP1: Proveedor que migrara el servicio | AQ1: Observación Discovery | AR1: Priorizacion | AS1: LINK ICEPANEL | AT1: LINK WSDL | AU1: LINK CODIGO | AV1: OLA | AW1: Consumen tecnologia deprecada
A2: ORQClientes0002 | B2: =CONCATENATE(LOWER(E2),"-msa-sp-",LOWER(A2)) -> tnd-msa-sp-orqclientes0002 | C2: Consulta información básica del cliente | D2: TRIBU SEGMENTOS Y NEGOCIOS DIGITALES | E2: =VLOOKUP(D2,Tribus!$A$1:$B$33,2,FALSE) -> tnd | F2: Bus Omnicanalidad | G2: ORQ | H2: Completado | I2: A Desarrollo | J2: WSTecnicos0036 (ConsultarDetalleTransaccionDelay03) - umptecnicos0111 (ConsultarDetalleTransaccionDelayCTServicio) -> BDD: PPOMNICA ESQUEMA: TRANESPERA TABLA: OMN_TRA_TRANSACCION_ESPERA WSTecnicos0006 (ConsultarAtributosTransaccion01) -> UMPTransferencias0001 (ValidarCupoCanalTransferencia51) -> TX031967 (Validación de cupo sobre cuenta para transferencias en la Banca Electrónica.) -> UMPTecnicos0025 (ConsultarDetallesEntidadFinanciera01) -> URL WAS http://10.151.8.62:8934/Omnicanalidad/AplicationServer/WSTecnicos0008 (Consulta detalles entidad financiera) -> UMPProductos0045 (ConsultarCobroReferenciaBancaria01) -> TX000503 (Consulta de cobro referencia bancaria.) WSClientes0024 (ConsultarIdentificacion01) -> UMPClientes0002 (ConsultarInformacionBasica01) -> TX060480 (Consulta datos de contacto para cliente de BEP e información básica) -> UMPClientes0181 (ConsultarInformacionBasicaOPS01) -> URL OCP https://mdw-msa-sp-tmp-customer-enp.apps.ocptest.uiotest.bpichinchatest.test/PartyReferenceDataDirectory/Reference/Retrieve (ConsultarInformacionBasicaOPS01) WSClientes0007 (ConsultarContactoTransaccional01) -> UMPClientes0002 (ConsultarInformacionBasica01) -> TX060480 (Consulta datos de contacto para cliente de BEP e información básica) -> UMPClientes0028 (ConsultarIdentificacion01) NO SE USA -> UMPClientes0003 (ConsultarContactoNotificacion01) -> TX067186 (Consulta datos de contacto para cliente de BEP e información básica) -> UMPClientes0020 (ConsultaInformacionCliente01) -> TX067050 (Consulta información basica del cliente mediante TX067050.) -> UMPClientes0005 (ActualizarContactoTransaccional31) -> TX067186 (Actualiza datos del contacto transaccional) WSClientes0006 (ConsultarInformacionBasica01) -> UMPClientes0020 (ConsultaInformacionCliente01) -> TX067050 (Consulta información basica del cliente mediante TX067050.) -> UMPTecnicos0006 (ConsultarTransaccionCatalogo01) -> TX079006 (Consultar TX de catalogo: ciudad, nacionalidad, agencia) -> UMPClientes0042 (ConsultarReferencia01) -> TX062120 (Consulta de Cuentas del cliente en Bancs) | K2: Bus Omnicanalidad Was Omnicanalidad | L2: ON-PREMISE | M2: 5 | N2: Alta | O2: api 8912 api - 443 - https://apis.pichincha.com/support/apigee/orqclientes0002/v1/api/customers-persons-contact-points/retrieve (APIM) -> datapowr interno api - 443 - https://api.pichincha.com/sda/tcs/ORQClientes0002 (APIGEE) -> datapower externo | P2: REST SOAP | Q2: Media | R2: Ninguna | S2: 0 | T2: Baja | U2: Almacena información de backend en cache obteniendo del WSTecnicos0006 para atributos de la tansaccion | V2: WSTecnicos0006 | W2: Media | X2: 129K | Y2: 202ms | AB2: Media | AC2: Si puede ser probado por las app | AD2: Baja | AE2: TRIBU CANALES TRIBU MEDIOS DE PAGO TRIBU PRODUCTOS TRIBU SEGMENTOS Y NEGOCIOS DIGITALES | AF2: APIM sda-msa-bank-certificates;CertificateController tdd-msa-card;CustomerAddressController crd-msa-customer-integration;CustomerIntegrationController tdd-msa-card;DebitCardRequestController bmo-msa-core-account-client-name;ClientNameController mht-msa-user-profile;ClientInformationController | AG2: 0 | AH2: 5 | AI2: Alta | AJ2: Ninguno | AK2: Baja | AL2: ConsultaInformacionBasicaCliente01 | AM2: Baja | AN2: =IFERROR(SUM(CHOOSE(MATCH(N2,{"Baja";"Media";"Alta"},0),1,2,3), CHOOSE(MATCH(Q2,{"Baja";"Media";"Alta"},0),1,2,3), CHOOSE(MATCH(T2,{"Baja";"Media";"Alta"},0),1,2,3), CHOOSE(MATCH(W2,{"Baja";"Media";"Alta"},0),1,2,3), CHOOSE(MATCH(AB2,{"Baja";"Media";"Alta"},0),1,2,3), CHOOSE(MATCH(AD2,{"Baja";"Media";"Alta"},0),1,2,3), CHOOSE(MATCH(AI2,{"Baja";"Media";"Alta"},0),1,2,3), CHOOSE(MATCH(AK2,{"Baja";"Media";"Alta"},0),1,2,3), CHOOSE(MATCH(AM2,{"Baja";"Media";"Alta"},0),1,2,3)),0) -> 16 | AO2: =IF(AN2=0,"Pendiente",IF(AN2<=15,"Bajo",IF(AN2<=21,"Medio","Alto"))) -> Medio | AR2: =VLOOKUP(A2,#REF!,2,FALSE) -> #REF! | AS2: https://app.icepanel.io/landscapes/w71QNHgfDvF79GrSuA3r/versions/latest/diagrams/editor?diagram=hhqQHHJSsg&model=sgwrn80kg0j&overlay_tab=tags&x1=-301.6&y1=-192&x2=1697.6&y2=832 | AT2: https://dev.azure.com/BancoPichinchaEC/adi-especificaciones-tecnicas/_git/adi-doc-tecspec-tribu-integracion-apis?version=GBmaster&path=/sp%20-%20Soporte/tnd-msa-sp-orqclientes0002 | AU2: https://dev.azure.com/BancoPichinchaEC/tpl-bus-omnicanal/_git/sqb-msa-orqclientes0002 | AV2: 1 | AW2: PCBG-545
A3: ORQClientes0003 | B3: =CONCATENATE(LOWER(E3),"-msa-sp-",LOWER(A3)) -> tpr-msa-sp-orqclientes0003 | C3: Orquestador que permite realizar la consulta de la posición consolidada de clientes. | D3: TRIBU PRODUCTOS | E3: =VLOOKUP(D3,Tribus!$A$1:$B$33,2,FALSE) -> tpr | F3: Bus Omnicanalidad | G3: ORQ | H3: Completado | I3: A Desarrollo | J3: WSClientes0024 --> ConsultarIdentificacion01 WSProductos0024 --> ConsultarDescripcionTodosProductos01 WSProductos0023 --> ConsultarConfiguracionProducto01 WSClientes0114 --> ConsultaCuentasCliente02 WSClientes0002 --> consultarPrestamosActivos01 ays-msa-dm-wsclientes0220 --> api/v1/Tarjetas/ConsultarTarjetas01 WSClientes0003 --> ConsultarTarjetasActivas01 WSProductos0123 --> consultarCatalogoTarjeta02 WSProductos0118 --> consultarClienteInterdin02 | K3: Bus Omnicanalidad Was Omnicanalidad openshift | L3: ON-PREMISE | M3: 9 | N3: Alta | O3: SOAP | P3: 1 | Q3: Baja | R3: Mapeo hacia servicio de consulta de tarjetas de OPS | S3: 1 | T3: Media | U3: Almacena archivos de parametros y catalogos en cache path: configuraciones/301000301.xml | V3: configuraciones/301000301.xml | W3: Alta | X3: 11.9M | Y3: 181ms | AB3: Alta | AC3: Si puede ser probado por las app | AD3: Baja | AE3: TRIBU MEDIOS DE PAGO TRIBU EMPRESAS TRIBU PRODUCTOS TRIBU CANALES COE_TRANSFORMACION_PROCESOS | AF3: APIM tdd-msa-card;AccountClientController omn-msa-account-balance;AccountController inv-msa-investments;AccountsController app-balance-by-type-account;AccountBalanceByTypeController app-transaction-balance;TransactionBalanceController bbe-msa-sp-account sda-msa-payments;BillPaymentsController omn-msa-account-balance;CreditCardController tdd-msa-card;DebitCardRequestController sge-msa-ux-insurance;HubController sda-msa-payments;ListFavoritesController one-msa-sp-customer-product sda-msa-payments;ProductSummaryController bbe-msa-bs-loan bbe-msa-sp-credit-card app-transaction-balance;TransactionBalanceController omn-msa-account-balance;ProductSummaryController sda-msa-payments;BillPaymentsController sda-msa-payments;PaymentFavoritesController sge-msa-insurance;InsuranceControllerImpl | AG3: Default Web Site:443,8043 (/BPMPichinchaSG) Default Web Site:80,8080 (/WApi_NetManager_CNB_MPagos) | AH3: 23 | AI3: Alta | AJ3: Interdin - Optar Integrador | AK3: Alta | AL3: ConsultarProductosActivos01 | AM3: Baja | AN3: =IFERROR(SUM(CHOOSE(MATCH(N3,{"Baja";"Media";"Alta"},0),1,2,3), CHOOSE(MATCH(Q3,{"Baja";"Media";"Alta"},0),1,2,3), CHOOSE(MATCH(T3,{"Baja";"Media";"Alta"},0),1,2,3), CHOOSE(MATCH(W3,{"Baja";"Media";"Alta"},0),1,2,3), CHOOSE(MATCH(AB3,{"Baja";"Media";"Alta"},0),1,2,3), CHOOSE(MATCH(AD3,{"Baja";"Media";"Alta"},0),1,2,3), CHOOSE(MATCH(AI3,{"Baja";"Media";"Alta"},0),1,2,3), CHOOSE(MATCH(AK3,{"Baja";"Media";"Alta"},0),1,2,3), CHOOSE(MATCH(AM3,{"Baja";"Media";"Alta"},0),1,2,3)),0) -> 20 | AO3: =IF(AN3=0,"Pendiente",IF(AN3<=15,"Bajo",IF(AN3<=21,"Medio","Alto"))) -> Medio | AR3: =VLOOKUP(A3,#REF!,2,FALSE) -> #REF! | AS3: https://s.icepanel.io/wJSECZOwwNkkW8/Rqyj | AT3: https://dev.azure.com/BancoPichinchaEC/adi-especificaciones-tecnicas/_git/adi-doc-tecspec-tribu-integracion-apis?path=/sp%20-%20Soporte/tpr-msa-sp-orqclientes0003 | AU3: sqb-msa-orqclientes0003 - Repos | AV3: 1 | AW3: https://pichincha.atlassian.net/browse/PCBG-654
A4: ORQClientes0004 | B4: =CONCATENATE(LOWER(E4),"-msa-sp-",LOWER(A4)) -> tnd-msa-sp-orqclientes0004 | C4: Microservicio que actualiza contacto transaccional | D4: TRIBU SEGMENTOS Y NEGOCIOS DIGITALES | E4: =VLOOKUP(D4,Tribus!$A$1:$B$33,2,FALSE) -> tnd | F4: Bus Omnicanalidad | G4: ORQ | H4: Completado | I4: A Desarrollo | J4: WSClientes0020 -> ActualizarContactoTransaccional31 WSClientes0024 -> ConsultarIdentificacion01 WSClientes0028 -> ConsultarClientePagosPichincha01, ActualizarClientePagosPichincha32 WSClientes0030 -> ConsultarContactoNotificacion01 WSProductos0015 -> ConsultarClientePichinchaCelular01, ActualizarClientePichinchaCelular32 WSSeguridad0020 -> consultarAfiliado01, actualizarInformacion33, actualizarEstadoClienten34 | K4: Bus Omnicanalidad Was Omnicanalidad | L4: ON-PREMISE | M4: 6 | N4: Alta | O4: REST SOAP | P4: 2 | Q4: Media | R4: Ninguna | S4: 0 | T4: Baja | U4: Ninguna | W4: Baja | X4: 455 | Y4: 339ms | AB4: Baja | AC4: Si puede ser probado por las app | AD4: Baja | AE4: TRIBU CANALES | AF4: Ninguno | AG4: Segun BDD: 00352 - Portal Empresarial_BPM | AH4: 1 | AI4: Baja | AJ4: Ninguno | AK4: Baja | AL4: ActualizarContactoTransaccional31 | AM4: Baja | AN4: =IFERROR(SUM(CHOOSE(MATCH(N4,{"Baja";"Media";"Alta"},0),1,2,3), CHOOSE(MATCH(Q4,{"Baja";"Media";"Alta"},0),1,2,3), CHOOSE(MATCH(T4,{"Baja";"Media";"Alta"},0),1,2,3), CHOOSE(MATCH(W4,{"Baja";"Media";"Alta"},0),1,2,3), CHOOSE(MATCH(AB4,{"Baja";"Media";"Alta"},0),1,2,3), CHOOSE(MATCH(AD4,{"Baja";"Media";"Alta"},0),1,2,3), CHOOSE(MATCH(AI4,{"Baja";"Media";"Alta"},0),1,2,3), CHOOSE(MATCH(AK4,{"Baja";"Media";"Alta"},0),1,2,3), CHOOSE(MATCH(AM4,{"Baja";"Media";"Alta"},0),1,2,3)),0) -> 12 | AO4: =IF(AN4=0,"Pendiente",IF(AN4<=15,"Bajo",IF(AN4<=21,"Medio","Alto"))) -> Bajo | AR4: =VLOOKUP(A4,#REF!,2,FALSE) -> #REF! | AS4: https://app.icepanel.io/landscapes/w71QNHgfDvF79GrSuA3r/versions/latest/diagrams/editor?diagram=C7BopaQBkK&model=IpbKqE7HWq&overlay_tab=tags&x1=0&y1=0&x2=1272&y2=564 | AT4: https://dev.azure.com/BancoPichinchaEC/adi-especificaciones-tecnicas/_git/adi-doc-tecspec-tribu-integracion-apis?version=GBmaster&path=/sp%20-%20Soporte/tnd-msa-sp-orqclientes0004 | AU4: https://dev.azure.com/BancoPichinchaEC/tpl-bus-omnicanal/_git/sqb-msa-orqclientes0004 | AV4: 1 | AW4: https://pichincha.atlassian.net/browse/PCBG-583
A5: ORQClientes0005 | B5: =CONCATENATE(LOWER(E5),"-msa-sp-",LOWER(A5)) -> csg-msa-sp-orqclientes0005 | C5: Servicio que actualiza preferencia de notificación para segundo factor de autenticación (OTP, Clave Dinámica) en BDD | D5: COE CIBERSEGURIDAD | E5: =VLOOKUP(D5,Tribus!$A$1:$B$33,2,FALSE) -> csg | F5: Bus Omnicanalidad | G5: ORQ | H5: Completado | I5: A Desarrollo | J5: WSClientes0024 --> ConsultarIdentificacion01 WSClientes0006 --> ConsultarInformacionBasica01 WSTecnicos0039 --> actualizarNotificacionesPorCliente31 WSClientes0010 --> consultarGrupoClaveDigital01 WSClientes0026 --> consultar02 WSClientes0026 --> registrar23 WSClientes0026 --> incrementar34 | K5: Bus Omnicanalidad Was Omnicanalidad | L5: ON-PREMISE | M5: 7 | N5: Alta | O5: SOAP | P5: 1 | Q5: Baja | R5: Si, existe cifrado mediante TCSProvider previo al llamado de servicios | S5: 1 | T5: Media | U5: Ninguna | W5: Baja | X5: 2.33k | Y5: 180ms | AB5: Baja | AC5: Si puede ser probado por las app | AD5: Baja | AE5: TRIBU CANALES | AF5: Se consume operativamente desde el Administrador Omnicanal | AG5: Administrador Omnicanal | AH5: 1 | AI5: Baja | AJ5: Ninguno | AK5: Baja | AL5: ActualizarMedioNotificacionCliente31 | AM5: Baja | AN5: =IFERROR(SUM(CHOOSE(MATCH(N5,{"Baja";"Media";"Alta"},0),1,2,3), CHOOSE(MATCH(Q5,{"Baja";"Media";"Alta"},0),1,2,3), CHOOSE(MATCH(T5,{"Baja";"Media";"Alta"},0),1,2,3), CHOOSE(MATCH(W5,{"Baja";"Media";"Alta"},0),1,2,3), CHOOSE(MATCH(AB5,{"Baja";"Media";"Alta"},0),1,2,3), CHOOSE(MATCH(AD5,{"Baja";"Media";"Alta"},0),1,2,3), CHOOSE(MATCH(AI5,{"Baja";"Media";"Alta"},0),1,2,3), CHOOSE(MATCH(AK5,{"Baja";"Media";"Alta"},0),1,2,3), CHOOSE(MATCH(AM5,{"Baja";"Media";"Alta"},0),1,2,3)),0) -> 12 | AO5: =IF(AN5=0,"Pendiente",IF(AN5<=15,"Bajo",IF(AN5<=21,"Medio","Alto"))) -> Bajo | AQ5: Considerar que el servicio se utilizaba para validar factor de autenticación al inicio de la clave digital, se debe validar si su logica se sigue usando de lo contratio se debe deprecar | AR5: =VLOOKUP(A5,#REF!,2,FALSE) -> #REF! | AS5: https://s.icepanel.io/wJSECZOwwNkkW8/geiS | AT5: https://dev.azure.com/BancoPichinchaEC/adi-especificaciones-tecnicas/_git/adi-doc-tecspec-tribu-integracion-apis?version=GBmaster&path=/sp%20-%20Soporte/csg-msa-sp-orqclientes0005 | AU5: sqb-msa-orqclientes0005 - Repos | AV5: 1 | AW5: https://pichincha.atlassian.net/browse/PCBG-584
A6: ORQClientes0007 | B6: =CONCATENATE(LOWER(E6),"-msa-sp-",LOWER(A6)) -> tpr-msa-sp-orqclientes0007 | C6: Servicio que actualiza cupo de cuentas del cliente | D6: TRIBU PRODUCTOS | E6: =VLOOKUP(D6,Tribus!$A$1:$B$33,2,FALSE) -> tpr | F6: Bus Omnicanalidad | G6: ORQ | H6: Completado | I6: A Desarrollo | J6: WSClientes0114 WSProductos0009 CE_EVENTOS | K6: Bus Omnicanalidad | L6: ON-PREMISE | M6: 1 | N6: Baja | O6: SOAP | P6: 1 | Q6: Baja | R6: Ninguna | S6: 0 | T6: Baja | U6: Parcialmente. path: configuraciones/000000001.xml | V6: configuraciones/000000001.xml | W6: Media | X6: 5.54K | Y6: 188ms | AB6: Baja | AC6: Puede ser consumido por apps. | AD6: Baja | AE6: TRIBU_CANALES | AF6: ORQTecnicos0003 (Invoca servicios asyncronos) | AG6: Segun BDD 00663 -> Banca Movil 00647 -> Banca Web | AH6: 2 | AI6: Media | AJ6: Ninguno | AK6: Baja | AL6: ActualizarCupoCuentaTransaccion31 | AM6: Baja | AN6: =IFERROR(SUM(CHOOSE(MATCH(N6,{"Baja";"Media";"Alta"},0),1,2,3), CHOOSE(MATCH(Q6,{"Baja";"Media";"Alta"},0),1,2,3), CHOOSE(MATCH(T6,{"Baja";"Media";"Alta"},0),1,2,3), CHOOSE(MATCH(W6,{"Baja";"Media";"Alta"},0),1,2,3), CHOOSE(MATCH(AB6,{"Baja";"Media";"Alta"},0),1,2,3), CHOOSE(MATCH(AD6,{"Baja";"Media";"Alta"},0),1,2,3), CHOOSE(MATCH(AI6,{"Baja";"Media";"Alta"},0),1,2,3), CHOOSE(MATCH(AK6,{"Baja";"Media";"Alta"},0),1,2,3), CHOOSE(MATCH(AM6,{"Baja";"Media";"Alta"},0),1,2,3)),0) -> 11 | AO6: =IF(AN6=0,"Pendiente",IF(AN6<=15,"Bajo",IF(AN6<=21,"Medio","Alto"))) -> Bajo | AQ6: Interactua con el MQ , lee mensaje | AR6: =VLOOKUP(A6,#REF!,2,FALSE) -> #REF! | AS6: https://s.icepanel.io/wJSECZOwwNkkW8/PkZD | AT6: https://dev.azure.com/BancoPichinchaEC/adi-especificaciones-tecnicas/_git/adi-doc-tecspec-tribu-integracion-apis?path=/sp%20-%20Soporte/tpr-msa-sp-orqclientes0007 | AU6: https://dev.azure.com/BancoPichinchaEC/tpl-bus-omnicanal/_git/sqb-msa-orqclientes0007?path=/com/bpichincha/esb/orqclientes0007/ActualizarCupoCuentaTransaccion31.esql | AV6: 1 | AW6: https://pichincha.atlassian.net/browse/PCBG-585
A7: ORQClientes0008 | B7: =CONCATENATE(LOWER(E7),"-msa-sp-",LOWER(A7)) -> tnd-msa-sp-orqclientes0008 | C7: Consultar detalle del cliente | D7: TRIBU SEGMENTOS Y NEGOCIOS DIGITALES | E7: =VLOOKUP(D7,Tribus!$A$1:$B$33,2,FALSE) -> tnd | F7: Bus Omnicanalidad | G7: ORQ | H7: Completado | I7: A Desarrollo | J7: WSClientes0024 -> ConsultarIdentificacion01 WSClientes0037 -> ConsultarClienteRegistroCivil01 WSClientes0038 -> ConsultarDetalleAdicionalesCliente01 / opc 5 / 21 / 1 / WSTecnicos0063 -> obtenerCatalogosSigloBancs01 | K7: Bus Omnicanalidad Was Omnicanalidad | L7: ON-PREMISE | M7: 4 | N7: Alta | O7: REST - datapowerexterno SOAP | P7: 2 | Q7: Media | R7: Ninguna | S7: 0 | T7: Baja | U7: Nacionalidades. Consumido de WSTecnicos0063 | V7: WSTecnicos0063 | W7: Media | X7: 9.96K | Y7: 310ms | AB7: Baja | AC7: Si puede ser probado por las app | AD7: Baja | AE7: AREA MICROFINANZAS | AF7: https://serviciosexternos.pichincha.com:8445/BPMicrofinanzasProd/Servicios/Rest/FlexibleUpdateWorkOrder | AG7: Segun BDD: Microfinanzas - 00650 | AH7: 1 | AI7: Baja | AJ7: ninguno | AK7: Baja | AL7: ConsultarDetalleCliente01 | AM7: Baja | AN7: =IFERROR(SUM(CHOOSE(MATCH(N7,{"Baja";"Media";"Alta"},0),1,2,3), CHOOSE(MATCH(Q7,{"Baja";"Media";"Alta"},0),1,2,3), CHOOSE(MATCH(T7,{"Baja";"Media";"Alta"},0),1,2,3), CHOOSE(MATCH(W7,{"Baja";"Media";"Alta"},0),1,2,3), CHOOSE(MATCH(AB7,{"Baja";"Media";"Alta"},0),1,2,3), CHOOSE(MATCH(AD7,{"Baja";"Media";"Alta"},0),1,2,3), CHOOSE(MATCH(AI7,{"Baja";"Media";"Alta"},0),1,2,3), CHOOSE(MATCH(AK7,{"Baja";"Media";"Alta"},0),1,2,3), CHOOSE(MATCH(AM7,{"Baja";"Media";"Alta"},0),1,2,3)),0) -> 13 | AO7: =IF(AN7=0,"Pendiente",IF(AN7<=15,"Bajo",IF(AN7<=21,"Medio","Alto"))) -> Bajo | AR7: =VLOOKUP(A7,#REF!,2,FALSE) -> #REF! | AS7: https://s.icepanel.io/wJSECZOwwNkkW8/s2K8 | AT7: https://dev.azure.com/BancoPichinchaEC/adi-especificaciones-tecnicas/_git/adi-doc-tecspec-tribu-integracion-apis?path=/sp%20-%20Soporte/tnd-msa-sp-orqclientes0008 | AU7: https://dev.azure.com/BancoPichinchaEC/tpl-bus-omnicanal/_git/sqb-msa-orqclientes0008 | AV7: 1 | AW7: https://pichincha.atlassian.net/browse/PCBG-586
A8: ORQClientes0016 | B8: =CONCATENATE(LOWER(E8),"-msa-sp-",LOWER(A8)) -> tnd-msa-sp-orqclientes0016 | C8: Orquestar las consultas para obtener la informacion complementaria del cliente | D8: TRIBU SEGMENTOS Y NEGOCIOS DIGITALES | E8: =VLOOKUP(D8,Tribus!$A$1:$B$33,2,FALSE) -> tnd | F8: Bus Omnicanalidad | G8: ORQ | H8: Completado | I8: A Desarrollo | J8: ORQClientes0016 WSClientes0060 (informacionAdicionalClienteSFI01 - WAS) -> UMPClientes0075 (OperacionInformacionComplementariaCliente51) -> UMPClientes0075 (ObtenerInformacionAdicionalClienteSFI) -> BDD: CREDIFE, SP: CFE_INFCOMPL_MVL(?,?) WSClientes0060 (OperacionDatosComplementariosCliente51 - IIB) -> UMPClientes0075 (OperacionInformacionComplementariaCliente51) -> TX067145 (Consultar informacion complentaria del cliente) WSClientes0038 (OperacionEconomicosCliente52) -> UMPClientes0020 (ConsultaInformacionCliente01) -> TX067050 (opc 1, 5, 15, 21) -> UMPClientes0061 (ActualizarInfAdicionalCliente31) -> TX067118 -> UMPClientes0057 (ActualizarInformacionCliente31) -> TX067116 WSClientes0055 (OperacionActividadEconomicaCliente51) -> UMPClientes0069 (Consulta actividad economica) -> TX67196 -> UMPClientes0066 (Consulta Correspondencia (localizacion)) -> TX062120 WSClientes0061 (OperacionDemograficosCliente51) -> UMPClientes0077 (OperacionDemograficosCliente51) -> TX061406 WSClientes0062 (OperacionIdentificacionCliente51) - UMPClientes0078 (OperacionIdentificacionCliente51 )-> TX067153 -> Consulta información de identificación del cliente WSClientes0099 (OperacionLocalizacion51) -> UMPClientes0064 - OperacionLocalizacion51 - TX061404 - Consulta la direccion de un cliente -> UMPClientes0065 - OperacionGeolocalizacion51 - TX062130 - Consulta la geolocalizacion de un cliente WSClientes0007 (ConsultarContactoTransaccional01) -> UMPClientes0002 -> ConsultarInformacionBasica01 -> TX060480 -> Consulta el CIF del cliente UMPClientes0028 -> ConsultarIdentificacion01 -> http://10.151.8.62:8934/Omnicanalidad/AplicationServer/WSClientes0045 -> Consulta identificacion cliente UMPClientes0020 -> ConsultaInformacionCliente01 -> 067050 -> Consulta información basica del cliente UMPClientes0003 -> ConsultarContactoNotificacion01 -> TX067186 -> Consulta contacto transaccional del cliente UMPClientes0005 -> ActualizarContactoTransaccional31 -> TX067186 -> Actualizar el contacto transaccional del cliente WSTecnicos0063 (obtenerCatalogosSigloBancs01) -> umptecnicos0066 (obtenerCatalogosSigloBean) -> Consulta de catalogos a BANCS , CREDIFE y S21 | K8: Bus Omnicanalidad Was Omnicanalidad | L8: ON-PREMISE | M8: 8 | N8: Alta | O8: REST - datapowerexterno SOAP | P8: 2 | Q8: Media | R8: Ninguna | S8: 0 | T8: Baja | U8: Almacena información de backend en cache, consumiendo WSTecnicos0063 | V8: WSTecnicos0063 | W8: Media | X8: 4.58K | Y8: 529ms | AB8: Baja | AC8: Si puede ser probado por las app | AD8: Baja | AE8: AREA MICROFINANZAS | AF8: https://serviciosexternos.pichincha.com:8445/BPMicrofinanzasProd/Servicios/Rest/FlexibleUpdateWorkOrder | AG8: Segun BDD: 00650 - Microfinanzas | AH8: - | AI8: Baja | AJ8: Ninguno | AK8: Baja | AL8: InformacionComplementariaCliente01 | AM8: Baja | AN8: =IFERROR(SUM(CHOOSE(MATCH(N8,{"Baja";"Media";"Alta"},0),1,2,3), CHOOSE(MATCH(Q8,{"Baja";"Media";"Alta"},0),1,2,3), CHOOSE(MATCH(T8,{"Baja";"Media";"Alta"},0),1,2,3), CHOOSE(MATCH(W8,{"Baja";"Media";"Alta"},0),1,2,3), CHOOSE(MATCH(AB8,{"Baja";"Media";"Alta"},0),1,2,3), CHOOSE(MATCH(AD8,{"Baja";"Media";"Alta"},0),1,2,3), CHOOSE(MATCH(AI8,{"Baja";"Media";"Alta"},0),1,2,3), CHOOSE(MATCH(AK8,{"Baja";"Media";"Alta"},0),1,2,3), CHOOSE(MATCH(AM8,{"Baja";"Media";"Alta"},0),1,2,3)),0) -> 13 | AO8: =IF(AN8=0,"Pendiente",IF(AN8<=15,"Bajo",IF(AN8<=21,"Medio","Alto"))) -> Bajo | AR8: =VLOOKUP(A8,#REF!,2,FALSE) -> #REF! | AS8: https://app.icepanel.io/landscapes/w71QNHgfDvF79GrSuA3r/versions/latest/diagrams/editor?diagram=uV2Jon7cnA&model=TBYWzEmBgJ&overlay_tab=tags&x1=-301.6&y1=-192&x2=1697.6&y2=832 | AT8: https://dev.azure.com/BancoPichinchaEC/adi-especificaciones-tecnicas/_git/adi-doc-tecspec-tribu-integracion-apis?path=/sp%20-%20Soporte/tnd-msa-sp-orqclientes0016 | AU8: https://dev.azure.com/BancoPichinchaEC/tpl-bus-omnicanal/_git/sqb-msa-orqclientes0016 | AV8: 1 | AW8: https://pichincha.atlassian.net/browse/PCBG-587
A9: ORQClientes0017 | B9: =CONCATENATE(LOWER(E9),"-msa-sp-",LOWER(A9)) -> tpr-msa-sp-orqclientes0017 | C9: Consultar Productos del Cliente | D9: TRIBU PRODUCTOS | E9: =VLOOKUP(D9,Tribus!$A$1:$B$33,2,FALSE) -> tpr | F9: Bus Omnicanalidad | G9: ORQ | H9: Completado | I9: A Desarrollo | J9: WSClientes0002 WSClientes0038 WSClientes0067 WSClientes0080 WSProductos0082 WSSeguridad0029 WSTecnicos0063 | K9: Bus Omnicanalidad Was Omnicanalidad | L9: ON-PREMISE | M9: 7 | N9: Alta | O9: REST - datapowerexterno SOAP | P9: 2 | Q9: Baja | R9: Ninguna | S9: 0 | T9: Baja | U9: Ninguna | W9: Baja | X9: 13.64K | Y9: 317ms | AB9: Baja | AC9: Si puede ser probado por las app | AD9: Baja | AE9: AREA MICROFINANZAS | AF9: https://serviciosexternos.pichincha.com:8445/BPMicrofinanzasProd/Servicios/Rest/FlexibleUpdateWorkOrder | AG9: Segun BDD: 00650 - Microfinanzas | AH9: 1 | AI9: Baja | AJ9: Ninguno | AK9: Baja | AL9: ConsultarProductosClientes01 | AM9: Baja | AN9: =IFERROR(SUM(CHOOSE(MATCH(N9,{"Baja";"Media";"Alta"},0),1,2,3), CHOOSE(MATCH(Q9,{"Baja";"Media";"Alta"},0),1,2,3), CHOOSE(MATCH(T9,{"Baja";"Media";"Alta"},0),1,2,3), CHOOSE(MATCH(W9,{"Baja";"Media";"Alta"},0),1,2,3), CHOOSE(MATCH(AB9,{"Baja";"Media";"Alta"},0),1,2,3), CHOOSE(MATCH(AD9,{"Baja";"Media";"Alta"},0),1,2,3), CHOOSE(MATCH(AI9,{"Baja";"Media";"Alta"},0),1,2,3), CHOOSE(MATCH(AK9,{"Baja";"Media";"Alta"},0),1,2,3), CHOOSE(MATCH(AM9,{"Baja";"Media";"Alta"},0),1,2,3)),0) -> 11 | AO9: =IF(AN9=0,"Pendiente",IF(AN9<=15,"Bajo",IF(AN9<=21,"Medio","Alto"))) -> Bajo | AR9: =VLOOKUP(A9,#REF!,2,FALSE) -> #REF! | AS9: https://s.icepanel.io/wJSECZOwwNkkW8/zJIi | AT9: https://dev.azure.com/BancoPichinchaEC/adi-especificaciones-tecnicas/_git/adi-doc-tecspec-tribu-integracion-apis?path=/sp%20-%20Soporte/tpr-msa-sp-orqclientes0017 | AU9: https://dev.azure.com/BancoPichinchaEC/tpl-bus-omnicanal/_git/sqb-msa-orqclientes0017 | AV9: 1 | AW9: https://pichincha.atlassian.net/browse/PCBG-588
A10: ORQClientes0019 | B10: =CONCATENATE(LOWER(E10),"-msa-sp-",LOWER(A10)) -> tnd-msa-sp-orqclientes0019 | C10: Consultar Datos Economicos Cliente | D10: TRIBU SEGMENTOS Y NEGOCIOS DIGITALES | E10: =VLOOKUP(D10,Tribus!$A$1:$B$33,2,FALSE) -> tnd | F10: Bus Omnicanalidad | G10: ORQ | H10: Completado | I10: A Desarrollo | J10: WSClientes0024 -> ConsultarIdentificacion01 WSClientes0038 -> OperacionEconomicosCliente52 WSClientes0071 -> AsignarInformacionBienes01 WSClientes0072 -> ActualizarDatosReferencias31 WSClientes0074 -> ActualizarDatosActividadEconomica31 | K10: Bus Omnicanalidad | L10: ON-PREMISE | M10: 5 | N10: Alta | O10: 8511 - SOAP | P10: 1 | Q10: Baja | R10: Ninguna | S10: 0 | T10: Baja | U10: Ninguna | W10: Baja | X10: 876 | Y10: 418ms | AB10: Baja | AC10: Si puede ser probado por las app | AD10: Baja | AE10: COE_TRANSFORMACION_PROCESOS | AF10: Ninguno | AG10: Default Web Site:443,8043 (/BPMPichincha) Default Web Site:443,8043 (/BPMPichinchaCH) Default Web Site:443,8043 (/BPMPichinchaCP) | AH10: 3 | AI10: Media | AJ10: Ninguno | AK10: Baja | AL10: ConsultarDatosEconomicosCliente01 | AM10: Baja | AN10: =IFERROR(SUM(CHOOSE(MATCH(N10,{"Baja";"Media";"Alta"},0),1,2,3), CHOOSE(MATCH(Q10,{"Baja";"Media";"Alta"},0),1,2,3), CHOOSE(MATCH(T10,{"Baja";"Media";"Alta"},0),1,2,3), CHOOSE(MATCH(W10,{"Baja";"Media";"Alta"},0),1,2,3), CHOOSE(MATCH(AB10,{"Baja";"Media";"Alta"},0),1,2,3), CHOOSE(MATCH(AD10,{"Baja";"Media";"Alta"},0),1,2,3), CHOOSE(MATCH(AI10,{"Baja";"Media";"Alta"},0),1,2,3), CHOOSE(MATCH(AK10,{"Baja";"Media";"Alta"},0),1,2,3), CHOOSE(MATCH(AM10,{"Baja";"Media";"Alta"},0),1,2,3)),0) -> 12 | AO10: =IF(AN10=0,"Pendiente",IF(AN10<=15,"Bajo",IF(AN10<=21,"Medio","Alto"))) -> Bajo | AR10: =VLOOKUP(A10,#REF!,2,FALSE) -> #REF! | AS10: https://app.icepanel.io/landscapes/w71QNHgfDvF79GrSuA3r/versions/latest/diagrams/editor?diagram=qXCLgnJ6TO&model=z8l3of38d7&overlay_tab=tags&x1=-642.7&y1=-192&x2=1666.7&y2=832 | AT10: https://dev.azure.com/BancoPichinchaEC/adi-especificaciones-tecnicas/_git/adi-doc-tecspec-tribu-integracion-apis?path=/sp%20-%20Soporte/tnd-msa-sp-orqclientes0019 | AU10: https://dev.azure.com/BancoPichinchaEC/tpl-bus-omnicanal/_git/sqb-msa-orqclientes0019 | AV10: 1 | AW10: https://pichincha.atlassian.net/browse/PCBG-589
A11: ORQClientes0022 | B11: =CONCATENATE(LOWER(E11),"-msa-sp-",LOWER(A11)) -> tnd-msa-sp-orqclientes0022 | C11: Consulta información de cliente con agencia virtual | D11: TRIBU SEGMENTOS Y NEGOCIOS DIGITALES | E11: =VLOOKUP(D11,Tribus!$A$1:$B$33,2,FALSE) -> tnd | F11: Bus Omnicanalidad | G11: ORQ | H11: Completado | I11: A Desarrollo | J11: WSClientes0046 --> ConsultarClienteVirtual01 | K11: Bus Omnicanalidad | L11: ON-PREMISE | M11: 1 | N11: Baja | O11: SOAP | P11: 1 | Q11: Baja | R11: Ninguna | S11: 0 | T11: Baja | U11: Ninguna | W11: Baja | X11: 49.4k | Y11: 163ms | AB11: Baja | AC11: Si puede ser probado por las app | AD11: Baja | AE11: AREA MICROFINANZAS | AF11: APIGee - cia-api-sp-ape-virtual-customers | AG11: Segun BDD: 00650 - Microfinanzas | AH11: 1 | AI11: Baja | AJ11: Ninguno | AK11: Baja | AL11: ConsultarInformacionClienteVirtual01 | AM11: Baja | AN11: =IFERROR(SUM(CHOOSE(MATCH(N11,{"Baja";"Media";"Alta"},0),1,2,3), CHOOSE(MATCH(Q11,{"Baja";"Media";"Alta"},0),1,2,3), CHOOSE(MATCH(T11,{"Baja";"Media";"Alta"},0),1,2,3), CHOOSE(MATCH(W11,{"Baja";"Media";"Alta"},0),1,2,3), CHOOSE(MATCH(AB11,{"Baja";"Media";"Alta"},0),1,2,3), CHOOSE(MATCH(AD11,{"Baja";"Media";"Alta"},0),1,2,3), CHOOSE(MATCH(AI11,{"Baja";"Media";"Alta"},0),1,2,3), CHOOSE(MATCH(AK11,{"Baja";"Media";"Alta"},0),1,2,3), CHOOSE(MATCH(AM11,{"Baja";"Media";"Alta"},0),1,2,3)),0) -> 9 | AO11: =IF(AN11=0,"Pendiente",IF(AN11<=15,"Bajo",IF(AN11<=21,"Medio","Alto"))) -> Bajo | AR11: =VLOOKUP(A11,#REF!,2,FALSE) -> #REF! | AS11: https://s.icepanel.io/wJSECZOwwNkkW8/oy6e | AT11: https://dev.azure.com/BancoPichinchaEC/adi-especificaciones-tecnicas/_git/adi-doc-tecspec-tribu-integracion-apis?path=/sp%20-%20Soporte/tnd-msa-sp-orqclientes0022 | AU11: sqb-msa-orqclientes0022 - Repos | AV11: 1 | AW11: https://pichincha.atlassian.net/browse/PCBG-590
A12: ORQClientes0023 | B12: =CONCATENATE(LOWER(E12),"-msa-sp-",LOWER(A12)) -> tpr-msa-sp-orqclientes0023 | C12: Consultar Creditos y Garantia | D12: TRIBU PRODUCTOS | E12: =VLOOKUP(D12,Tribus!$A$1:$B$33,2,FALSE) -> tpr | F12: Bus Omnicanalidad | G12: ORQ | H12: Completado | I12: A Desarrollo | J12: WSClientes0024 WSClientes0078 WSClientes0090 WSClientes0091 | K12: Bus Omnicanalidad Was Omnicanalidad | L12: ON-PREMISE | M12: 4 | N12: Alta | O12: 8511 - SOAP | P12: 1 | Q12: Baja | R12: Ninguna | S12: 0 | T12: Baja | U12: Ninguna | W12: Baja | X12: 896 | Y12: 375ms | AB12: Baja | AC12: Si puede ser probado por las app | AD12: Baja | AE12: COE_TRANSFORMACION_PROCESOS | AG12: Default Web Site:443,8043 (/BPMPichincha) Default Web Site:443,8043 (/BPMPichinchaCH) Default Web Site:443,8043 (/BPMPichinchaCP) Default Web Site:443,8043 (/BPMPichinchaAS) | AH12: 3 | AI12: Media | AJ12: Ninguno | AK12: Baja | AL12: ConsultarCreditosGarantia | AM12: Baja | AN12: =IFERROR(SUM(CHOOSE(MATCH(N12,{"Baja";"Media";"Alta"},0),1,2,3), CHOOSE(MATCH(Q12,{"Baja";"Media";"Alta"},0),1,2,3), CHOOSE(MATCH(T12,{"Baja";"Media";"Alta"},0),1,2,3), CHOOSE(MATCH(W12,{"Baja";"Media";"Alta"},0),1,2,3), CHOOSE(MATCH(AB12,{"Baja";"Media";"Alta"},0),1,2,3), CHOOSE(MATCH(AD12,{"Baja";"Media";"Alta"},0),1,2,3), CHOOSE(MATCH(AI12,{"Baja";"Media";"Alta"},0),1,2,3), CHOOSE(MATCH(AK12,{"Baja";"Media";"Alta"},0),1,2,3), CHOOSE(MATCH(AM12,{"Baja";"Media";"Alta"},0),1,2,3)),0) -> 12 | AO12: =IF(AN12=0,"Pendiente",IF(AN12<=15,"Bajo",IF(AN12<=21,"Medio","Alto"))) -> Bajo | AQ12: Considerar que consume el WSClientes0090 que no estuvo contemplado en la ola 1 | AR12: =VLOOKUP(A12,#REF!,2,FALSE) -> #REF! | AS12: https://s.icepanel.io/wJSECZOwwNkkW8/CUjN | AT12: https://dev.azure.com/BancoPichinchaEC/adi-especificaciones-tecnicas/_git/adi-doc-tecspec-tribu-integracion-apis?version=GBmaster&path=/sp%20-%20Soporte/tpr-msa-sp-orqclientes0023 | AU12: https://dev.azure.com/BancoPichinchaEC/tpl-bus-omnicanal/_git/sqb-msa-orqclientes0023 | AV12: 1 | AW12: https://pichincha.atlassian.net/browse/PCBG-591
A13: ORQClientes0024 | B13: =CONCATENATE(LOWER(E13),"-msa-sp-",LOWER(A13)) -> tpr-msa-sp-orqclientes0024 | C13: Consultar Cuentas e Inversiones del Cliente | D13: TRIBU PRODUCTOS | E13: =VLOOKUP(D13,Tribus!$A$1:$B$33,2,FALSE) -> tpr | F13: Bus Omnicanalidad | G13: ORQ | H13: Completado | I13: A Desarrollo | J13: WSClientes0075 -> ConsultarSaldosCuenta01 WSClientes0081 -> ConsultarCuentasFirmaAutorizada01 WSClientes0082 -> ConsultarCuentasTipoEstado01 WSProductos0016 -> ConsultarCotitularesCuenta02 | K13: Bus Omnicanalidad | L13: ON-PREMISE | M13: 4 | N13: Alta | O13: 8937 - REST 8511 - SOAP | P13: 2 | Q13: Media | R13: Ninguna | S13: 0 | T13: Baja | U13: Ninguna | W13: Baja | X13: 10.26K | Y13: 227ms | AB13: Baja | AC13: Si puede ser probado por las app | AD13: Baja | AE13: COE_TRANSFORMACION_PROCESOS | AF13: 0 | AG13: Default Web Site:443,8043 (/BPMPichincha) Default Web Site:443,8043 (/BPMPichinchaCH) Default Web Site:443,8043 (/BPMPichinchaCP) Segun BDD: Bizagi: 00657 | AH13: 4 | AI13: Alta | AJ13: ninguno | AK13: Baja | AL13: ConsultarCuentasInversionesCliente01 | AM13: Baja | AN13: =IFERROR(SUM(CHOOSE(MATCH(N13,{"Baja";"Media";"Alta"},0),1,2,3), CHOOSE(MATCH(Q13,{"Baja";"Media";"Alta"},0),1,2,3), CHOOSE(MATCH(T13,{"Baja";"Media";"Alta"},0),1,2,3), CHOOSE(MATCH(W13,{"Baja";"Media";"Alta"},0),1,2,3), CHOOSE(MATCH(AB13,{"Baja";"Media";"Alta"},0),1,2,3), CHOOSE(MATCH(AD13,{"Baja";"Media";"Alta"},0),1,2,3), CHOOSE(MATCH(AI13,{"Baja";"Media";"Alta"},0),1,2,3), CHOOSE(MATCH(AK13,{"Baja";"Media";"Alta"},0),1,2,3), CHOOSE(MATCH(AM13,{"Baja";"Media";"Alta"},0),1,2,3)),0) -> 14 | AO13: =IF(AN13=0,"Pendiente",IF(AN13<=15,"Bajo",IF(AN13<=21,"Medio","Alto"))) -> Bajo | AR13: =VLOOKUP(A13,#REF!,2,FALSE) -> #REF! | AS13: https://s.icepanel.io/wJSECZOwwNkkW8/kzAK | AT13: https://dev.azure.com/BancoPichinchaEC/adi-especificaciones-tecnicas/_git/adi-doc-tecspec-tribu-integracion-apis?path=/sp%20-%20Soporte/tpr-msa-sp-orqclientes0024 | AU13: https://dev.azure.com/BancoPichinchaEC/tpl-bus-omnicanal/_git/sqb-msa-orqclientes0024 | AV13: 1 | AW13: https://pichincha.atlassian.net/browse/PCBG-592
A14: ORQClientes0025 | B14: =CONCATENATE(LOWER(E14),"-msa-sp-",LOWER(A14)) -> tpr-msa-sp-orqclientes0025 | C14: Consultar Cheques Protestados del Cliente | D14: TRIBU PRODUCTOS | E14: =VLOOKUP(D14,Tribus!$A$1:$B$33,2,FALSE) -> tpr | F14: Bus Omnicanalidad | G14: ORQ | H14: Completado | I14: A Desarrollo | J14: ORQClientes0025 WSClientes0001 (ConsultarCuentasActivas01) -> UMPProductos0049 (ConsultarPosicionConsolidadaCliente01) -> TX060450 UMPProductos0001 (ConsultarCuentas01) -> TX060453 / 060452 UMPProductos0066 (ConsultarFirmaUnicaIndependiente01) -> TX064014 WSClientes0082 (ConsultarCuentasTipoEstado01) -> UMPProductos0021 (ConsultarCuentas21) -> Consulta de Cuentas del cliente en Bancs TX060453 -> TX060452 -> TX de consulta cuentas en Bancs WSClientes0025 (ConsultarInformacionChequeProtestado01) -> UMPClientes0010 (ConsultarInformacionChequeProtestado01)-> TX051059 | K14: Bus Omnicanalidad | L14: ON-PREMISE | M14: 3 | N14: Media | O14: 8511 - SOAP | Q14: Baja | R14: Ninguna | S14: 0 | T14: Baja | U14: Ninguna | W14: Baja | X14: 13.3K | Y14: 530 ms | AB14: Baja | AC14: Si puede ser probado por las app | AD14: Baja | AE14: COE_TRANSFORMACION_PROCESOS TRIBU ADMINISTRACION DE CREDITO | AF14: deployment-fda-msa-dm-orqclientes*-*; ORQClientes0067.API | AG14: Default Web Site:443,8043 (/BPMPichincha) Default Web Site:443,8043 (/BPMPichinchaCH) Default Web Site:443,8043 (/BPMPichinchaCP) | AI14: Baja | AJ14: Ninguno | AK14: Baja | AL14: ConsultarChequesProtestadosCliente01 | AM14: Baja | AN14: =IFERROR(SUM(CHOOSE(MATCH(N14,{"Baja";"Media";"Alta"},0),1,2,3), CHOOSE(MATCH(Q14,{"Baja";"Media";"Alta"},0),1,2,3), CHOOSE(MATCH(T14,{"Baja";"Media";"Alta"},0),1,2,3), CHOOSE(MATCH(W14,{"Baja";"Media";"Alta"},0),1,2,3), CHOOSE(MATCH(AB14,{"Baja";"Media";"Alta"},0),1,2,3), CHOOSE(MATCH(AD14,{"Baja";"Media";"Alta"},0),1,2,3), CHOOSE(MATCH(AI14,{"Baja";"Media";"Alta"},0),1,2,3), CHOOSE(MATCH(AK14,{"Baja";"Media";"Alta"},0),1,2,3), CHOOSE(MATCH(AM14,{"Baja";"Media";"Alta"},0),1,2,3)),0) -> 10 | AO14: =IF(AN14=0,"Pendiente",IF(AN14<=15,"Bajo",IF(AN14<=21,"Medio","Alto"))) -> Bajo | AR14: =VLOOKUP(A14,#REF!,2,FALSE) -> #REF! | AS14: https://app.icepanel.io/landscapes/w71QNHgfDvF79GrSuA3r/versions/latest/diagrams/editor?diagram=5SlzCdmf2o&model=052757cjuefp&overlay_tab=tags&x1=-301.6&y1=-192&x2=1697.6&y2=832 | AT14: https://dev.azure.com/BancoPichinchaEC/adi-especificaciones-tecnicas/_git/adi-doc-tecspec-tribu-integracion-apis?path=/sp%20-%20Soporte/tpr-msa-sp-orqclientes0025 | AU14: https://dev.azure.com/BancoPichinchaEC/tpl-bus-omnicanal/_git/sqb-msa-orqclientes0025 | AV14: 1 | AW14: https://pichincha.atlassian.net/browse/PCBG-593
A15: ORQClientes0026 | B15: =CONCATENATE(LOWER(E15),"-msa-sp-",LOWER(A15)) -> tpr-msa-sp-orqclientes0026 | C15: Consulta de Creditos, Debitos y Cuentas Activas del Cliente | D15: TRIBU PRODUCTOS | E15: =VLOOKUP(D15,Tribus!$A$1:$B$33,2,FALSE) -> tpr | F15: Bus Omnicanalidad | G15: ORQ | H15: Completado | I15: A Desarrollo | J15: WSClientes0082 WSProductos0130 | K15: Bus Omnicanalidad | L15: ON-PREMISE | M15: 2 | N15: Media | O15: SOAP 8511 - SOAP | P15: 1 | Q15: Baja | R15: Ninguna | S15: 0 | T15: Baja | U15: Ninguna | W15: Baja | X15: 516 | Y15: 559ms | AB15: Baja | AC15: Si puede ser probado por las app | AD15: Baja | AE15: COE_TRANSFORMACION_PROCESOS | AG15: Default Web Site:443,8043 (/BPMPichincha) Default Web Site:443,8043 (/BPMPichinchaCH) Default Web Site:443,8043 (/BPMPichinchaCP) | AH15: 3 | AI15: Media | AJ15: Ninguno | AK15: Baja | AL15: ConsultaCreditosDebitosCuentasActivasCliente01 | AM15: Baja | AN15: =IFERROR(SUM(CHOOSE(MATCH(N15,{"Baja";"Media";"Alta"},0),1,2,3), CHOOSE(MATCH(Q15,{"Baja";"Media";"Alta"},0),1,2,3), CHOOSE(MATCH(T15,{"Baja";"Media";"Alta"},0),1,2,3), CHOOSE(MATCH(W15,{"Baja";"Media";"Alta"},0),1,2,3), CHOOSE(MATCH(AB15,{"Baja";"Media";"Alta"},0),1,2,3), CHOOSE(MATCH(AD15,{"Baja";"Media";"Alta"},0),1,2,3), CHOOSE(MATCH(AI15,{"Baja";"Media";"Alta"},0),1,2,3), CHOOSE(MATCH(AK15,{"Baja";"Media";"Alta"},0),1,2,3), CHOOSE(MATCH(AM15,{"Baja";"Media";"Alta"},0),1,2,3)),0) -> 11 | AO15: =IF(AN15=0,"Pendiente",IF(AN15<=15,"Bajo",IF(AN15<=21,"Medio","Alto"))) -> Bajo | AR15: =VLOOKUP(A15,#REF!,2,FALSE) -> #REF! | AS15: https://s.icepanel.io/wJSECZOwwNkkW8/r3I4 | AT15: https://dev.azure.com/BancoPichinchaEC/adi-especificaciones-tecnicas/_git/adi-doc-tecspec-tribu-integracion-apis?path=/sp%20-%20Soporte/tpr-msa-sp-orqclientes0026 | AU15: https://dev.azure.com/BancoPichinchaEC/tpl-bus-omnicanal/_git/sqb-msa-orqclientes0026 | AV15: 1 | AW15: https://pichincha.atlassian.net/browse/PCBG-594
A16: ORQClientes0027 | B16: =CONCATENATE(LOWER(E16),"-msa-sp-",LOWER(A16)) -> tmp-msa-sp-orqclientes0027 | C16: Consulta tarjetas de Credito BP | D16: TRIBU MEDIOS DE PAGO | E16: =VLOOKUP(D16,Tribus!$A$1:$B$33,2,FALSE) -> tmp | F16: Bus Omnicanalidad | G16: ORQ | H16: Completado | I16: A Desarrollo | J16: WSClientes0023 -> ConsultarTarjetasCreditoBP01 WSClientes0076 -> ConsultarDiasMoraTarjeta01 | K16: Bus Omnicanalidad | L16: ON-PREMISE | M16: 1 | N16: Baja | O16: 8511 - SOAP | P16: 1 | Q16: Baja | R16: Ninguna | S16: 0 | T16: Baja | U16: Ninguna | W16: Baja | X16: 862 | Y16: 99.3ms | AB16: Baja | AC16: Si puede ser probado por las app | AD16: Baja | AE16: COE_TRANSFORMACION_PROCESOS | AF16: Ninguno | AG16: Default Web Site:443,8043 (/BPMPichincha) Default Web Site:443,8043 (/BPMPichinchaCH) Default Web Site:443,8043 (/BPMPichinchaCP) | AH16: 3 | AI16: Media | AJ16: Ninguno | AK16: Baja | AL16: ConsultarTarjetasCreditoBP01 | AM16: Baja | AN16: =IFERROR(SUM(CHOOSE(MATCH(N16,{"Baja";"Media";"Alta"},0),1,2,3), CHOOSE(MATCH(Q16,{"Baja";"Media";"Alta"},0),1,2,3), CHOOSE(MATCH(T16,{"Baja";"Media";"Alta"},0),1,2,3), CHOOSE(MATCH(W16,{"Baja";"Media";"Alta"},0),1,2,3), CHOOSE(MATCH(AB16,{"Baja";"Media";"Alta"},0),1,2,3), CHOOSE(MATCH(AD16,{"Baja";"Media";"Alta"},0),1,2,3), CHOOSE(MATCH(AI16,{"Baja";"Media";"Alta"},0),1,2,3), CHOOSE(MATCH(AK16,{"Baja";"Media";"Alta"},0),1,2,3), CHOOSE(MATCH(AM16,{"Baja";"Media";"Alta"},0),1,2,3)),0) -> 10 | AO16: =IF(AN16=0,"Pendiente",IF(AN16<=15,"Bajo",IF(AN16<=21,"Medio","Alto"))) -> Bajo | AR16: =VLOOKUP(A16,#REF!,2,FALSE) -> #REF! | AS16: https://app.icepanel.io/landscapes/w71QNHgfDvF79GrSuA3r/versions/latest/diagrams/editor?diagram=xs1LYUUDwU&model=g103dyijmna&overlay_tab=tags&x1=-642.7&y1=-192&x2=1666.7&y2=832 | AT16: https://dev.azure.com/BancoPichinchaEC/adi-especificaciones-tecnicas/_git/adi-doc-tecspec-tribu-integracion-apis?version=GBmaster&path=/sp%20-%20Soporte/tmp-msa-sp-orqclientes0027 | AU16: https://dev.azure.com/BancoPichinchaEC/tpl-bus-omnicanal/_git/sqb-msa-orqclientes0027 | AV16: 1 | AW16: https://pichincha.atlassian.net/browse/PCBG-595
A17: ORQClientes0028 | B17: =CONCATENATE(LOWER(E17),"-msa-sp-",LOWER(A17)) -> tnd-msa-sp-orqclientes0028 | C17: Cancelar Actualizacion de Datos Delay | D17: TRIBU SEGMENTOS Y NEGOCIOS DIGITALES | E17: =VLOOKUP(D17,Tribus!$A$1:$B$33,2,FALSE) -> tnd | F17: Bus Omnicanalidad | G17: ORQ | H17: Completado | I17: A Desarrollo | J17: WSTecnicos0035 WSTecnicos0036 CE_EVENTOS | K17: Was Omnicanalidad | L17: ON-PREMISE | M17: 2 | N17: Media | O17: Rest desde datapower externo Soap - propio del servicio | P17: 2 | Q17: Media | R17: 0 | S17: 0 | T17: Baja | U17: Ninguna | W17: Baja | X17: 4 | Y17: 68ms | AB17: Baja | AC17: Si puede ser probado por las app | AD17: Baja | AE17: COE_TRANSFORMACION_PROCESOS TRIBU SEGMENTOS Y NEGOCIOS DIGITALES | AF17: datapower externo - WSAP117401007 | AG17: Bizagi Segun BDD: 00344 - CRM Gestión Comercial (Salesforce) | AH17: 2 | AI17: Media | AJ17: Ninguno | AK17: Baja | AL17: CancelarActualizacionDatosDelay31 | AM17: Baja | AN17: =IFERROR(SUM(CHOOSE(MATCH(N17,{"Baja";"Media";"Alta"},0),1,2,3), CHOOSE(MATCH(Q17,{"Baja";"Media";"Alta"},0),1,2,3), CHOOSE(MATCH(T17,{"Baja";"Media";"Alta"},0),1,2,3), CHOOSE(MATCH(W17,{"Baja";"Media";"Alta"},0),1,2,3), CHOOSE(MATCH(AB17,{"Baja";"Media";"Alta"},0),1,2,3), CHOOSE(MATCH(AD17,{"Baja";"Media";"Alta"},0),1,2,3), CHOOSE(MATCH(AI17,{"Baja";"Media";"Alta"},0),1,2,3), CHOOSE(MATCH(AK17,{"Baja";"Media";"Alta"},0),1,2,3), CHOOSE(MATCH(AM17,{"Baja";"Media";"Alta"},0),1,2,3)),0) -> 12 | AO17: =IF(AN17=0,"Pendiente",IF(AN17<=15,"Bajo",IF(AN17<=21,"Medio","Alto"))) -> Bajo | AQ17: RITM0738122 / RITM0745618 | AR17: =VLOOKUP(A17,#REF!,2,FALSE) -> #REF! | AS17: https://s.icepanel.io/wJSECZOwwNkkW8/sDBV | AT17: https://dev.azure.com/BancoPichinchaEC/adi-especificaciones-tecnicas/_git/adi-doc-tecspec-tribu-integracion-apis?version=GBmaster&path=/sp%20-%20Soporte/tnd-msa-sp-orqclientes0028 | AU17: https://dev.azure.com/BancoPichinchaEC/tpl-bus-omnicanal/_git/sqb-msa-orqclientes0028 | AV17: 1 | AW17: https://pichincha.atlassian.net/browse/PCBG-596
A18: ORQClientes0029 | B18: =CONCATENATE(LOWER(E18),"-msa-sp-",LOWER(A18)) -> tnd-msa-sp-orqclientes0029 | C18: Consulta datos basicos del Cliente | D18: TRIBU SEGMENTOS Y NEGOCIOS DIGITALES | E18: =VLOOKUP(D18,Tribus!$A$1:$B$33,2,FALSE) -> tnd | F18: Bus Omnicanalidad | G18: ORQ | H18: Completado | I18: A Desarrollo | J18: WSClientes0024 → ConsultarIdentificacion01 (destino: IIB) WSClientes0077 → ConsultarDatoBasicoCliente01 (destino: IIB) WSClientes0078 → consultarClienteSAR01 (destino: IIB) WSClientes0011 → ConsultarDatosIdentificacionCliente01 (destino: IIB) WSClientes0012 → ConsultarDatoDemograficoCliente01 (destino: IIB) WSClientes0013 → ConsultarDatosLocalizacionCliente01 (destino: IIB) WSClientes0007 → ConsultarContactoTransaccional01 (destino: IIB) | K18: Bus Omnicanalidad | L18: ON-PREMISE | M18: 7 | N18: Alta | O18: SOAP 8511 - SOAP | P18: 1 | Q18: Baja | R18: NO | S18: 0 | T18: Baja | U18: Ninguna | W18: Baja | X18: 1164 | Y18: 890ms | AB18: Baja | AC18: Si puede ser probado por las app | AD18: Baja | AE18: COE_TRANSFORMACION_PROCESOS | AG18: Default Web Site:443,8043 (/BPMPichincha) Default Web Site:443,8043 (/BPMPichinchaCH) Default Web Site:443,8043 (/BPMPichinchaCP) Default Web Site:443,8043 (/BPMPichinchaAS) | AH18: 4 | AI18: Media | AJ18: NO | AK18: Baja | AL18: ConsultarDatosCliente01 | AM18: Baja | AN18: =IFERROR(SUM(CHOOSE(MATCH(N18,{"Baja";"Media";"Alta"},0),1,2,3), CHOOSE(MATCH(Q18,{"Baja";"Media";"Alta"},0),1,2,3), CHOOSE(MATCH(T18,{"Baja";"Media";"Alta"},0),1,2,3), CHOOSE(MATCH(W18,{"Baja";"Media";"Alta"},0),1,2,3), CHOOSE(MATCH(AB18,{"Baja";"Media";"Alta"},0),1,2,3), CHOOSE(MATCH(AD18,{"Baja";"Media";"Alta"},0),1,2,3), CHOOSE(MATCH(AI18,{"Baja";"Media";"Alta"},0),1,2,3), CHOOSE(MATCH(AK18,{"Baja";"Media";"Alta"},0),1,2,3), CHOOSE(MATCH(AM18,{"Baja";"Media";"Alta"},0),1,2,3)),0) -> 12 | AO18: =IF(AN18=0,"Pendiente",IF(AN18<=15,"Bajo",IF(AN18<=21,"Medio","Alto"))) -> Bajo | AR18: =VLOOKUP(A18,#REF!,2,FALSE) -> #REF! | AS18: https://s.icepanel.io/wJSECZOwwNkkW8/sZlg | AT18: https://dev.azure.com/BancoPichinchaEC/adi-especificaciones-tecnicas/_git/adi-doc-tecspec-tribu-integracion-apis?version=GBmaster&path=/sp%20-%20Soporte/tnd-msa-sp-orqclientes0029 | AU18: https://dev.azure.com/BancoPichinchaEC/tpl-bus-omnicanal/_git/sqb-msa-orqclientes0029 | AV18: 1 | AW18: https://pichincha.atlassian.net/browse/PCBG-597
A19: ORQClientes0035 | B19: =CONCATENATE(LOWER(E19),"-msa-sp-",LOWER(A19)) -> tnd-msa-sp-orqclientes0035 | C19: Orquestar los web service para creacion del cliente | D19: TRIBU SEGMENTOS Y NEGOCIOS DIGITALES | E19: =VLOOKUP(D19,Tribus!$A$1:$B$33,2,FALSE) -> tnd | F19: Bus Omnicanalidad | G19: ORQ | H19: Completado | I19: A Desarrollo | J19: WSClientes0024 -< ConsultarIdentificacion01 WSClientes0038 -> OperacionEconomicosCliente52 WSClientes0055 -> OperacionActividadEconomicaCliente51 WSClientes0060 -> OperacionDatosComplementariosCliente51 (opc1/ops2/opc3) WSClientes0061-> OperacionDemograficosCliente51 WSClientes0062 -> OperacionIdentificacionCliente51 WSClientes0063 -> OperacionReferenciasCliente51 WSClientes0096 -> CrearProspecto21 WSClientes0098 -> transmisionClienteSFI01 WSClientes0099 -> OperacionLocalizacion51 WSClientes0101 -> OperacionRelacionesCliente51 WSClientes0102 -> SegmentacionEntradaFija01 WSTecnicos0076 -> crearLogModificaciones21 WSTecnicos0063 -> obtenerCatalogosSigloBancs01 | K19: Bus Omnicanalidad Was Omnicanalidad | L19: ON-PREMISE | M19: 14 | N19: Alta | O19: REST - datapowerexterno SOAP | P19: 2 | Q19: Media | R19: Ninguna | S19: 0 | T19: Baja | U19: Catalogo de sector economico, consume WSTecnicos0063 | V19: WSTecnicos0063 | W19: Media | X19: 64 | Y19: 2.26s | AB19: Baja | AC19: Si puede ser probado por las app | AD19: Baja | AE19: TRIBU CANALES TRIBU PRODUCTOS AREA MICROFINANZAS | AF19: 0 | AG19: Servicios_Consumidos_Vinculacion_Integral Segun BDD: 00650 - Microfinanzas Movilidad app movil 00662 - Referidos | AH19: 3 | AI19: Media | AJ19: ninguno | AK19: Baja | AL19: CreacionCliente21 | AM19: Baja | AN19: =IFERROR(SUM(CHOOSE(MATCH(N19,{"Baja";"Media";"Alta"},0),1,2,3), CHOOSE(MATCH(Q19,{"Baja";"Media";"Alta"},0),1,2,3), CHOOSE(MATCH(T19,{"Baja";"Media";"Alta"},0),1,2,3), CHOOSE(MATCH(W19,{"Baja";"Media";"Alta"},0),1,2,3), CHOOSE(MATCH(AB19,{"Baja";"Media";"Alta"},0),1,2,3), CHOOSE(MATCH(AD19,{"Baja";"Media";"Alta"},0),1,2,3), CHOOSE(MATCH(AI19,{"Baja";"Media";"Alta"},0),1,2,3), CHOOSE(MATCH(AK19,{"Baja";"Media";"Alta"},0),1,2,3), CHOOSE(MATCH(AM19,{"Baja";"Media";"Alta"},0),1,2,3)),0) -> 14 | AO19: =IF(AN19=0,"Pendiente",IF(AN19<=15,"Bajo",IF(AN19<=21,"Medio","Alto"))) -> Bajo | AR19: =VLOOKUP(A19,#REF!,2,FALSE) -> #REF! | AS19: https://s.icepanel.io/wJSECZOwwNkkW8/NQF9 | AT19: https://dev.azure.com/BancoPichinchaEC/adi-especificaciones-tecnicas/_git/adi-doc-tecspec-tribu-integracion-apis?version=GBmaster&path=/sp%20-%20Soporte/tnd-msa-sp-orqclientes0035 | AU19: https://dev.azure.com/BancoPichinchaEC/tpl-bus-omnicanal/_git/sqb-msa-orqclientes0035 | AV19: 1 | AW19: https://pichincha.atlassian.net/browse/PCBG-598
A20: ORQClientes0036 | B20: =CONCATENATE(LOWER(E20),"-msa-sp-",LOWER(A20)) -> tnd-msa-sp-orqclientes0036 | C20: Consumir la WS para actualizacion del cliente | D20: TRIBU SEGMENTOS Y NEGOCIOS DIGITALES | E20: =VLOOKUP(D20,Tribus!$A$1:$B$33,2,FALSE) -> tnd | F20: Bus Omnicanalidad | G20: ORQ | H20: Completado | I20: A Desarrollo | J20: ORQClientes0036 WSClientes0061 (OperacionDemograficosCliente51) -> UMPClientes0077 (OperacionDemograficosCliente51) -> TX061406 WSClientes0103 (ActualizarInformacionCliente31) -> umpclientes0102 (Actualizacion del cliente en bancs) -> TX067510 (Procedimiento que realiza la operacion de actualizacion del cliente) WSClientes0098 (transmisionClienteSFI01) -> UMPClientes0100 (TransmisionClienteSFI) -> BDD: CREDIFE, SP: CFE_TRANSMISIONCLIENTESS1_MVL WSTecnicos0063 (obtenerCatalogosSigloBancs01) -> umptecnicos0066 (Consulta de catalogos a BANCS , CREDIFE y S21) -> jndi.sfi p11431BDD CREDIFE, jndi.catalogo.bancs p1521 BDD p012band_taf, jndi.catalogo.sigloBDD SRVPPRD WSClientes0038 (ConsultarDetalleAdicionalesCliente01) -> UMPClientes0020 (ConsultaInformacionCliente01) -> TX067050 (opc 1, 5, 15, 21) UMPClientes0061 (ActualizarInfAdicionalCliente31) -> TX067118 UMPClientes0057 (ActualizarInformacionCliente31) -> TX067116 WSClientes0101 (OperacionRelacionesCliente51) -> UMPClientes0076 (OperacionInformacionComplementariaRelaciones51) -> TX067151 (Consultar informacion complementaria de referencia del cliente) WSTecnicos0076 (crearLogModificaciones21) -> umptecnicos0098 (CrearLogModificacionesDao) -> Esquema: portal -> jndi.bancs.clientes | K20: Bus Omnicanalidad Was Omnicanalidad | L20: ON-PREMISE | M20: 6 | N20: Alta | O20: REST SOAP | P20: 2 | Q20: Media | R20: Ninguna | S20: 0 | T20: Baja | U20: Almacena información de backend en cache, consume WSTecnicos0063 | V20: WSTecnicos0063 | W20: Media | X20: 2.84K | Y20: 1.34s | AB20: Baja | AC20: Si puede ser probado por las app | AD20: Baja | AE20: AREA MICROFINANZAS TRIBU CANALES | AF20: Ninguno | AG20: Servicios_Consumidos_Vinculacion_Integral Segun BDD: 00650 - Microfinanzas Movilidad app movil 00662 - Referidos | AH20: 3 | AI20: Baja | AJ20: Ninguno | AK20: Baja | AL20: ActualizacionCliente31 | AM20: Baja | AN20: =IFERROR(SUM(CHOOSE(MATCH(N20,{"Baja";"Media";"Alta"},0),1,2,3), CHOOSE(MATCH(Q20,{"Baja";"Media";"Alta"},0),1,2,3), CHOOSE(MATCH(T20,{"Baja";"Media";"Alta"},0),1,2,3), CHOOSE(MATCH(W20,{"Baja";"Media";"Alta"},0),1,2,3), CHOOSE(MATCH(AB20,{"Baja";"Media";"Alta"},0),1,2,3), CHOOSE(MATCH(AD20,{"Baja";"Media";"Alta"},0),1,2,3), CHOOSE(MATCH(AI20,{"Baja";"Media";"Alta"},0),1,2,3), CHOOSE(MATCH(AK20,{"Baja";"Media";"Alta"},0),1,2,3), CHOOSE(MATCH(AM20,{"Baja";"Media";"Alta"},0),1,2,3)),0) -> 13 | AO20: =IF(AN20=0,"Pendiente",IF(AN20<=15,"Bajo",IF(AN20<=21,"Medio","Alto"))) -> Bajo | AR20: =VLOOKUP(A20,#REF!,2,FALSE) -> #REF! | AS20: https://app.icepanel.io/landscapes/w71QNHgfDvF79GrSuA3r/versions/latest/diagrams/editor?diagram=0xsCJ6T9F7&model=9JNMa0g1gL&overlay_tab=tags&x1=-301.6&y1=-192&x2=1697.6&y2=832 | AT20: https://dev.azure.com/BancoPichinchaEC/adi-especificaciones-tecnicas/_git/adi-doc-tecspec-tribu-integracion-apis?version=GBmaster&path=/sp%20-%20Soporte/tnd-msa-sp-orqclientes0036 | AU20: https://dev.azure.com/BancoPichinchaEC/tpl-bus-omnicanal/_git/sqb-msa-orqclientes0036 | AV20: 1 | AW20: https://pichincha.atlassian.net/browse/PCBG-599
A21: ORQClientes0037 | B21: =CONCATENATE(LOWER(E21),"-msa-sp-",LOWER(A21)) -> tnd-msa-sp-orqclientes0037 | C21: Consulta las preferencias de notificaciones de un cliente cuando crea el usuario por banca web. | D21: TRIBU SEGMENTOS Y NEGOCIOS DIGITALES | E21: =VLOOKUP(D21,Tribus!$A$1:$B$33,2,FALSE) -> tnd | F21: Bus Omnicanalidad | G21: ORQ | H21: Completado | I21: A Desarrollo | J21: WSClientes0006(ConsultarInformacionBasica01) WSClientes0007(ConsultarContactoTransaccional0) WSClientes0010(consultarGrupoClaveDigital01) WSClientes0024(ConsultarIdentificacion01) WSClientes0026(consultar02) → srvppomnica WSClientes0030(ConsultarContactoNotificacion01) WSTecnicos0039(consultarNotificacion01) → srvppomnica WSSeguridad0067(consultarDispositivosDetectId01) CE_EVENTOS | K21: BUS OMNICANAL WAS OMNICANAL | L21: ON-PREMISE | M21: 2 | N21: Media | O21: SOAP | P21: 1 | Q21: Baja | R21: Ninguna | S21: 0 | T21: Baja | U21: Ninguna | V21: No aplica | W21: Baja | X21: 3.03k | Y21: 373 ms | AB21: Baja | AC21: Si puede ser probado por las app | AD21: Baja | AE21: TRIBU CANALES | AF21: CANALES | AG21: NO aplica | AH21: 1 | AI21: Baja | AJ21: 0 | AK21: Baja | AL21: ConsultarPreferenciaNotificacionCliente01 | AM21: Baja | AN21: =IFERROR(SUM(CHOOSE(MATCH(N21,{"Baja";"Media";"Alta"},0),1,2,3), CHOOSE(MATCH(Q21,{"Baja";"Media";"Alta"},0),1,2,3), CHOOSE(MATCH(T21,{"Baja";"Media";"Alta"},0),1,2,3), CHOOSE(MATCH(W21,{"Baja";"Media";"Alta"},0),1,2,3), CHOOSE(MATCH(AB21,{"Baja";"Media";"Alta"},0),1,2,3), CHOOSE(MATCH(AD21,{"Baja";"Media";"Alta"},0),1,2,3), CHOOSE(MATCH(AI21,{"Baja";"Media";"Alta"},0),1,2,3), CHOOSE(MATCH(AK21,{"Baja";"Media";"Alta"},0),1,2,3), CHOOSE(MATCH(AM21,{"Baja";"Media";"Alta"},0),1,2,3)),0) -> 10 | AO21: =IF(AN21=0,"Pendiente",IF(AN21<=15,"Bajo",IF(AN21<=21,"Medio","Alto"))) -> Bajo | AR21: =VLOOKUP(A21,#REF!,2,FALSE) -> #REF! | AS21: ORQClientes0037 Component Diagram | Banco Pichincha C.A. landscape | IcePanel App | AT21: https://dev.azure.com/BancoPichinchaEC/adi-especificaciones-tecnicas/_git/adi-doc-tecspec-tribu-integracion-apis?version=GBmaster&path=/sp%20-%20Soporte/tnd-msa-sp-orqclientes0037 | AU21: https://BancoPichinchaEC@dev.azure.com/BancoPichinchaEC/tpl-bus-omnicanal/_git/sqb-msa-orqclientes0037 | AV21: 1 | AW21: https://pichincha.atlassian.net/browse/PCBG-600
A22: ORQClientes0038 | B22: =CONCATENATE(LOWER(E22),"-msa-sp-",LOWER(A22)) -> tnd-msa-sp-orqclientes0038 | C22: Servicio para crear y actualizar cliente PRY_CENTRO_DIGITAL | D22: TRIBU SEGMENTOS Y NEGOCIOS DIGITALES | E22: =VLOOKUP(D22,Tribus!$A$1:$B$33,2,FALSE) -> tnd | F22: Bus Omnicanalidad | G22: ORQ | H22: Completado | I22: A Desarrollo | J22: WSClientes0104 -> crearProspectoCliente21 -> TX062001 WSClientes0108 -> crearCliente24 WSClientes0029 -> ActualizarDatosDemograficos31 WSClientes0060 -> OperacionDatosComplementariosCliente51 WSClientes0101 -> OperacionRelacionesCliente51 WSClientes0099 -> OperacionLocalizacion51 WSClientes0072 -> ActualizarDatosReferencias31 WSClientes0020 -> ActualizarContactoTransaccional31 WSClientes0038 -> OperacionEconomicosCliente53 WSClientes0055 -> OperacionActividadEconomicaCliente52 WSClientes0154 -> consultarOficialHomologado01 WSTecnicos0076 -> crearLogModificaciones21 | K22: BUS OMNICANAL WAS OMNICANAL | L22: ON-PREMISE | M22: 12 | N22: Alta | O22: SOAP - 8934 | P22: 1 | Q22: Baja | R22: Ninguna | S22: 0 | T22: Baja | U22: Ninguna | W22: Baja | X22: 3.02K | Y22: 1.87s | AB22: Baja | AC22: Si puede ser probado por las app | AD22: Baja | AE22: TRIBU PRODUCTOS | AF22: WSClientes0020 WSClientes0029 WSClientes0038 WSClientes0055 WSClientes0060 WSClientes0072 WSClientes0099 WSClientes0101 WSClientes0104 WSClientes0108 WSClientes0154Service.WSClientes0154Port WSTecnicos0076Request.WSTecnicos0076Port | AH22: 12 | AI22: Alta | AJ22: Ninguna | AK22: Baja | AL22: CrearCliente0038 | AM22: Baja | AN22: =IFERROR(SUM(CHOOSE(MATCH(N22,{"Baja";"Media";"Alta"},0),1,2,3), CHOOSE(MATCH(Q22,{"Baja";"Media";"Alta"},0),1,2,3), CHOOSE(MATCH(T22,{"Baja";"Media";"Alta"},0),1,2,3), CHOOSE(MATCH(W22,{"Baja";"Media";"Alta"},0),1,2,3), CHOOSE(MATCH(AB22,{"Baja";"Media";"Alta"},0),1,2,3), CHOOSE(MATCH(AD22,{"Baja";"Media";"Alta"},0),1,2,3), CHOOSE(MATCH(AI22,{"Baja";"Media";"Alta"},0),1,2,3), CHOOSE(MATCH(AK22,{"Baja";"Media";"Alta"},0),1,2,3), CHOOSE(MATCH(AM22,{"Baja";"Media";"Alta"},0),1,2,3)),0) -> 13 | AO22: =IF(AN22=0,"Pendiente",IF(AN22<=15,"Bajo",IF(AN22<=21,"Medio","Alto"))) -> Bajo | AR22: =VLOOKUP(A22,#REF!,2,FALSE) -> #REF! | AS22: https://s.icepanel.io/wJSECZOwwNkkW8/EbyE | AT22: https://dev.azure.com/BancoPichinchaEC/adi-especificaciones-tecnicas/_git/adi-doc-tecspec-tribu-integracion-apis?version=GBmaster&path=/sp%20-%20Soporte/tnd-msa-sp-orqclientes0038 | AU22: https://dev.azure.com/BancoPichinchaEC/tpl-bus-omnicanal/_git/sqb-msa-orqclientes0038 | AV22: 1 | AW22: https://pichincha.atlassian.net/browse/PCBG-601
A23: ORQClientes0040 | B23: =CONCATENATE(LOWER(E23),"-msa-sp-",LOWER(A23)) -> tnd-msa-sp-orqclientes0040 | C23: Orquestar las consultas para obtener el PDF de Auto Certificacion de Residencias Fiscales | D23: TRIBU SEGMENTOS Y NEGOCIOS DIGITALES | E23: =VLOOKUP(D23,Tribus!$A$1:$B$33,2,FALSE) -> tnd | F23: Bus Omnicanalidad | G23: ORQ | H23: Completado | I23: A Desarrollo | J23: WSTecnicos0070 --> ConsultarLogsCertificacion03 WSClientes0111 --> ConsultarResidenciaFiscal01 WSTecnicos0063 --> obtenerCatalogosSigloBancs01 WSTecnicos0077 --> generarAutocertificacion51 WSClientes0007 --> ConsultarContactoTransaccional01 WSTecnicos0078 --> EnvioNotificacionAdjunto52 | K23: BUS OMNICANAL WAS OMNICANAL | L23: ON-PREMISE | M23: 6 | N23: Alta | O23: SOAP | P23: 1 | Q23: Baja | R23: Ninguna | S23: 0 | T23: Baja | U23: Ninguna | W23: Baja | X23: 1896 | Y23: 430ms | AB23: Baja | AC23: Si puede ser probado por las app | AD23: Baja | AE23: TRIBU_DE_UNA | AF23: ORQClientes0045 | AG23: Segun BDD: 00670: Aplicativo Billetera Movil Pichincha 00352 -> Portal Empresarial BPM 00662 -> Referidos | AH23: 1 | AI23: Baja | AJ23: Ninguno | AK23: Baja | AL23: ConsultarInformacionCertificacion01 | AM23: Baja | AN23: =IFERROR(SUM(CHOOSE(MATCH(N23,{"Baja";"Media";"Alta"},0),1,2,3), CHOOSE(MATCH(Q23,{"Baja";"Media";"Alta"},0),1,2,3), CHOOSE(MATCH(T23,{"Baja";"Media";"Alta"},0),1,2,3), CHOOSE(MATCH(W23,{"Baja";"Media";"Alta"},0),1,2,3), CHOOSE(MATCH(AB23,{"Baja";"Media";"Alta"},0),1,2,3), CHOOSE(MATCH(AD23,{"Baja";"Media";"Alta"},0),1,2,3), CHOOSE(MATCH(AI23,{"Baja";"Media";"Alta"},0),1,2,3), CHOOSE(MATCH(AK23,{"Baja";"Media";"Alta"},0),1,2,3), CHOOSE(MATCH(AM23,{"Baja";"Media";"Alta"},0),1,2,3)),0) -> 11 | AO23: =IF(AN23=0,"Pendiente",IF(AN23<=15,"Bajo",IF(AN23<=21,"Medio","Alto"))) -> Bajo | AR23: =VLOOKUP(A23,#REF!,2,FALSE) -> #REF! | AS23: https://s.icepanel.io/wJSECZOwwNkkW8/eDfb | AT23: https://dev.azure.com/BancoPichinchaEC/adi-especificaciones-tecnicas/_git/adi-doc-tecspec-tribu-integracion-apis?version=GBmaster&path=/sp%20-%20Soporte/tnd-msa-sp-orqclientes0040 | AU23: sqb-msa-orqclientes0040 - Repos | AV23: 1 | AW23: https://pichincha.atlassian.net/browse/PCBG-602
A24: ORQClientes0045 | B24: =CONCATENATE(LOWER(E24),"-msa-sp-",LOWER(A24)) -> tnd-msa-sp-orqclientes0045 | C24: Registrar residencia fiscal | D24: TRIBU SEGMENTOS Y NEGOCIOS DIGITALES | E24: =VLOOKUP(D24,Tribus!$A$1:$B$33,2,FALSE) -> tnd | F24: Bus Omnicanalidad | G24: ORQ | H24: Completado | I24: A Desarrollo | J24: ORQClientes0040 -> ConsultarInformacionCertificacion01 WSClientes0111 -> CrearResidenciaFiscal23 WSTecnicos0078 -> EnvioNotificacionAdjunto52 WSTecnicos0070 -> CrearLogsCertificacion22 / ConsultarLogsCertificacion03 WSTecnicos0027 -> EvaluarOTP54 | K24: BUS OMNICANAL WAS OMNICANAL | L24: ON-PREMISE | M24: 5 | N24: Alta | O24: REST - datapowerexterno SOAP | P24: 2 | Q24: Media | R24: Transforma a json encripta | S24: 2 | T24: Media | U24: Ninguna | W24: Baja | X24: 6.02K | Y24: 1.4s | AB24: Baja | AC24: Si puede ser probado por las app | AD24: Baja | AE24: TRIBU_DE_UNA | AF24: 0 | AG24: Segun BDD: 00670 - Aplicativo Billetera Movil Pichincha | AH24: 1 | AI24: Baja | AJ24: ninguno | AK24: Baja | AL24: registrarResidenciaFiscal01 | AM24: Baja | AN24: =IFERROR(SUM(CHOOSE(MATCH(N24,{"Baja";"Media";"Alta"},0),1,2,3), CHOOSE(MATCH(Q24,{"Baja";"Media";"Alta"},0),1,2,3), CHOOSE(MATCH(T24,{"Baja";"Media";"Alta"},0),1,2,3), CHOOSE(MATCH(W24,{"Baja";"Media";"Alta"},0),1,2,3), CHOOSE(MATCH(AB24,{"Baja";"Media";"Alta"},0),1,2,3), CHOOSE(MATCH(AD24,{"Baja";"Media";"Alta"},0),1,2,3), CHOOSE(MATCH(AI24,{"Baja";"Media";"Alta"},0),1,2,3), CHOOSE(MATCH(AK24,{"Baja";"Media";"Alta"},0),1,2,3), CHOOSE(MATCH(AM24,{"Baja";"Media";"Alta"},0),1,2,3)),0) -> 13 | AO24: =IF(AN24=0,"Pendiente",IF(AN24<=15,"Bajo",IF(AN24<=21,"Medio","Alto"))) -> Bajo | AR24: =VLOOKUP(A24,#REF!,2,FALSE) -> #REF! | AS24: https://s.icepanel.io/wJSECZOwwNkkW8/r3cl | AT24: https://dev.azure.com/BancoPichinchaEC/adi-especificaciones-tecnicas/_git/adi-doc-tecspec-tribu-integracion-apis?version=GBmaster&path=/sp%20-%20Soporte/tnd-msa-sp-orqclientes0045 | AU24: https://dev.azure.com/BancoPichinchaEC/tpl-bus-omnicanal/_git/sqb-msa-orqclientes0045 | AV24: 1 | AW24: https://pichincha.atlassian.net/browse/PCBG-603
A25: ORQClientes0048 | B25: =CONCATENATE(LOWER(E25),"-msa-sp-",LOWER(A25)) -> tnd-msa-sp-orqclientes0048 | C25: Servicio de actualizar los modulos del cliente PRY_CENTRO_DIGITAL | D25: TRIBU SEGMENTOS Y NEGOCIOS DIGITALES | E25: =VLOOKUP(D25,Tribus!$A$1:$B$33,2,FALSE) -> tnd | F25: Bus Omnicanalidad | G25: ORQ | H25: Completado | I25: A Desarrollo | J25: WSClientes0007 -> ConsultarContactoTransaccional01 WSClientes0020 -> ActualizarContactoTransaccional31 WSClientes0024 -> ConsultarIdentificacion01 WSClientes0027 -> ProcesarDatosIdentificacionCliente51_ProcesarWS WSClientes0038 -> OperacionEconomicosCliente52 WSClientes0055 -> OperacionActividadEconomicaCliente52 WSClientes0060 -> OperacionDatosComplementariosCliente51 WSClientes0061 -> OperacionDemograficosCliente51 WSClientes0062 -> OperacionIdentificacionCliente51 WSClientes0072 -> ActualizarDatosReferencias31 WSClientes0099 -> OperacionLocalizacion51 WSClientes0101 -> OperacionRelacionesCliente51 WSClientes0154 -> consultarOficialHomologado01 WSTecnicos0076 -> crearLogModificaciones21 | K25: BUS OMNICANAL WAS OMNICANAL | L25: ON-PREMISE | M25: 14 | N25: Media | O25: 8912 - Rest | P25: 1 | Q25: Baja | R25: Ninguna | S25: 0 | T25: Baja | U25: Ninguna | W25: Baja | X25: 115.2K | Y25: 713ms | AB25: Media | AC25: Si puede ser probado por las app | AD25: Baja | AE25: COE_TRANSFORMACION_PROCESOS TRIBU CANALES | AF25: deployment-cta-customers-core-*; CustomersController deployment-cta-customers-core-*; CustomerUpdateController onb-msa-firc deployment-one-msa-sp-customer-v*-* deployment-cta-customers-core-*; ProspectController | AG25: Default Web Site:443,8043 (/BPMPichinchaDU); IIS app pool | AH25: 6 | AI25: Alta | AJ25: ninguno | AK25: Baja | AL25: actualizarDatosCliente32 | AM25: Baja | AN25: =IFERROR(SUM(CHOOSE(MATCH(N25,{"Baja";"Media";"Alta"},0),1,2,3), CHOOSE(MATCH(Q25,{"Baja";"Media";"Alta"},0),1,2,3), CHOOSE(MATCH(T25,{"Baja";"Media";"Alta"},0),1,2,3), CHOOSE(MATCH(W25,{"Baja";"Media";"Alta"},0),1,2,3), CHOOSE(MATCH(AB25,{"Baja";"Media";"Alta"},0),1,2,3), CHOOSE(MATCH(AD25,{"Baja";"Media";"Alta"},0),1,2,3), CHOOSE(MATCH(AI25,{"Baja";"Media";"Alta"},0),1,2,3), CHOOSE(MATCH(AK25,{"Baja";"Media";"Alta"},0),1,2,3), CHOOSE(MATCH(AM25,{"Baja";"Media";"Alta"},0),1,2,3)),0) -> 13 | AO25: =IF(AN25=0,"Pendiente",IF(AN25<=15,"Bajo",IF(AN25<=21,"Medio","Alto"))) -> Bajo | AR25: =VLOOKUP(A25,#REF!,2,FALSE) -> #REF! | AS25: https://s.icepanel.io/wJSECZOwwNkkW8/NIXN | AT25: https://dev.azure.com/BancoPichinchaEC/adi-especificaciones-tecnicas/_git/adi-doc-tecspec-tribu-integracion-apis?version=GBmaster&path=/sp%20-%20Soporte/tnd-msa-sp-orqclientes0048 | AU25: https://dev.azure.com/BancoPichinchaEC/tpl-bus-omnicanal/_git/sqb-msa-orqclientes0048 | AV25: 1 | AW25: https://pichincha.atlassian.net/browse/PCBG-604
A26: ORQClientes0050 | B26: =CONCATENATE(LOWER(E26),"-msa-sp-",LOWER(A26)) -> tnd-msa-sp-orqclientes0050 | C26: Actualiza contacto transaccional email y/o telefono celular , tiene una variante cuando el cliente no tiene n confianza de session el proceso no es en linea sino en un batch que corre cada hora | D26: TRIBU SEGMENTOS Y NEGOCIOS DIGITALES | E26: =VLOOKUP(D26,Tribus!$A$1:$B$33,2,FALSE) -> tnd | F26: Bus Omnicanalidad | G26: ORQ | H26: Completado | I26: A Desarrollo | J26: WSClientes0024 --> ConsultarIdentificacion01 WSClientes0030 --> ConsultarContactoNotificacion01 WSClientes0028 --> ActualizarEmailLocalizacion33 WSClientes0028 --> ConsultarEmailLocalizacion02 WSClientes0028 --> ActualizarCelularLocalizacion34 WSClientes0028 --> ConsultarCelularLocalizacion01 WSClientes0020 --> ActualizarContactoTransaccional31 WSTecnicos0035 --> ActualizarEstadoTransaccionEspera31 WSTecnicos0036 --> ConsultarDetalleTransaccionDelay02 WSTecnicos0036 --> ConsultarDetalleTransaccionDelay03 WSTecnicos0036 --> CrearDetalleTransaccionDelayServicio21 WSTecnicos0027 --> GenerarOTP51 WSTecnicos0027 --> EvaluarOTP52 WSTecnicos0003 --> obtenerCatalogo01 WSReglas0004 --> ConsultarTransaccionDelay01 WSReglas0010 --> ConsultarSeguridadNoFinanciero01 | K26: BUS OMNICANAL WAS OMNICANAL | L26: ON-PREMISE | M26: 16 | N26: Alta | O26: SOAP 8911 REST 8912 | P26: 2 | Q26: Media | R26: Ninguna | S26: 0 | T26: Baja | U26: Almacena catalogo de horarios para delay en cache shared row, consume WSTecnicos0003 | V26: WSTecnicos0003 | W26: Media | X26: 8.41k | Y26: 600ms | AB26: Baja | AC26: Si puede ser probado por las app | AD26: Baja | AE26: TRIBU PRODUCTOS TRIBU CANALES TRIBU SEGMENTOS Y NEGOCIOS DIGITALES TRIBU_DE_UNA | AF26: ClientInformationController; mht-msa-user-profile CustomerUpdateController; deployment-cta-customers-core-* IBM MQ Queue Listener - CE_DELAY_301005031 WSTecnicos0064Request.WSTecnicos0064Port ProspectController; deployment-cta-customers-core-* Netty on 0:0:0:0:0:0:0:0:*; onb-msa-firc Apigee; waf-tcs-ORQClientes0050 | AH26: 6 | AI26: Alta | AJ26: Ninguno | AK26: Baja | AL26: ActualizarContactoTransaccional31 | AM26: Baja | AN26: =IFERROR(SUM(CHOOSE(MATCH(N26,{"Baja";"Media";"Alta"},0),1,2,3), CHOOSE(MATCH(Q26,{"Baja";"Media";"Alta"},0),1,2,3), CHOOSE(MATCH(T26,{"Baja";"Media";"Alta"},0),1,2,3), CHOOSE(MATCH(W26,{"Baja";"Media";"Alta"},0),1,2,3), CHOOSE(MATCH(AB26,{"Baja";"Media";"Alta"},0),1,2,3), CHOOSE(MATCH(AD26,{"Baja";"Media";"Alta"},0),1,2,3), CHOOSE(MATCH(AI26,{"Baja";"Media";"Alta"},0),1,2,3), CHOOSE(MATCH(AK26,{"Baja";"Media";"Alta"},0),1,2,3), CHOOSE(MATCH(AM26,{"Baja";"Media";"Alta"},0),1,2,3)),0) -> 15 | AO26: =IF(AN26=0,"Pendiente",IF(AN26<=15,"Bajo",IF(AN26<=21,"Medio","Alto"))) -> Bajo | AQ26: No se toma en cuenta las actualizaciones en Pichincah celular, Internexo y Banca Movil antigua ya que esos sitemas estan deprecados. Servicio consume informacion de CE_DELAY_301005031 | AR26: =VLOOKUP(A26,#REF!,2,FALSE) -> #REF! | AS26: https://s.icepanel.io/wJSECZOwwNkkW8/EgCH | AT26: https://dev.azure.com/BancoPichinchaEC/adi-especificaciones-tecnicas/_git/adi-doc-tecspec-tribu-integracion-apis?version=GBmaster&path=/sp%20-%20Soporte/tnd-msa-sp-orqclientes0050 | AU26: sqb-msa-orqclientes0050 - Repos | AV26: 1 | AW26: https://pichincha.atlassian.net/browse/PCBG-605
A27: ORQClientes0052 | B27: =CONCATENATE(LOWER(E27),"-msa-sp-",LOWER(A27)) -> tpr-msa-sp-orqclientes0052 | C27: Servicio que en lista las tarjetas de debito | D27: TRIBU PRODUCTOS | E27: =VLOOKUP(D27,Tribus!$A$1:$B$33,2,FALSE) -> tpr | F27: Bus Omnicanalidad | G27: ORQ | H27: Completado | I27: A Desarrollo | J27: WSClientes0141 -> consultarTarjetasDebitoCliente01 | K27: WAS OMNICANALIDAD | L27: ON-PREMISE | M27: 1 | N27: Baja | O27: API - 443 - https://api.pichincha.com/tcs/ORQClientes0052 | P27: 1 | Q27: Baja | R27: Ninguna | S27: 0 | T27: Baja | U27: Ninguna | W27: Baja | X27: 1584K | Y27: 40.1ms | AB27: Alta | AC27: Si puede ser probado por las app | AD27: Baja | AE27: TRIBU MEDIOS DE PAGO TRIBU CANALES TRIBU PRODUCTOS | AF27: DebitCardConsolidateController, tdd-msa-card DebitCardController, sda-msa-card-design-system DebitCardRequestStateController, tdd-msa-card CustomersInformationController, com.pichincha.AccountsApplication cta-accounts-* WSClientes0141Request.WSClientes0141Port | AH27: 5 | AI27: Media | AJ27: Ninguna | AK27: Baja | AL27: consultarTarjetasDebitoCliente01 | AM27: Baja | AN27: =IFERROR(SUM(CHOOSE(MATCH(N27,{"Baja";"Media";"Alta"},0),1,2,3), CHOOSE(MATCH(Q27,{"Baja";"Media";"Alta"},0),1,2,3), CHOOSE(MATCH(T27,{"Baja";"Media";"Alta"},0),1,2,3), CHOOSE(MATCH(W27,{"Baja";"Media";"Alta"},0),1,2,3), CHOOSE(MATCH(AB27,{"Baja";"Media";"Alta"},0),1,2,3), CHOOSE(MATCH(AD27,{"Baja";"Media";"Alta"},0),1,2,3), CHOOSE(MATCH(AI27,{"Baja";"Media";"Alta"},0),1,2,3), CHOOSE(MATCH(AK27,{"Baja";"Media";"Alta"},0),1,2,3), CHOOSE(MATCH(AM27,{"Baja";"Media";"Alta"},0),1,2,3)),0) -> 12 | AO27: =IF(AN27=0,"Pendiente",IF(AN27<=15,"Bajo",IF(AN27<=21,"Medio","Alto"))) -> Bajo | AR27: =VLOOKUP(A27,#REF!,2,FALSE) -> #REF! | AS27: https://s.icepanel.io/wJSECZOwwNkkW8/XNiB | AT27: https://dev.azure.com/BancoPichinchaEC/adi-especificaciones-tecnicas/_git/adi-doc-tecspec-tribu-integracion-apis?version=GBmaster&path=/sp%20-%20Soporte/tpr-msa-sp-orqclientes0052 | AU27: sqb-msa-orqclientes0052 - Repos | AV27: 1 | AW27: https://pichincha.atlassian.net/browse/PCBG-606
A28: ORQClientes0053 | B28: =CONCATENATE(LOWER(E28),"-msa-sp-",LOWER(A28)) -> tnd-msa-sp-orqclientes0053 | C28: Servicio para consultar retencion por cuenta y cliente | D28: TRIBU SEGMENTOS Y NEGOCIOS DIGITALES | E28: =VLOOKUP(D28,Tribus!$A$1:$B$33,2,FALSE) -> tnd | F28: Bus Omnicanalidad | G28: ORQ | H28: Completado | I28: A Desarrollo | J28: WSClientes0024 --> ConsultarIdentificacion01 WSProductos0189 --> consultarRetencionJudicialId01 WSProductos0189 --> consultarRetencionJudicialCuenta02 WSClientes0067 --> ConsultarCuentasClientes01 | K28: Bus Omnicanal | L28: ON-PREMISE | M28: 4 | N28: Media | O28: SOAP | P28: 1 | Q28: Baja | R28: Ninguna | S28: 0 | T28: Baja | U28: Ninguna | W28: Baja | X28: 7.66k | Y28: 170ms | AB28: Baja | AC28: Si puede ser probado por las app | AD28: Baja | AE28: TRIBU PRODUCTOS COE_TRANSFORMACION_PROCESOS | AF28: creditoenlinea - crd-msa-control-list-integration - /api/v1/credit/precise/control-list-integration/validate-filters WSClientes0179.API - /api/v1/ValidarCuentas/ValidarCuentas01 -> Bizagi | AH28: 2 | AI28: Media | AJ28: Ninguno | AK28: Baja | AL28: ConsultarRetencionJudicial04 | AM28: Baja | AN28: =IFERROR(SUM(CHOOSE(MATCH(N28,{"Baja";"Media";"Alta"},0),1,2,3), CHOOSE(MATCH(Q28,{"Baja";"Media";"Alta"},0),1,2,3), CHOOSE(MATCH(T28,{"Baja";"Media";"Alta"},0),1,2,3), CHOOSE(MATCH(W28,{"Baja";"Media";"Alta"},0),1,2,3), CHOOSE(MATCH(AB28,{"Baja";"Media";"Alta"},0),1,2,3), CHOOSE(MATCH(AD28,{"Baja";"Media";"Alta"},0),1,2,3), CHOOSE(MATCH(AI28,{"Baja";"Media";"Alta"},0),1,2,3), CHOOSE(MATCH(AK28,{"Baja";"Media";"Alta"},0),1,2,3), CHOOSE(MATCH(AM28,{"Baja";"Media";"Alta"},0),1,2,3)),0) -> 11 | AO28: =IF(AN28=0,"Pendiente",IF(AN28<=15,"Bajo",IF(AN28<=21,"Medio","Alto"))) -> Bajo | AR28: =VLOOKUP(A28,#REF!,2,FALSE) -> #REF! | AS28: https://s.icepanel.io/wJSECZOwwNkkW8/Chdz | AT28: https://dev.azure.com/BancoPichinchaEC/adi-especificaciones-tecnicas/_git/adi-doc-tecspec-tribu-integracion-apis?version=GBmaster&path=/sp%20-%20Soporte/tnd-msa-sp-orqclientes0053 | AU28: sqb-msa-orqclientes0053 | AV28: 1 | AW28: https://pichincha.atlassian.net/browse/PCBG-607
A29: ORQClientes0054 | B29: =CONCATENATE(LOWER(E29),"-msa-sp-",LOWER(A29)) -> tnd-msa-sp-orqclientes0054 | C29: Consulta datos basicos del Cliente | D29: TRIBU SEGMENTOS Y NEGOCIOS DIGITALES | E29: =VLOOKUP(D29,Tribus!$A$1:$B$33,2,FALSE) -> tnd | F29: Bus Omnicanalidad | G29: ORQ | H29: Completado | I29: A Desarrollo | J29: WSClientes0024 → ConsultarIdentificacion01 (destino: IIB) WSClientes0038 → ConsultarDetalleAdicionalesCliente01 (destino: IIB) WSClientes0061 → OperacionDemograficosCliente51 (destino: IIB) WSClientes0007 → ConsultarContactoTransaccional01 (destino: IIB) WSClientes0055 → OperacionActividadEconomicaCliente51 (destino: IIB) WSClientes0038 → OperacionEconomicosCliente52 (destino: IIB) WSClientes0099 → OperacionLocalizacion51 (destino: IIB) WSTecnicos0063 → obtenerCatalogosSigloBancs01 (destino: WAS) | K29: BUS OMNICANAL WAS OMNICANAL | L29: ON-PREMISE | M29: 7 | N29: Alta | O29: SOAP | P29: 1 | Q29: Baja | R29: NO | S29: 0 | T29: Baja | U29: Ninguna | W29: Baja | X29: 1638 | Y29: 439ms | AB29: Baja | AC29: Si puede ser probado por las app | AD29: Baja | AE29: TRIBU PRODUCTOS | AF29: inv-msa-investments; InvestmentsController | AH29: 1 | AI29: Baja | AJ29: NO | AK29: Baja | AL29: ConsultarInformacionCliente01 | AM29: Baja | AN29: =IFERROR(SUM(CHOOSE(MATCH(N29,{"Baja";"Media";"Alta"},0),1,2,3), CHOOSE(MATCH(Q29,{"Baja";"Media";"Alta"},0),1,2,3), CHOOSE(MATCH(T29,{"Baja";"Media";"Alta"},0),1,2,3), CHOOSE(MATCH(W29,{"Baja";"Media";"Alta"},0),1,2,3), CHOOSE(MATCH(AB29,{"Baja";"Media";"Alta"},0),1,2,3), CHOOSE(MATCH(AD29,{"Baja";"Media";"Alta"},0),1,2,3), CHOOSE(MATCH(AI29,{"Baja";"Media";"Alta"},0),1,2,3), CHOOSE(MATCH(AK29,{"Baja";"Media";"Alta"},0),1,2,3), CHOOSE(MATCH(AM29,{"Baja";"Media";"Alta"},0),1,2,3)),0) -> 11 | AO29: =IF(AN29=0,"Pendiente",IF(AN29<=15,"Bajo",IF(AN29<=21,"Medio","Alto"))) -> Bajo | AR29: =VLOOKUP(A29,#REF!,2,FALSE) -> #REF! | AS29: https://s.icepanel.io/wJSECZOwwNkkW8/jGPX | AT29: https://dev.azure.com/BancoPichinchaEC/adi-especificaciones-tecnicas/_git/adi-doc-tecspec-tribu-integracion-apis?version=GBmaster&path=/sp%20-%20Soporte/tnd-msa-sp-orqclientes0054 | AU29: https://dev.azure.com/BancoPichinchaEC/tpl-bus-omnicanal/_git/sqb-msa-orqclientes0054 | AV29: 1 | AW29: https://pichincha.atlassian.net/browse/PCBG-608
A30: ORQClientes0056 | B30: =CONCATENATE(LOWER(E30),"-msa-sp-",LOWER(A30)) -> tnd-msa-sp-orqclientes0056 | C30: Orquesta la actualizacion de datos del cliente y del asesor | D30: TRIBU SEGMENTOS Y NEGOCIOS DIGITALES | E30: =VLOOKUP(D30,Tribus!$A$1:$B$33,2,FALSE) -> tnd | F30: Bus Omnicanalidad | G30: ORQ | H30: Completado | I30: A Desarrollo | J30: WSClientes0153 -> ConsultarDatosAdicionalesCliente01 WSClientes0154 -> consultarOficialHomologado01 WSClientes0155 -> consultarOficialHomologado02 WSClientes0156 -> ActualizarOficialCliente31 | K30: BUS OMNICANAL WAS OMNICANAL | L30: ON-PREMISE | M30: 4 | N30: Alta | O30: SOAP | P30: 1 | Q30: Baja | R30: NO | S30: 0 | T30: Baja | U30: Ninguna | W30: Baja | X30: 1068 | Y30: 144ms | AB30: Baja | AC30: Si puede ser probado por las app | AD30: Baja | AE30: TRIBU SEGMENTOS Y NEGOCIOS DIGITALES | AF30: 0 | AG30: Segun BDD: 00344 - PLATAFORMACOMERCIALCRM | AH30: 1 | AI30: Baja | AJ30: NO | AK30: Baja | AL30: ActualizarOficialCliente31 | AM30: Baja | AN30: =IFERROR(SUM(CHOOSE(MATCH(N30,{"Baja";"Media";"Alta"},0),1,2,3), CHOOSE(MATCH(Q30,{"Baja";"Media";"Alta"},0),1,2,3), CHOOSE(MATCH(T30,{"Baja";"Media";"Alta"},0),1,2,3), CHOOSE(MATCH(W30,{"Baja";"Media";"Alta"},0),1,2,3), CHOOSE(MATCH(AB30,{"Baja";"Media";"Alta"},0),1,2,3), CHOOSE(MATCH(AD30,{"Baja";"Media";"Alta"},0),1,2,3), CHOOSE(MATCH(AI30,{"Baja";"Media";"Alta"},0),1,2,3), CHOOSE(MATCH(AK30,{"Baja";"Media";"Alta"},0),1,2,3), CHOOSE(MATCH(AM30,{"Baja";"Media";"Alta"},0),1,2,3)),0) -> 11 | AO30: =IF(AN30=0,"Pendiente",IF(AN30<=15,"Bajo",IF(AN30<=21,"Medio","Alto"))) -> Bajo | AR30: =VLOOKUP(A30,#REF!,2,FALSE) -> #REF! | AS30: https://s.icepanel.io/wJSECZOwwNkkW8/zVf0 | AT30: https://dev.azure.com/BancoPichinchaEC/adi-especificaciones-tecnicas/_git/adi-doc-tecspec-tribu-integracion-apis?version=GBmaster&path=/sp%20-%20Soporte/tnd-msa-sp-orqclientes0056 | AU30: https://dev.azure.com/BancoPichinchaEC/tpl-bus-omnicanal/_git/sqb-msa-orqclientes0056 | AV30: 1 | AW30: https://pichincha.atlassian.net/browse/PCBG-609
A31: ORQClientes0059 | B31: =CONCATENATE(LOWER(E31),"-msa-sp-",LOWER(A31)) -> tnd-msa-sp-orqclientes0059 | C31: Servicio de actualizar y consultar datos complementarios PRY_CENTRO_DIGITAL | D31: TRIBU SEGMENTOS Y NEGOCIOS DIGITALES | E31: =VLOOKUP(D31,Tribus!$A$1:$B$33,2,FALSE) -> tnd | F31: Bus Omnicanalidad | G31: ORQ | H31: Completado | I31: A Desarrollo | J31: WSClientes0006 WSClientes0060 WSClientes0101 WSClientes0122 | K31: Bus Omnicanalidad | L31: ON-PREMISE | M31: 4 | N31: Alta | O31: SOAP 8511 - SOAP | P31: 1 | Q31: Baja | R31: Ninguna | S31: 0 | T31: Baja | U31: Ninguna | W31: Baja | X31: 632 | Y31: 259ms | AB31: Baja | AC31: Si puede ser probado por las app | AD31: Baja | AE31: TRIBU CANALES | AF31: No se identifica consumidores (doble check) | AG31: Servicios_Consumidos_Vinculacion_Integral | AH31: 0 | AI31: Baja | AJ31: Ninguno | AK31: Baja | AL31: ProcesarDatosComplementariosCliente31 | AM31: Baja | AN31: =IFERROR(SUM(CHOOSE(MATCH(N31,{"Baja";"Media";"Alta"},0),1,2,3), CHOOSE(MATCH(Q31,{"Baja";"Media";"Alta"},0),1,2,3), CHOOSE(MATCH(T31,{"Baja";"Media";"Alta"},0),1,2,3), CHOOSE(MATCH(W31,{"Baja";"Media";"Alta"},0),1,2,3), CHOOSE(MATCH(AB31,{"Baja";"Media";"Alta"},0),1,2,3), CHOOSE(MATCH(AD31,{"Baja";"Media";"Alta"},0),1,2,3), CHOOSE(MATCH(AI31,{"Baja";"Media";"Alta"},0),1,2,3), CHOOSE(MATCH(AK31,{"Baja";"Media";"Alta"},0),1,2,3), CHOOSE(MATCH(AM31,{"Baja";"Media";"Alta"},0),1,2,3)),0) -> 11 | AO31: =IF(AN31=0,"Pendiente",IF(AN31<=15,"Bajo",IF(AN31<=21,"Medio","Alto"))) -> Bajo | AR31: =VLOOKUP(A31,#REF!,2,FALSE) -> #REF! | AS31: https://s.icepanel.io/wJSECZOwwNkkW8/bfwG | AT31: https://dev.azure.com/BancoPichinchaEC/adi-especificaciones-tecnicas/_git/adi-doc-tecspec-tribu-integracion-apis?version=GBmaster&path=/sp%20-%20Soporte/tnd-msa-sp-orqclientes0059 | AU31: sqb-msa-orqclientes0059 - Repos | AV31: 1 | AW31: https://pichincha.atlassian.net/browse/PCBG-610 | AY31: pendiente icepanel
A32: ORQClientes0062 | B32: =CONCATENATE(LOWER(E32),"-msa-sp-",LOWER(A32)) -> tnd-msa-sp-orqclientes0062 | C32: procesa direcciones del cliente sin segundo factor de autenticación | D32: TRIBU SEGMENTOS Y NEGOCIOS DIGITALES | E32: =VLOOKUP(D32,Tribus!$A$1:$B$33,2,FALSE) -> tnd | F32: Bus Omnicanalidad | G32: ORQ | H32: Completado | I32: A Desarrollo | J32: WSClientes0015(eliminarDireccionCliente44, consultarDireccionesClientes01, crearModificarDireccionCliente22) → WSConexionLdap → srcpprd WSTecnicos0063(obtenerCatalogosSigloBancs01) → p012band_taf CE_EVENTOS | K32: BUS OMNICANAL WAS OMNICANAL | L32: ON-PREMISE | M32: 2 | N32: Media | O32: SOAP | P32: 1 | Q32: Baja | R32: Ninguna | S32: 0 | T32: Baja | U32: Ninguna | V32: No aplica | W32: Baja | X32: 72.6k | Y32: 92.4 ms | AB32: Media | AC32: Si puede ser probado por las app | AD32: Baja | AE32: TRIBU PRODUCTOS TRIBU MEDIOS DE PAGO TRIBU SEGMENTOS Y NEGOCIOS DIGITALES AREA MICROFINANZAS | AF32: creditoenlinea -crd-msa-insurance-integration -deployment-crd-msa-insurance-integration-* CustomerAddressController: tdd-msa-card-debitcard-gateway (REN) NovaController: sge-msa-bc-prab-insurance-management | AG32: NOVA(Hub Seguros) REN | AH32: 3 | AI32: Media | AJ32: 0 | AK32: Baja | AL32: procesarDireccionesCliente05 | AM32: Baja | AN32: =IFERROR(SUM(CHOOSE(MATCH(N32,{"Baja";"Media";"Alta"},0),1,2,3), CHOOSE(MATCH(Q32,{"Baja";"Media";"Alta"},0),1,2,3), CHOOSE(MATCH(T32,{"Baja";"Media";"Alta"},0),1,2,3), CHOOSE(MATCH(W32,{"Baja";"Media";"Alta"},0),1,2,3), CHOOSE(MATCH(AB32,{"Baja";"Media";"Alta"},0),1,2,3), CHOOSE(MATCH(AD32,{"Baja";"Media";"Alta"},0),1,2,3), CHOOSE(MATCH(AI32,{"Baja";"Media";"Alta"},0),1,2,3), CHOOSE(MATCH(AK32,{"Baja";"Media";"Alta"},0),1,2,3), CHOOSE(MATCH(AM32,{"Baja";"Media";"Alta"},0),1,2,3)),0) -> 12 | AO32: =IF(AN32=0,"Pendiente",IF(AN32<=15,"Bajo",IF(AN32<=21,"Medio","Alto"))) -> Bajo | AQ32: Servicio que procesa direcciones sin 2FA, reglas de seguridad apagadas | AR32: =VLOOKUP(A32,#REF!,2,FALSE) -> #REF! | AS32: ORQClientes0062 Component Diagram | Banco Pichincha C.A. landscape | IcePanel App | AT32: https://dev.azure.com/BancoPichinchaEC/adi-especificaciones-tecnicas/_git/adi-doc-tecspec-tribu-integracion-apis?version=GBmaster&path=/sp%20-%20Soporte/tnd-msa-sp-orqclientes0062 | AU32: https://dev.azure.com/BancoPichinchaEC/tpl-bus-omnicanal/_git/sqb-msa-orqclientes0062 | AV32: 1 | AW32: https://pichincha.atlassian.net/browse/PCBG-611
A33: ORQClientes0063 | B33: =CONCATENATE(LOWER(E33),"-msa-sp-",LOWER(A33)) -> tnd-msa-sp-orqclientes0063 | C33: procesa datos sobre la actividad económica de un cliente | D33: TRIBU SEGMENTOS Y NEGOCIOS DIGITALES | E33: =VLOOKUP(D33,Tribus!$A$1:$B$33,2,FALSE) -> tnd | F33: Bus Omnicanalidad | G33: ORQ | H33: Completado | I33: A Desarrollo | J33: WSClientes0027(ProcesarDatosIdentificacionCliente51) WSClientes0055(OperacionActividadEconomicaCliente52) → WSConexionLdap → srvpprd CE_EVENTOS | K33: BUS OMNICANAL | L33: ON-PREMISE | M33: 2 | N33: Media | O33: SOAP | P33: 1 | Q33: Baja | R33: Ninguna | S33: 0 | T33: Baja | U33: Ninguna | V33: No aplica | W33: Baja | X33: 14.72k | Y33: 127 ms | AB33: Baja | AC33: Si puede ser probado por las app | AD33: Baja | AE33: TRIBU SEGMENTOS Y NEGOCIOS DIGITALES | AF33: deployment-mht-msa-economic-data-* deployment-mht-msa-firc-gtw-* | AG33: Onboard Clientes CRM | AH33: 2 | AI33: Media | AJ33: 0 | AK33: Baja | AL33: actualizarActividadEconomicoCliente31 | AM33: Baja | AN33: =IFERROR(SUM(CHOOSE(MATCH(N33,{"Baja";"Media";"Alta"},0),1,2,3), CHOOSE(MATCH(Q33,{"Baja";"Media";"Alta"},0),1,2,3), CHOOSE(MATCH(T33,{"Baja";"Media";"Alta"},0),1,2,3), CHOOSE(MATCH(W33,{"Baja";"Media";"Alta"},0),1,2,3), CHOOSE(MATCH(AB33,{"Baja";"Media";"Alta"},0),1,2,3), CHOOSE(MATCH(AD33,{"Baja";"Media";"Alta"},0),1,2,3), CHOOSE(MATCH(AI33,{"Baja";"Media";"Alta"},0),1,2,3), CHOOSE(MATCH(AK33,{"Baja";"Media";"Alta"},0),1,2,3), CHOOSE(MATCH(AM33,{"Baja";"Media";"Alta"},0),1,2,3)),0) -> 11 | AO33: =IF(AN33=0,"Pendiente",IF(AN33<=15,"Bajo",IF(AN33<=21,"Medio","Alto"))) -> Bajo | AR33: =VLOOKUP(A33,#REF!,2,FALSE) -> #REF! | AS33: ORQClientes0063 Component Diagram | Banco Pichincha C.A. landscape | IcePanel App | AT33: https://dev.azure.com/BancoPichinchaEC/adi-especificaciones-tecnicas/_git/adi-doc-tecspec-tribu-integracion-apis?version=GBmaster&path=/sp%20-%20Soporte/tnd-msa-sp-orqclientes0063 | AU33: sqb-msa-orqclientes0063 - Repos | AV33: 1 | AW33: https://pichincha.atlassian.net/browse/PCBG-686
A34: ORQClientes0071 | B34: =CONCATENATE(LOWER(E34),"-msa-sp-",LOWER(A34)) -> tnd-msa-sp-orqclientes0071 | C34: Consultar detalle del cliente como identificación, segmento, económicos, FATCA. | D34: TRIBU SEGMENTOS Y NEGOCIOS DIGITALES | E34: =VLOOKUP(D34,Tribus!$A$1:$B$33,2,FALSE) -> tnd | F34: Bus Omnicanalidad | G34: ORQ | H34: Completado | I34: A Desarrollo | J34: WSClientes0055(OperacionActividadEconomicaCliente51) WSClientes0062(OperacionIdentificacionCliente51) WSClientes0077(ConsultarDatoBasicoCliente01) WSSeguridad0029(consultaAsesorAgenciaAnclaje01) → srvpprd WSTecnicos0063(obtenerCatalogosSigloBancs01) → srvpprd WSClientes0038(OperacionEconomicosCliente52) WSClientes0024(ConsultarIdentificacion01) CE_EVENTOS | K34: BUS OMNICANAL WAS OMNICANAL | L34: ON-PREMISE | M34: 2 | N34: Media | O34: SOAP | P34: 1 | Q34: Baja | R34: Ninguna | S34: 0 | T34: Baja | U34: Ninguna | V34: No aplica | W34: Baja | X34: 97.6k | Y34: 433 ms | AB34: Media | AC34: Si puede ser probado por las app | AD34: Baja | AE34: TRIBU SEGMENTOS Y NEGOCIOS DIGITALES TRIBU CANALES | AF34: DebitCardOfferController → - tdd-msa-debitcard-gateway - REN Default Web Site:443, 8043 (/BPMPichinchaSG) Default Web Site:443, 8043 (BPMPichinchaCH) ORQClientes0079 → deployment-tcf-msa-dm-orqclientes*_* ExternalServicesController → deployment-sec-msa-car-parameter-analysis-* mht-msa-user-profile; ClientInformationController mht-msa-user-profile; ProcessAddressController omn-msa-user-profile; ClientInformationController | AG34: DebitCardOfferController BPMPichinchaSG BPMPichincahCH ExternalServicesController | AH34: 4 | AI34: Alta | AJ34: 1 | AK34: Media | AL34: consultarDetalleCliente01 | AM34: Baja | AN34: =IFERROR(SUM(CHOOSE(MATCH(N34,{"Baja";"Media";"Alta"},0),1,2,3), CHOOSE(MATCH(Q34,{"Baja";"Media";"Alta"},0),1,2,3), CHOOSE(MATCH(T34,{"Baja";"Media";"Alta"},0),1,2,3), CHOOSE(MATCH(W34,{"Baja";"Media";"Alta"},0),1,2,3), CHOOSE(MATCH(AB34,{"Baja";"Media";"Alta"},0),1,2,3), CHOOSE(MATCH(AD34,{"Baja";"Media";"Alta"},0),1,2,3), CHOOSE(MATCH(AI34,{"Baja";"Media";"Alta"},0),1,2,3), CHOOSE(MATCH(AK34,{"Baja";"Media";"Alta"},0),1,2,3), CHOOSE(MATCH(AM34,{"Baja";"Media";"Alta"},0),1,2,3)),0) -> 14 | AO34: =IF(AN34=0,"Pendiente",IF(AN34<=15,"Bajo",IF(AN34<=21,"Medio","Alto"))) -> Bajo | AR34: =VLOOKUP(A34,#REF!,2,FALSE) -> #REF! | AS34: OrqClientes0071 Component Diagram | Banco Pichincha C.A. landscape | IcePanel App | AT34: https://dev.azure.com/BancoPichinchaEC/adi-especificaciones-tecnicas/_git/adi-doc-tecspec-tribu-integracion-apis?version=GBmaster&path=/sp%20-%20Soporte/tnd-msa-sp-orqclientes0071 | AU34: sqb-msa-orqclientes0071 - Repos | AV34: 1 | AW34: https://pichincha.atlassian.net/browse/PCBG-687
A35: ORQClientes0072 | B35: =CONCATENATE(LOWER(E35),"-msa-sp-",LOWER(A35)) -> tnd-msa-sp-orqclientes0072 | C35: Servicio que actualiza, elimina, consulta y modifica las direcciones del cliente PRY_CENTRO_DIGITAL | D35: TRIBU SEGMENTOS Y NEGOCIOS DIGITALES | E35: =VLOOKUP(D35,Tribus!$A$1:$B$33,2,FALSE) -> tnd | F35: Bus Omnicanalidad | G35: ORQ | H35: Completado | I35: A Desarrollo | J35: WSClientes0015 crearModificarDireccionCliente22 consultarDireccionesClientes01 eliminarDireccionCliente44 WSTecnicos0063 obtenerCatalogosSigloBancs01 WSReglas0010 ConsultarSeguridadNoFinanciero01 WSTecnicos0027 GenerarOTP51 EvaluarOTP52 | K35: BUS OMNICANAL WAS OMNICANAL | L35: ON-PREMISE | M35: 4 | N35: Media | O35: REST | P35: 1 | Q35: Baja | R35: NO | S35: 0 | T35: Baja | U35: Ninguna | W35: Media | X35: 39.6K | Y35: 87.2ms | AB35: Baja | AC35: Si puede ser probado por las app | AD35: Baja | AE35: TRIBU SEGMENTOS Y NEGOCIOS DIGITALES BPM | AF35: mht-msa-user-profile; ClientInformationController mht-msa-user-profile; ProcessAddressController | AH35: 1 | AI35: Baja | AJ35: NO | AK35: Baja | AL35: procesarDireccionesCliente51 | AM35: Baja | AN35: =IFERROR(SUM(CHOOSE(MATCH(N35,{"Baja";"Media";"Alta"},0),1,2,3), CHOOSE(MATCH(Q35,{"Baja";"Media";"Alta"},0),1,2,3), CHOOSE(MATCH(T35,{"Baja";"Media";"Alta"},0),1,2,3), CHOOSE(MATCH(W35,{"Baja";"Media";"Alta"},0),1,2,3), CHOOSE(MATCH(AB35,{"Baja";"Media";"Alta"},0),1,2,3), CHOOSE(MATCH(AD35,{"Baja";"Media";"Alta"},0),1,2,3), CHOOSE(MATCH(AI35,{"Baja";"Media";"Alta"},0),1,2,3), CHOOSE(MATCH(AK35,{"Baja";"Media";"Alta"},0),1,2,3), CHOOSE(MATCH(AM35,{"Baja";"Media";"Alta"},0),1,2,3)),0) -> 11 | AO35: =IF(AN35=0,"Pendiente",IF(AN35<=15,"Bajo",IF(AN35<=21,"Medio","Alto"))) -> Bajo | AR35: =VLOOKUP(A35,#REF!,2,FALSE) -> #REF! | AS35: https://s.icepanel.io/wJSECZOwwNkkW8/rqTm | AT35: https://dev.azure.com/BancoPichinchaEC/adi-especificaciones-tecnicas/_git/adi-doc-tecspec-tribu-integracion-apis?version=GBmaster&path=/sp%20-%20Soporte/tnd-msa-sp-orqclientes0072 | AU35: sqb-msa-orqclientes0072 - Repos | AV35: 1 | AW35: https://pichincha.atlassian.net/browse/PCBG-614
A36: WSClientes0001 | B36: =CONCATENATE(LOWER(E36),"-msa-sp-",LOWER(A36)) -> tpr-msa-sp-wsclientes0001 | C36: Consulta Cuentas Activas | D36: TRIBU PRODUCTOS | E36: =VLOOKUP(D36,Tribus!$A$1:$B$33,2,FALSE) -> tpr | F36: Bus Omnicanalidad | G36: WS | H36: Completado | I36: A Desarrollo | J36: UMPProductos0049 -> ConsultarPosicionConsolidadaCliente01 -> 060450 UMPProductos0001 -> ConsultarCuentas01 -> 060453 / 060452 UMPProductos0066 -> ConsultarFirmaUnicaIndependiente01 -> 064014 | K36: TX BANCS | L36: ON-PREMISE | M36: 3 | N36: Media | O36: SOAP - 8934 | P36: 1 | Q36: Baja | R36: Ninguna | S36: 0 | T36: Baja | U36: Ninguna | W36: Baja | X36: 29.8K | Y36: 36.8 ms | AB36: Baja | AC36: Afecta algunos servicios | AD36: Media | AE36: COE_TRANSFORMACION_PROCESOS TRIBU ADMINISTRACION DE CREDITO TRIBU CANALES | AF36: ORQClientes0025 ORQProductos0019 WSProductos0183.API; deployment-cnb-msa-dm-wsproductos WSProductos0184.API; deployment-cnb-msa-dm-wsproductos WSProductos0185.API; deployment-cnb-msa-dm-wsproductos | AG36: 0 | AH36: 5 | AI36: Alta | AJ36: Ninguno | AK36: Baja | AL36: ConsultarCuentasActivas01 | AM36: Baja | AN36: =IFERROR(SUM(CHOOSE(MATCH(N36,{"Baja";"Media";"Alta"},0),1,2,3), CHOOSE(MATCH(Q36,{"Baja";"Media";"Alta"},0),1,2,3), CHOOSE(MATCH(T36,{"Baja";"Media";"Alta"},0),1,2,3), CHOOSE(MATCH(W36,{"Baja";"Media";"Alta"},0),1,2,3), CHOOSE(MATCH(AB36,{"Baja";"Media";"Alta"},0),1,2,3), CHOOSE(MATCH(AD36,{"Baja";"Media";"Alta"},0),1,2,3), CHOOSE(MATCH(AI36,{"Baja";"Media";"Alta"},0),1,2,3), CHOOSE(MATCH(AK36,{"Baja";"Media";"Alta"},0),1,2,3), CHOOSE(MATCH(AM36,{"Baja";"Media";"Alta"},0),1,2,3)),0) -> 13 | AO36: =IF(AN36=0,"Pendiente",IF(AN36<=15,"Bajo",IF(AN36<=21,"Medio","Alto"))) -> Bajo | AR36: =VLOOKUP(A36,#REF!,2,FALSE) -> #REF! | AS36: https://s.icepanel.io/wJSECZOwwNkkW8/6HIP | AT36: https://dev.azure.com/BancoPichinchaEC/adi-especificaciones-tecnicas/_git/adi-doc-tecspec-tribu-integracion-apis?version=GBmaster&path=/sp%20-%20Soporte/tpr-msa-sp-wsclientes0001 | AU36: sqb-msa-wsclientes0001 - Repos | AV36: 1 | AW36: https://pichincha.atlassian.net/browse/PCBG-690
A37: WSClientes0003 | B37: =CONCATENATE(LOWER(E37),"-msa-sp-",LOWER(A37)) -> tpr-msa-sp-wsclientes0003 | C37: Permite consultar tarjetas de cliente | D37: TRIBU PRODUCTOS | E37: =VLOOKUP(D37,Tribus!$A$1:$B$33,2,FALSE) -> tpr | F37: Bus Omnicanalidad | G37: WS | H37: Completado | I37: A Desarrollo | J37: UMPProductos0003 (ConsultarTarjetas01) → https://www.optar.com.ec:443/optar.Banco.Web/PosicionConsolidada.aspx UMPProductos0041(ConsultarTarjetaCreditoIntegrador01) → "https://bpintegrador.pichincha.com/TCSIntegradorInterdin/InterdinPosConsTarj.aspx?UserId=" | K37: InterdinPosConsTarj.aspx INTEDIN | L37: ON-PREMISE | M37: 1 | N37: Baja | O37: SOAP | P37: 1 | Q37: Baja | R37: CIfrado para la consulta de tarjetas en UMP | S37: 2 | T37: Media | U37: Ninguna | V37: No aplica | W37: Baja | X37: 288k | Y37: 110ms | Z37: 74.7k | AA37: 928 | AB37: Media | AC37: Si puede ser probado por las app | AD37: Media | AE37: TRIBU CANALES TRIBU MEDIOS DE PAGOS | AF37: ORQClientes0003 | AG37: no aplica | AH37: 1 | AI37: Baja | AJ37: Interdin /Common/VS_MNT_VISA:443 (https://bpintegrador.pichincha.com:443/TCSIntegradorInterdin/InterdinPosConsTarj.aspx) | AK37: Media | AL37: ConsultarTarjetasActivas01 | AM37: Baja | AN37: =IFERROR(SUM(CHOOSE(MATCH(N37,{"Baja";"Media";"Alta"},0),1,2,3), CHOOSE(MATCH(Q37,{"Baja";"Media";"Alta"},0),1,2,3), CHOOSE(MATCH(T37,{"Baja";"Media";"Alta"},0),1,2,3), CHOOSE(MATCH(W37,{"Baja";"Media";"Alta"},0),1,2,3), CHOOSE(MATCH(AB37,{"Baja";"Media";"Alta"},0),1,2,3), CHOOSE(MATCH(AD37,{"Baja";"Media";"Alta"},0),1,2,3), CHOOSE(MATCH(AI37,{"Baja";"Media";"Alta"},0),1,2,3), CHOOSE(MATCH(AK37,{"Baja";"Media";"Alta"},0),1,2,3), CHOOSE(MATCH(AM37,{"Baja";"Media";"Alta"},0),1,2,3)),0) -> 13 | AO37: =IF(AN37=0,"Pendiente",IF(AN37<=15,"Bajo",IF(AN37<=21,"Medio","Alto"))) -> Bajo | AQ37: 1. con el valor booleano en true consulta una sola UMP 2. Se debe considerar no usar la integración con interdinPosConsTarj.aspc que en su momento fue el mediador con INTERDIN. Ya que ahora se expuso nuevas interfaz a travé sde APIM con el partner. | AR37: =VLOOKUP(A37,#REF!,2,FALSE) -> #REF! | AS37: https://app.icepanel.io/landscapes/w71QNHgfDvF79GrSuA3r/versions/latest/diagrams/editor?domain=z5rnxbake2&diagram=r5OdNur28F&model=7occc01ipao&overlay_tab=tags&x1=-773.6&y1=-72&x2=1717.6&y2=1248 | AT37: https://dev.azure.com/BancoPichinchaEC/adi-especificaciones-tecnicas/_git/adi-doc-tecspec-tribu-integracion-apis?version=GBmaster&path=/sp%20-%20Soporte/tpr-msa-sp-wsclientes0003 | AU37: sqb-msa-wsclientes0003 - Repos | AV37: 1 | AW37: https://pichincha.atlassian.net/browse/PCBG-741 | AX37: llama dos umps
A38: WSClientes0006 | B38: =CONCATENATE(LOWER(E38),"-msa-sp-",LOWER(A38)) -> tnd-msa-sp-wsclientes0006 | C38: Consulta informacion basica del cliente | D38: TRIBU SEGMENTOS Y NEGOCIOS DIGITALES | E38: =VLOOKUP(D38,Tribus!$A$1:$B$33,2,FALSE) -> tnd | F38: Bus Omnicanalidad | G38: WS | H38: Completado | I38: A Desarrollo | J38: UMPClientes0020-> ConsultaInformacionCliente01-> TX067050-> Consulta información basica del cliente UMPTecnicos0006 -> ConsultarTransaccionCatalogo01 -> TX079006 -> Consultar de catalogo: ciudad, nacionalidad, agencia UMPClientes0042 -> ConsultarReferencia01 -> TX062120 -> Consulta el instancia de direccion correspondencia ->TX061404->Consulta el direccion correspondencia | K38: TX BANCS | L38: ON-PREMISE | M38: 3 | N38: Media | O38: SOAP - 8934 REST - 8912 | P38: 2 | Q38: Media | R38: Ninguna | S38: 0 | T38: Baja | U38: Ninguna | W38: Baja | X38: 768K | Y38: 100ms | AB38: Media | AC38: Afecta algunos servicios | AD38: Media | AE38: TRIBU CANALES TRIBU MEDIOS DE PAGO TRIBU PRODUCTOS | AF38: deployment-omn-msa-creditcard-payment-* omn-msa-creditcard-payment deployment-omn-msa-interbank-creditcard-payment-* omn-msa-interbank-creditcard-payment ORQClientes0002 ORQClientes0059 ORQProductos1002 ORQClientes0079.API deployment-tcf-msa-dm-orqclientes*-* DebitCardOffertController tdd-msa-card PaymentFavoritesController sda-msa-payments BillPaymentsController sda-msa-payments | AG38: Default Web Site:443,8043 (/BPMPichinchaTD) | AH38: 10 | AI38: Alta | AJ38: Ninguna | AK38: Baja | AL38: ConsultarInformacionBasica01 | AM38: Baja | AN38: =IFERROR(SUM(CHOOSE(MATCH(N38,{"Baja";"Media";"Alta"},0),1,2,3), CHOOSE(MATCH(Q38,{"Baja";"Media";"Alta"},0),1,2,3), CHOOSE(MATCH(T38,{"Baja";"Media";"Alta"},0),1,2,3), CHOOSE(MATCH(W38,{"Baja";"Media";"Alta"},0),1,2,3), CHOOSE(MATCH(AB38,{"Baja";"Media";"Alta"},0),1,2,3), CHOOSE(MATCH(AD38,{"Baja";"Media";"Alta"},0),1,2,3), CHOOSE(MATCH(AI38,{"Baja";"Media";"Alta"},0),1,2,3), CHOOSE(MATCH(AK38,{"Baja";"Media";"Alta"},0),1,2,3), CHOOSE(MATCH(AM38,{"Baja";"Media";"Alta"},0),1,2,3)),0) -> 15 | AO38: =IF(AN38=0,"Pendiente",IF(AN38<=15,"Bajo",IF(AN38<=21,"Medio","Alto"))) -> Bajo | AR38: =VLOOKUP(A38,#REF!,2,FALSE) -> #REF! | AS38: https://s.icepanel.io/wJSECZOwwNkkW8/xhL8 | AT38: https://dev.azure.com/BancoPichinchaEC/adi-especificaciones-tecnicas/_git/adi-doc-tecspec-tribu-integracion-apis?version=GBmaster&path=/sp%20-%20Soporte/tnd-msa-sp-wsclientes0006 | AU38: sqb-msa-wsclientes0006 - Repos | AV38: 1 | AW38: https://pichincha.atlassian.net/browse/PCBG-382
A39: WSClientes0007 | B39: =CONCATENATE(LOWER(E39),"-msa-sp-",LOWER(A39)) -> tnd-msa-sp-wsclientes0007 | C39: Consultar Contacto Transaccional para notificaciones | D39: TRIBU SEGMENTOS Y NEGOCIOS DIGITALES | E39: =VLOOKUP(D39,Tribus!$A$1:$B$33,2,FALSE) -> tnd | F39: Bus Omnicanalidad | G39: WS | H39: Completado | I39: A Desarrollo | J39: UMPClientes0002 -> ConsultarInformacionBasica01 -> TX060480 -> Consulta el CIF del cliente UMPClientes0028 -> ConsultarIdentificacion01 -> http://10.151.8.62:8934/Omnicanalidad/AplicationServer/WSClientes0045 -> Consulta identificacion cliente (Declarada pero no usada) UMPClientes0020 -> ConsultaInformacionCliente01 -> 067050 -> Consulta información basica del cliente UMPClientes0003 -> ConsultarContactoNotificacion01 -> TX067186 -> Consulta contacto transaccional del cliente UMPClientes0005 -> ActualizarContactoTransaccional31 -> TX067186 -> Actualizar el contacto transaccional del cliente | K39: TXT BANCS | L39: ON-PREMISE | M39: 5 | N39: Alta | O39: SOAP - 8934 SOAP - 8911 REST - 8912 | P39: 2 | Q39: Media | R39: Ninguna | S39: 0 | T39: Baja | U39: Ninguna | W39: Baja | X39: 1386K | Y39: 36.1ms | AB39: Media | AC39: Afecta algunos servicios | AD39: Media | AE39: TRIBU CORES Y TRANSACCIONES TRIBU MEDIOS DE PAGO TRIBU CANALES TRIBU PRODUCTOS COE DE TRANSFORMACIÓN DE PROCESOS Y AUTOMATIZACION TRIBU INTEGRACIONES Y APIS AREA REMESAS AREA MICROFINANZAS | AF39: apim-apimtrans-prod-01 East US ClientContactInformationController; app-core-account-client-contact-info GatewayController; deployment-ws-motor-transferencias-java-* trv-msa-sp-customer; deployment-trv-msa-sp deployment-tcp-custom deployment-one-msa-sp-customer-v*-* NovaController; sge-msa-bc-prab-insurance-management ORQClientes0064.API; deployment-bmn-msa-bs-orqclientes*-* ORQClientes0078.API; deployment-ays-msa-dm-orqclientes*-* ORQClientes0079.API; deployment-tcf-msa-dm-orqclientes*-* ORQTransferencias0006.API; deployment-tna-msa-dm-orqtransferencias*-* ORQTransferencias1021.API; deployment-rms-msa-dm-orqtransferencias*-* WSProductos0239.API; deployment-mfi-msa-dm-wsproductos*-* TransaccionalContactController; ach-msa-customer -> https://10.151.152.109:8912/Omnicanalidad/IntegrationBus/WSClientes0007 TransactionalContactController; tre-msa-customer CustomerIntegrationController; deployment-crd- -> ORQClientes0002 InsuranceControllerImpl; sge-msa-insurance ORQProductos1002 ORQProductos0068 ORQSeguridad0004 ORQSeguridad0021 ORQSeguridad0022 ORQClientes0002 ORQClientes0016 ORQClientes0029 ORQClientes0037 ORQClientes0040 ORQClientes0048 ORQClientes0054 WSBilleteraMovil005 | AG39: Default Web Site:443,8043 (/BPMPichinchaCTA) Default Web Site:443,8043 (/BPMPichinchaSG) Default Web Site:443,8043 (/BPMPichinchaTD) | AH39: 34 | AI39: Alta | AJ39: Ninguno | AK39: Baja | AL39: ConsultarContactoTransaccional01 | AM39: Baja | AN39: =IFERROR(SUM(CHOOSE(MATCH(N39,{"Baja";"Media";"Alta"},0),1,2,3), CHOOSE(MATCH(Q39,{"Baja";"Media";"Alta"},0),1,2,3), CHOOSE(MATCH(T39,{"Baja";"Media";"Alta"},0),1,2,3), CHOOSE(MATCH(W39,{"Baja";"Media";"Alta"},0),1,2,3), CHOOSE(MATCH(AB39,{"Baja";"Media";"Alta"},0),1,2,3), CHOOSE(MATCH(AD39,{"Baja";"Media";"Alta"},0),1,2,3), CHOOSE(MATCH(AI39,{"Baja";"Media";"Alta"},0),1,2,3), CHOOSE(MATCH(AK39,{"Baja";"Media";"Alta"},0),1,2,3), CHOOSE(MATCH(AM39,{"Baja";"Media";"Alta"},0),1,2,3)),0) -> 16 | AO39: =IF(AN39=0,"Pendiente",IF(AN39<=15,"Bajo",IF(AN39<=21,"Medio","Alto"))) -> Medio | AQ39: No se observa transaccionalidad en el servicio WSClientes0045 que es backend a nivel del codigo no se usa la UMPClientes0028 | AR39: =VLOOKUP(A39,#REF!,2,FALSE) -> #REF! | AS39: https://s.icepanel.io/wJSECZOwwNkkW8/7y4b | AT39: https://dev.azure.com/BancoPichinchaEC/adi-especificaciones-tecnicas/_git/adi-doc-tecspec-tribu-integracion-apis?path=/sp%20-%20Soporte/tnd-msa-sp-wsclientes0007 | AU39: sqb-msa-wsclientes0007 - Repos | AV39: 1 | AW39: https://pichincha.atlassian.net/browse/PCBG-383
A40: WSClientes0011 | B40: =CONCATENATE(LOWER(E40),"-msa-sp-",LOWER(A40)) -> tnd-msa-sp-wsclientes0011 | C40: Consulta datos de identificacion del Cliente | D40: TRIBU SEGMENTOS Y NEGOCIOS DIGITALES | E40: =VLOOKUP(D40,Tribus!$A$1:$B$33,2,FALSE) -> tnd | F40: Bus Omnicanalidad | G40: WS | H40: Completado | I40: A Desarrollo | J40: UMPClientes0020 (ConsultaInformacionCliente01) -> TX067050 - Consulta información basica del cliente | K40: TXT BANCS | L40: ON-PREMISE | M40: 1 | N40: Baja | O40: REST, SOAP | P40: 2 | Q40: Media | R40: NO | S40: 0 | T40: Baja | U40: Ninguna | W40: Baja | X40: 3k | Y40: 55ms | AB40: Baja | AC40: Afecta algunos servicios | AD40: Media | AE40: Coe de Transformacion de Procesos y Automatizacion | AF40: ORQClientes0064 ORQClientes0029 | AH40: 2 | AI40: Baja | AJ40: NO | AK40: Baja | AL40: ConsultarDatosIdentificacionCliente01 | AM40: Baja | AN40: =IFERROR(SUM(CHOOSE(MATCH(N40,{"Baja";"Media";"Alta"},0),1,2,3), CHOOSE(MATCH(Q40,{"Baja";"Media";"Alta"},0),1,2,3), CHOOSE(MATCH(T40,{"Baja";"Media";"Alta"},0),1,2,3), CHOOSE(MATCH(W40,{"Baja";"Media";"Alta"},0),1,2,3), CHOOSE(MATCH(AB40,{"Baja";"Media";"Alta"},0),1,2,3), CHOOSE(MATCH(AD40,{"Baja";"Media";"Alta"},0),1,2,3), CHOOSE(MATCH(AI40,{"Baja";"Media";"Alta"},0),1,2,3), CHOOSE(MATCH(AK40,{"Baja";"Media";"Alta"},0),1,2,3), CHOOSE(MATCH(AM40,{"Baja";"Media";"Alta"},0),1,2,3)),0) -> 11 | AO40: =IF(AN40=0,"Pendiente",IF(AN40<=15,"Bajo",IF(AN40<=21,"Medio","Alto"))) -> Bajo | AR40: =VLOOKUP(A40,#REF!,2,FALSE) -> #REF! | AS40: https://s.icepanel.io/wJSECZOwwNkkW8/UBTz | AT40: https://dev.azure.com/BancoPichinchaEC/adi-especificaciones-tecnicas/_git/adi-doc-tecspec-tribu-integracion-apis?path=/sp%20-%20Soporte/tnd-msa-sp-wsclientes0011 | AU40: sqb-msa-wsclientes0011 - Repos | AV40: 1 | AW40: https://pichincha.atlassian.net/browse/PCBG-471
A41: WSClientes0012 | B41: =CONCATENATE(LOWER(E41),"-msa-sp-",LOWER(A41)) -> tnd-msa-sp-wsclientes0012 | C41: Consulta dato demográfico del cliente | D41: TRIBU SEGMENTOS Y NEGOCIOS DIGITALES | E41: =VLOOKUP(D41,Tribus!$A$1:$B$33,2,FALSE) -> tnd | F41: Bus Omnicanalidad | G41: WS | H41: Completado | I41: A Desarrollo | J41: UMPClientes0020 -> ConsultaInformacionCliente01 -> TX067050-> Consulta información basica del cliente | K41: TXT BANCS | L41: ON-PREMISE | M41: 1 | N41: Baja | O41: SOAP - 8934 REST- 8937 | P41: 2 | Q41: Media | R41: Ninguna | S41: 0 | T41: Baja | U41: Ninguna | W41: Baja | X41: 2.34k | Y41: 51.8ms | AB41: Baja | AC41: Afecta algunos servicios | AD41: Media | AF41: ORQClientes0029 ORQClientes0064.API;deployment-bmn-msa-bs-orqclientes*-* | AH41: 2 | AI41: Media | AJ41: Ninguna | AK41: Baja | AL41: ConsultarDatoDemograficoCliente01 | AM41: Baja | AN41: =IFERROR(SUM(CHOOSE(MATCH(N41,{"Baja";"Media";"Alta"},0),1,2,3), CHOOSE(MATCH(Q41,{"Baja";"Media";"Alta"},0),1,2,3), CHOOSE(MATCH(T41,{"Baja";"Media";"Alta"},0),1,2,3), CHOOSE(MATCH(W41,{"Baja";"Media";"Alta"},0),1,2,3), CHOOSE(MATCH(AB41,{"Baja";"Media";"Alta"},0),1,2,3), CHOOSE(MATCH(AD41,{"Baja";"Media";"Alta"},0),1,2,3), CHOOSE(MATCH(AI41,{"Baja";"Media";"Alta"},0),1,2,3), CHOOSE(MATCH(AK41,{"Baja";"Media";"Alta"},0),1,2,3), CHOOSE(MATCH(AM41,{"Baja";"Media";"Alta"},0),1,2,3)),0) -> 12 | AO41: =IF(AN41=0,"Pendiente",IF(AN41<=15,"Bajo",IF(AN41<=21,"Medio","Alto"))) -> Bajo | AR41: =VLOOKUP(A41,#REF!,2,FALSE) -> #REF! | AS41: https://s.icepanel.io/wJSECZOwwNkkW8/IS9I | AT41: https://dev.azure.com/BancoPichinchaEC/adi-especificaciones-tecnicas/_git/adi-doc-tecspec-tribu-integracion-apis?path=/sp%20-%20Soporte/tnd-msa-sp-wsclientes0012 | AU41: sqb-msa-wsclientes0012 - Repos | AV41: 1 | AW41: https://pichincha.atlassian.net/browse/PCBG-472
A42: WSClientes0013 | B42: =CONCATENATE(LOWER(E42),"-msa-sp-",LOWER(A42)) -> tnd-msa-sp-wsclientes0013 | C42: Servicio que permite reutilizar la funcionalidad de consultar información de localización del cliente. | D42: TRIBU SEGMENTOS Y NEGOCIOS DIGITALES | E42: =VLOOKUP(D42,Tribus!$A$1:$B$33,2,FALSE) -> tnd | F42: Bus Omnicanalidad | G42: WS | H42: Completado | I42: A Desarrollo | J42: UMPClientes0020 -> Consulta información basica del cliente mediante TX067050. TX067050 -> Consulta el CIF del cliente. opción: 2 21 18 17 15 14 | K42: TXT BANCS | L42: ON-PREMISE | M42: 1 | N42: Baja | O42: SOAP - 8934 | P42: 1 | Q42: Baja | R42: Ninguna | S42: 0 | T42: Baja | U42: Ninguna | W42: Baja | X42: 2.68k | Y42: 460 ms | AB42: Baja | AC42: Afecta algunos servicios | AD42: Media | AF42: ORQClientes0029 ORQClientes0064.API ORQClientes*.API.dll deployment-bmn-msa-bs-orqclientes*-* | AG42: N/A | AH42: 2 | AI42: Media | AJ42: Ninguno | AK42: Baja | AL42: ConsultarDatosLocalizacionCliente01 | AM42: Baja | AN42: =IFERROR(SUM(CHOOSE(MATCH(N42,{"Baja";"Media";"Alta"},0),1,2,3), CHOOSE(MATCH(Q42,{"Baja";"Media";"Alta"},0),1,2,3), CHOOSE(MATCH(T42,{"Baja";"Media";"Alta"},0),1,2,3), CHOOSE(MATCH(W42,{"Baja";"Media";"Alta"},0),1,2,3), CHOOSE(MATCH(AB42,{"Baja";"Media";"Alta"},0),1,2,3), CHOOSE(MATCH(AD42,{"Baja";"Media";"Alta"},0),1,2,3), CHOOSE(MATCH(AI42,{"Baja";"Media";"Alta"},0),1,2,3), CHOOSE(MATCH(AK42,{"Baja";"Media";"Alta"},0),1,2,3), CHOOSE(MATCH(AM42,{"Baja";"Media";"Alta"},0),1,2,3)),0) -> 11 | AO42: =IF(AN42=0,"Pendiente",IF(AN42<=15,"Bajo",IF(AN42<=21,"Medio","Alto"))) -> Bajo | AR42: =VLOOKUP(A42,#REF!,2,FALSE) -> #REF! | AS42: https://app.icepanel.io/landscapes/w71QNHgfDvF79GrSuA3r/versions/latest/diagrams/editor?diagram=DgtCdHrjDp&model=w4gvcsly0h&overlay_tab=tags&x1=-489.6&y1=-24&x2=2384.2&y2=1448 | AT42: https://dev.azure.com/BancoPichinchaEC/adi-especificaciones-tecnicas/_git/adi-doc-tecspec-tribu-integracion-apis?path=/sp%20-%20Soporte/tnd-msa-sp-wsclientes0013 | AU42: sqb-msa-wsclientes0013 - Repos | AV42: 1 | AW42: https://pichincha.atlassian.net/browse/PCBG-473
A43: WSClientes0015 | B43: =CONCATENATE(LOWER(E43),"-msa-sp-",LOWER(A43)) -> tnd-msa-sp-wsclientes0015 | C43: Microservicio que consulta, crea y elimina las direcciones del cliente PRY_CENTRO_DIGITAL | D43: TRIBU SEGMENTOS Y NEGOCIOS DIGITALES | E43: =VLOOKUP(D43,Tribus!$A$1:$B$33,2,FALSE) -> tnd | F43: Bus Omnicanalidad | G43: WS | H43: Completado | I43: A Desarrollo | J43: UMPClientes0064 -> OperacionLocalizacion51 -> TX061404 -> Consulta la localizacion de un cliente UMPClientes0175 -> OperacionGeolocalizacion52 -> TX062130 -> Consulta, actualiza, crea y elimina las geolocalizacion UMPClientes0066 -> OperacionCorrespondenciaLocalizacion51 -> TX062120 -> Consulta la correspondencia de un cliente UMPClientes0020 -> ConsultaInformacionCliente01 -> TX067050 -> Consulta información basica del cliente UMPClientes0063 -> OperacionDireccion51 -> TX067010 -> Consulta la localizacion de un cliente | K43: TXT BANCS | L43: ON-PREMISE | M43: 5 | N43: Alta | O43: SOAP - 8934 | P43: 1 | Q43: Baja | R43: Ninguna | S43: 0 | T43: Baja | U43: Ninguna | W43: Baja | X43: 102,8K | Y43: 75.9ms | AB43: Media | AC43: Afecta algunos servicios | AD43: Media | AF43: ORQClientes0062 ORQClientes0072 | AH43: 2 | AI43: Media | AJ43: Ninguno | AK43: Baja | AL43: OperacionLocalizacion51 OperacionGeolocalizacion52 OperacionCorrespondenciaLocalizacion51 ConsultaInformacionCliente01 OperacionDireccion51 | AM43: Alta | AN43: =IFERROR(SUM(CHOOSE(MATCH(N43,{"Baja";"Media";"Alta"},0),1,2,3), CHOOSE(MATCH(Q43,{"Baja";"Media";"Alta"},0),1,2,3), CHOOSE(MATCH(T43,{"Baja";"Media";"Alta"},0),1,2,3), CHOOSE(MATCH(W43,{"Baja";"Media";"Alta"},0),1,2,3), CHOOSE(MATCH(AB43,{"Baja";"Media";"Alta"},0),1,2,3), CHOOSE(MATCH(AD43,{"Baja";"Media";"Alta"},0),1,2,3), CHOOSE(MATCH(AI43,{"Baja";"Media";"Alta"},0),1,2,3), CHOOSE(MATCH(AK43,{"Baja";"Media";"Alta"},0),1,2,3), CHOOSE(MATCH(AM43,{"Baja";"Media";"Alta"},0),1,2,3)),0) -> 16 | AO43: =IF(AN43=0,"Pendiente",IF(AN43<=15,"Bajo",IF(AN43<=21,"Medio","Alto"))) -> Medio | AR43: =VLOOKUP(A43,#REF!,2,FALSE) -> #REF! | AS43: https://app.icepanel.io/landscapes/w71QNHgfDvF79GrSuA3r/versions/latest/diagrams/editor?diagram=tQFeLLP7bp&model=RNAuXBAYB9&overlay_tab=tags&x1=-184&y1=-160.4&x2=3065.5&y2=1280.4 | AT43: https://dev.azure.com/BancoPichinchaEC/adi-especificaciones-tecnicas/_git/adi-doc-tecspec-tribu-integracion-apis?path=/sp%20-%20Soporte/tnd-msa-sp-wsclientes0015 | AU43: sqb-msa-wsclientes0015 - Repos | AV43: 1 | AW43: https://pichincha.atlassian.net/browse/PCBG-384
A44: WSClientes0020 | B44: =CONCATENATE(LOWER(E44),"-msa-sp-",LOWER(A44)) -> tnd-msa-sp-wsclientes0020 | C44: Microservicio que permite Actualizar el contacto transaccional en Bancs | D44: TRIBU SEGMENTOS Y NEGOCIOS DIGITALES | E44: =VLOOKUP(D44,Tribus!$A$1:$B$33,2,FALSE) -> tnd | F44: Bus Omnicanalidad | G44: WS | H44: Completado | I44: A Desarrollo | J44: UMPClientes0003 -> ConsultarContactoNotificacion -> TX067186 -> Consulta contacto transaccional del cliente UMPClientes0005 -> ActualizarContactoTransacciona -> TX067186 -> Actualizar el contacto transaccional del cliente | K44: TXT BANCS | L44: ON-PREMISE | M44: 2 | N44: Media | O44: SOAP - 8934 | P44: 1 | Q44: Baja | R44: Ninguna | S44: 0 | T44: Baja | U44: Ninguna | W44: Baja | X44: 13.8K | Y44: 49.5ms | AB44: Baja | AC44: Afecta algunos servicios | AD44: Media | AE44: TRIBU CANALES TRIBU PRODUCTOS COE_TRANSFORMACION_PROCESOS TRIBU SEGMENTOS Y NEGOCIOS DIGITALES TRIBU_DE_UNA | AF44: ORQClientes0004 ORQClientes0038 ORQClientes0048 ORQClientes0050 ORQProductos0052 | AH44: 5 | AI44: Alta | AJ44: Ninguno | AK44: Baja | AL44: ActualizarContactoTransaccional31 | AM44: Baja | AN44: =IFERROR(SUM(CHOOSE(MATCH(N44,{"Baja";"Media";"Alta"},0),1,2,3), CHOOSE(MATCH(Q44,{"Baja";"Media";"Alta"},0),1,2,3), CHOOSE(MATCH(T44,{"Baja";"Media";"Alta"},0),1,2,3), CHOOSE(MATCH(W44,{"Baja";"Media";"Alta"},0),1,2,3), CHOOSE(MATCH(AB44,{"Baja";"Media";"Alta"},0),1,2,3), CHOOSE(MATCH(AD44,{"Baja";"Media";"Alta"},0),1,2,3), CHOOSE(MATCH(AI44,{"Baja";"Media";"Alta"},0),1,2,3), CHOOSE(MATCH(AK44,{"Baja";"Media";"Alta"},0),1,2,3), CHOOSE(MATCH(AM44,{"Baja";"Media";"Alta"},0),1,2,3)),0) -> 13 | AO44: =IF(AN44=0,"Pendiente",IF(AN44<=15,"Bajo",IF(AN44<=21,"Medio","Alto"))) -> Bajo | AR44: =VLOOKUP(A44,#REF!,2,FALSE) -> #REF! | AS44: https://s.icepanel.io/wJSECZOwwNkkW8/QOc8 | AT44: https://dev.azure.com/BancoPichinchaEC/adi-especificaciones-tecnicas/_git/adi-doc-tecspec-tribu-integracion-apis?path=/sp%20-%20Soporte/tnd-msa-sp-wsclientes0020 | AU44: sqb-msa-wsclientes0020 - Repos | AV44: 1 | AW44: https://pichincha.atlassian.net/browse/PCBG-385
A45: WSClientes0024 | B45: =CONCATENATE(LOWER(E45),"-msa-sp-",LOWER(A45)) -> tnd-msa-sp-wsclientes0024 | C45: Servicio que consulta la información básica del cliente. | D45: TRIBU SEGMENTOS Y NEGOCIOS DIGITALES | E45: =VLOOKUP(D45,Tribus!$A$1:$B$33,2,FALSE) -> tnd | F45: Bus Omnicanalidad | G45: WS | H45: Completado | I45: A Desarrollo | J45: UMPClientes0002 -> ConsultarInformacionBasica01 -> TX060480 -> Consulta el CIF del cliente mdw-msa-sp-tmp-customer --> Stratio | K45: TXT Bancs openshift 4 | L45: ON-PREMISE | M45: 2 | N45: Media | O45: SOAP | P45: 1 | Q45: Baja | R45: Mapeo hacia MSA de OPS mdw-msa-sp-tmp-customer | S45: 1 | T45: Media | U45: Ninguna | W45: Baja | X45: 2.634M | Y45: 31ms | AB45: Alta | AC45: Afecta algunos servicios | AD45: Media | AE45: TRIBU PRODUCTOS | AF45: ORQClientes0005 ORQClientes0003 ORQClientes0008 ORQClientes0019 ORQClientes0037 ORQClientes0048 ORQClientes0050 ORQClientes0053 ORQClientes0071 ORQProductos0036 ORQProductos0038 ORQProductos0062 ORQProductos0068 WSProductos0183.API - /api/v1/clients/{idCliente}/accounts/{account}/cashdeposit WSProductos0184.API - /api/v1/clients/{idCliente}/accounts/0121/cashwithdrawal ORQTransferencias1016.API - /api/v1/TransferenciasInterbancarias/EjecutarTransferenciaInterbancarias11 ORQTransferencias1005.API - /api/v1/TransferenciasDirectas/EjecutarTransferenciaDirecta15 ORQPagos1002.API - /api/v1/PagoTarjetaOtrosBancos/EjecutarPagoTarjetaOtroBanco11 WSTecnicos0038 (eventHandler Framework Omnicanal) ORQSeguridad0004 ORQSeguridad0021 cta-customers-core - /getCustomerInformation ach-msa-customer - /getUserValidation onb-msa-insurance - /api/v1/onboard/insurance/validate-offerable-product onb-msa-firc - /api/v1/firc/customer/{idCliente}/{tipoId} onb-msa-checking-customer - /api/v1/onboard/checking-customers | AG45: BIZAGI_IAAS https://autogestiontd.bpichincha.com/ Gestor Documental IBM FileNet https://gestiondocumental.pichincha.com/navigator/?desktop=***** | AH45: 28 | AI45: Alta | AJ45: Ninguno | AK45: Baja | AL45: ConsultarIdentificacion01 | AM45: Baja | AN45: =IFERROR(SUM(CHOOSE(MATCH(N45,{"Baja";"Media";"Alta"},0),1,2,3), CHOOSE(MATCH(Q45,{"Baja";"Media";"Alta"},0),1,2,3), CHOOSE(MATCH(T45,{"Baja";"Media";"Alta"},0),1,2,3), CHOOSE(MATCH(W45,{"Baja";"Media";"Alta"},0),1,2,3), CHOOSE(MATCH(AB45,{"Baja";"Media";"Alta"},0),1,2,3), CHOOSE(MATCH(AD45,{"Baja";"Media";"Alta"},0),1,2,3), CHOOSE(MATCH(AI45,{"Baja";"Media";"Alta"},0),1,2,3), CHOOSE(MATCH(AK45,{"Baja";"Media";"Alta"},0),1,2,3), CHOOSE(MATCH(AM45,{"Baja";"Media";"Alta"},0),1,2,3)),0) -> 16 | AO45: =IF(AN45=0,"Pendiente",IF(AN45<=15,"Bajo",IF(AN45<=21,"Medio","Alto"))) -> Medio | AQ45: No se requiere migrar, validar reapuntamiento de MPGW hacia msa mdw-msa-sp-tmp-customer en caso de que legacy no soporte la nueva entrada y para los MSA y API de OPS el apuntamiento se haga directo al msa mdw-msa-sp-tmp-customer | AR45: =VLOOKUP(A45,#REF!,2,FALSE) -> #REF! | AS45: https://s.icepanel.io/wJSECZOwwNkkW8/Tf15 | AT45: https://dev.azure.com/BancoPichinchaEC/adi-especificaciones-tecnicas/_git/adi-doc-tecspec-tribu-integracion-apis?path=/sp%20-%20Soporte/tnd-msa-sp-wsclientes0024 | AU45: sqb-msa-wsclientes0024 - Repos | AV45: 1 | AW45: https://pichincha.atlassian.net/browse/PCBG-386
A46: WSClientes0025 | B46: =CONCATENATE(LOWER(E46),"-msa-sp-",LOWER(A46)) -> tpr-msa-sp-wsclientes0025 | C46: Consulta informacion de cheque protestado | D46: TRIBU PRODUCTOS | E46: =VLOOKUP(D46,Tribus!$A$1:$B$33,2,FALSE) -> tpr | F46: Bus Omnicanalidad | G46: WS | H46: Completado | I46: A Desarrollo | J46: UMPClientes0010 -> ConsultarInformacionChequeProtestado01->051059 | K46: TXT BANCS | L46: ON-PREMISE | M46: 1 | N46: Baja | O46: SOAP | P46: 1 | Q46: Baja | R46: NO | S46: 0 | T46: Baja | U46: Ninguna | W46: Baja | X46: 832/ Diario | Y46: 45ms | AB46: Baja | AC46: ORQClientes0025 | AD46: Media | AE46: BPM Tribu de Administracion de Credito Tribu Retail | AF46: ORQClientes0025 | AH46: 1 | AI46: Baja | AJ46: NO | AK46: Baja | AL46: onsultarInformacionChequeProtestado01 | AM46: Baja | AN46: =IFERROR(SUM(CHOOSE(MATCH(N46,{"Baja";"Media";"Alta"},0),1,2,3), CHOOSE(MATCH(Q46,{"Baja";"Media";"Alta"},0),1,2,3), CHOOSE(MATCH(T46,{"Baja";"Media";"Alta"},0),1,2,3), CHOOSE(MATCH(W46,{"Baja";"Media";"Alta"},0),1,2,3), CHOOSE(MATCH(AB46,{"Baja";"Media";"Alta"},0),1,2,3), CHOOSE(MATCH(AD46,{"Baja";"Media";"Alta"},0),1,2,3), CHOOSE(MATCH(AI46,{"Baja";"Media";"Alta"},0),1,2,3), CHOOSE(MATCH(AK46,{"Baja";"Media";"Alta"},0),1,2,3), CHOOSE(MATCH(AM46,{"Baja";"Media";"Alta"},0),1,2,3)),0) -> 10 | AO46: =IF(AN46=0,"Pendiente",IF(AN46<=15,"Bajo",IF(AN46<=21,"Medio","Alto"))) -> Bajo | AQ46: Solicitar ConsultarInformacionChequeProtestado01_Compute.esql del servidor 10.70.128.112 Se cierra el servcio 09/12/25 | AR46: =VLOOKUP(A46,#REF!,2,FALSE) -> #REF! | AS46: https://s.icepanel.io/wJSECZOwwNkkW8/XbGe | AT46: https://dev.azure.com/BancoPichinchaEC/adi-especificaciones-tecnicas/_git/adi-doc-tecspec-tribu-integracion-apis?path=/sp%20-%20Soporte/tpr-msa-sp-wsclientes0025 | AU46: https://bancopichincha.service-now.com/esc?id=ticket&table=sc_req_item&sys_id=90ef38c48779f2501ec985580cbb3509&view=sp | AV46: 1 | AW46: https://pichincha.atlassian.net/browse/PCBG-474
A47: WSClientes0027 | B47: =CONCATENATE(LOWER(E47),"-msa-sp-",LOWER(A47)) -> tnd-msa-sp-wsclientes0027 | C47: Microservicio que consulta la correspondencia de un cliente | D47: TRIBU SEGMENTOS Y NEGOCIOS DIGITALES | E47: =VLOOKUP(D47,Tribus!$A$1:$B$33,2,FALSE) -> tnd | F47: Bus Omnicanalidad | G47: WS | H47: Completado | I47: A Desarrollo | J47: UMPClientes0078 -> OperacionIdentificacionCliente51 -> TX067153 -> Consulta información de identificación del cliente UMPClientes0066 -> OperacionCorrespondenciaLocalizacion51 -> TX062120 -> Consulta la correspondencia de un cliente | K47: TXT BANCS | L47: ON-PREMISE | M47: 2 | N47: Media | O47: SOAP - 8934 | P47: 1 | Q47: Baja | R47: Ninguna | S47: 0 | T47: Baja | U47: Ninguna | W47: Baja | X47: 114,6k | Y47: 48.6ms | AB47: Media | AC47: Afecta algunos servicios | AD47: Media | AF47: ORQClientes0048 ORQClientes0063 | AH47: 2 | AI47: Media | AJ47: Ninguno | AK47: Baja | AL47: OperacionCorrespondenciaLocalizacion51 | AM47: Baja | AN47: =IFERROR(SUM(CHOOSE(MATCH(N47,{"Baja";"Media";"Alta"},0),1,2,3), CHOOSE(MATCH(Q47,{"Baja";"Media";"Alta"},0),1,2,3), CHOOSE(MATCH(T47,{"Baja";"Media";"Alta"},0),1,2,3), CHOOSE(MATCH(W47,{"Baja";"Media";"Alta"},0),1,2,3), CHOOSE(MATCH(AB47,{"Baja";"Media";"Alta"},0),1,2,3), CHOOSE(MATCH(AD47,{"Baja";"Media";"Alta"},0),1,2,3), CHOOSE(MATCH(AI47,{"Baja";"Media";"Alta"},0),1,2,3), CHOOSE(MATCH(AK47,{"Baja";"Media";"Alta"},0),1,2,3), CHOOSE(MATCH(AM47,{"Baja";"Media";"Alta"},0),1,2,3)),0) -> 13 | AO47: =IF(AN47=0,"Pendiente",IF(AN47<=15,"Bajo",IF(AN47<=21,"Medio","Alto"))) -> Bajo | AR47: =VLOOKUP(A47,#REF!,2,FALSE) -> #REF! | AS47: https://s.icepanel.io/wJSECZOwwNkkW8/tar5 | AT47: https://dev.azure.com/BancoPichinchaEC/adi-especificaciones-tecnicas/_git/adi-doc-tecspec-tribu-integracion-apis?path=/sp%20-%20Soporte/tnd-msa-sp-wsclientes0027 | AU47: https://dev.azure.com/BancoPichinchaEC/tpl-bus-omnicanal/_git/sqb-msa-wsclientes0027 | AV47: 1 | AW47: https://pichincha.atlassian.net/browse/PCBG-387
A48: WSClientes0028 | B48: =CONCATENATE(LOWER(E48),"-msa-sp-",LOWER(A48)) -> tnd-msa-sp-wsclientes0028 | C48: Consulta y actualiza datos de localización como medios de contacto del cliente (celular, emai) | D48: TRIBU SEGMENTOS Y NEGOCIOS DIGITALES | E48: =VLOOKUP(D48,Tribus!$A$1:$B$33,2,FALSE) -> tnd | F48: Bus Omnicanalidad | G48: WS | H48: Completado | I48: A Desarrollo | J48: ActualizarCelularLocalizacion34 → - UMPClientes0020(ConsultaInformacionCliente01) → TX067050 opcion:14 - UMPClientes0034(ActualizarCelularLocalizacionCliente31) → TX067125 option21:A ActualizarEmailLocalizacion33 → - UMPClientes0020(ConsultaInformacionCliente01) → TX067050 opcioni:15 - UMPClientes0033(ActualizarEmailLocalizacionCliente31) → TX067126 option21:A ConsultarCelularLocalizacion01 → - UMPClientes0020(ConsultaInformacionCliente01) → TX067050 opcion:14 ConsultarEmailLocalizacion02 → - UMPClientes0020(ConsultaInformacionCliente01) → TX067050 opcion:15 | K48: BANCS | L48: ON-PREMISE | M48: 1 | N48: Baja | O48: SOAP | P48: 1 | Q48: Baja | R48: Ninguna | S48: 0 | T48: Baja | U48: Ninguna | V48: No aplica | W48: Baja | X48: 10.6k | Y48: 42.8 ms | Z48: 12.9 | AA48: 64 | AB48: Baja | AC48: Si puede ser probado por las app | AD48: Media | AE48: TRIBU SEGMENTOS Y NEGOCIOS DIGITALES COE CIBERSEGURIDAD | AF48: ORQClientes0050 | AG48: no aplica | AH48: 1 | AI48: Baja | AJ48: 0 | AK48: Baja | AL48: ConsultarCelularLocalizacion01 ConsultarEmailLocalizacion02 ActualizarCelularLocalizacion34 ActualizarEmailLocalizacion33 | AM48: Alta | AN48: =IFERROR(SUM(CHOOSE(MATCH(N48,{"Baja";"Media";"Alta"},0),1,2,3), CHOOSE(MATCH(Q48,{"Baja";"Media";"Alta"},0),1,2,3), CHOOSE(MATCH(T48,{"Baja";"Media";"Alta"},0),1,2,3), CHOOSE(MATCH(W48,{"Baja";"Media";"Alta"},0),1,2,3), CHOOSE(MATCH(AB48,{"Baja";"Media";"Alta"},0),1,2,3), CHOOSE(MATCH(AD48,{"Baja";"Media";"Alta"},0),1,2,3), CHOOSE(MATCH(AI48,{"Baja";"Media";"Alta"},0),1,2,3), CHOOSE(MATCH(AK48,{"Baja";"Media";"Alta"},0),1,2,3), CHOOSE(MATCH(AM48,{"Baja";"Media";"Alta"},0),1,2,3)),0) -> 12 | AO48: =IF(AN48=0,"Pendiente",IF(AN48<=15,"Bajo",IF(AN48<=21,"Medio","Alto"))) -> Bajo | AQ48: Utilizado para actualizar datos del contacto transaccional en línea o delay | AR48: =VLOOKUP(A48,#REF!,2,FALSE) -> #REF! | AS48: https://app.icepanel.io/landscapes/w71QNHgfDvF79GrSuA3r/versions/latest/diagrams/editor?domain=z5rnxbake2&diagram=hFxr4XJYAz&model=6VcKYw8fMd&overlay_tab=tags&x1=-346.9&y1=-307.7&x2=1979.1&y2=924.8 | AT48: https://dev.azure.com/BancoPichinchaEC/adi-especificaciones-tecnicas/_git/adi-doc-tecspec-tribu-integracion-apis?path=/sp%20-%20Soporte/tnd-msa-sp-wsclientes0028 | AU48: https://dev.azure.com/BancoPichinchaEC/tpl-bus-omnicanal/_git/sqb-msa-wsclientes0028 | AV48: 1 | AW48: https://pichincha.atlassian.net/browse/PCBG-475
A49: WSClientes0029 | B49: =CONCATENATE(LOWER(E49),"-msa-sp-",LOWER(A49)) -> tnd-msa-sp-wsclientes0029 | C49: Actualiza datos demograficos del cliente | D49: TRIBU SEGMENTOS Y NEGOCIOS DIGITALES | E49: =VLOOKUP(D49,Tribus!$A$1:$B$33,2,FALSE) -> tnd | F49: Bus Omnicanalidad | G49: WS | H49: Completado | I49: A Desarrollo | J49: UMPClientes0011 -> ActualizarDatosDemograficos31 -> TX061406 -> Cargar los datos demograficos del cliente en la salida del servicio | K49: TXT BANCS | L49: ON-PREMISE | M49: 1 | N49: Baja | O49: SOAP - 8934 | P49: 1 | Q49: Baja | R49: Ninguna | S49: 0 | T49: Baja | U49: Ninguna | W49: Baja | X49: 2.94k | Y49: 69.8ms | AB49: Baja | AC49: Afecta algunos servicios | AD49: Media | AF49: ORQClientes0038 | AH49: 1 | AI49: Baja | AJ49: Ninguna | AK49: Baja | AL49: ActualizarDatosDemograficos31 | AM49: Baja | AN49: =IFERROR(SUM(CHOOSE(MATCH(N49,{"Baja";"Media";"Alta"},0),1,2,3), CHOOSE(MATCH(Q49,{"Baja";"Media";"Alta"},0),1,2,3), CHOOSE(MATCH(T49,{"Baja";"Media";"Alta"},0),1,2,3), CHOOSE(MATCH(W49,{"Baja";"Media";"Alta"},0),1,2,3), CHOOSE(MATCH(AB49,{"Baja";"Media";"Alta"},0),1,2,3), CHOOSE(MATCH(AD49,{"Baja";"Media";"Alta"},0),1,2,3), CHOOSE(MATCH(AI49,{"Baja";"Media";"Alta"},0),1,2,3), CHOOSE(MATCH(AK49,{"Baja";"Media";"Alta"},0),1,2,3), CHOOSE(MATCH(AM49,{"Baja";"Media";"Alta"},0),1,2,3)),0) -> 10 | AO49: =IF(AN49=0,"Pendiente",IF(AN49<=15,"Bajo",IF(AN49<=21,"Medio","Alto"))) -> Bajo | AR49: =VLOOKUP(A49,#REF!,2,FALSE) -> #REF! | AS49: https://s.icepanel.io/wJSECZOwwNkkW8/Q6FF | AT49: https://dev.azure.com/BancoPichinchaEC/adi-especificaciones-tecnicas/_git/adi-doc-tecspec-tribu-integracion-apis?path=/sp%20-%20Soporte/tnd-msa-sp-wsclientes0029 | AU49: https://dev.azure.com/BancoPichinchaEC/tpl-bus-omnicanal/_git/sqb-msa-wsclientes0029 | AV49: 1 | AW49: https://pichincha.atlassian.net/browse/PCBG-476
A50: WSClientes0030 | B50: =CONCATENATE(LOWER(E50),"-msa-sp-",LOWER(A50)) -> tnd-msa-sp-wsclientes0030 | C50: Consulta contacto Transaccional celular , mail | D50: TRIBU SEGMENTOS Y NEGOCIOS DIGITALES | E50: =VLOOKUP(D50,Tribus!$A$1:$B$33,2,FALSE) -> tnd | F50: Bus Omnicanalidad | G50: WS | H50: Completado | I50: A Desarrollo | J50: Consume : UMPClientes0002 - > Informacion Basica -> TX060480 UMPClientes0003 -> Consulta Contacto TX -> TX067186 Transaccional UMPClientes0028 -> ConsultarIdentificacion01 (CIF x Identificacion) -> "http://datapowerprod.uio.bpichincha.com:7180/IntegrationBus/soap/WSConsultaIdentificacion001" cuando servicio.tipoConsulta = '1' | K50: TXT BANCS BUS SOPORTE -> descartado porq no se ve transaccionalidad | L50: ON-PREMISE | M50: 3 | N50: Alta | O50: SOAP - 8934 | P50: 1 | Q50: Baja | R50: NO | S50: 0 | T50: Baja | U50: Ninguna | W50: Baja | X50: 240TPM - 21.6K/Diario | Y50: 100ms | AB50: Baja | AC50: ORQClientes0050 ORQProductos1001 ORQProductos0048 ORQTecnicos0002 ORQClientes0004 ORQProductos0042 | AD50: Media | AE50: Tribu Negocios digitales Tribu Canales Digitales | AF50: ORQClientes0050 ORQProductos1001 ORQProductos0048 ORQTecnicos0002 ORQClientes0004 ORQProductos0042 | AH50: 6 | AI50: Alta | AJ50: NO | AK50: Baja | AL50: ConsultarContactoNotificacion01 | AM50: Baja | AN50: =IFERROR(SUM(CHOOSE(MATCH(N50,{"Baja";"Media";"Alta"},0),1,2,3), CHOOSE(MATCH(Q50,{"Baja";"Media";"Alta"},0),1,2,3), CHOOSE(MATCH(T50,{"Baja";"Media";"Alta"},0),1,2,3), CHOOSE(MATCH(W50,{"Baja";"Media";"Alta"},0),1,2,3), CHOOSE(MATCH(AB50,{"Baja";"Media";"Alta"},0),1,2,3), CHOOSE(MATCH(AD50,{"Baja";"Media";"Alta"},0),1,2,3), CHOOSE(MATCH(AI50,{"Baja";"Media";"Alta"},0),1,2,3), CHOOSE(MATCH(AK50,{"Baja";"Media";"Alta"},0),1,2,3), CHOOSE(MATCH(AM50,{"Baja";"Media";"Alta"},0),1,2,3)),0) -> 14 | AO50: =IF(AN50=0,"Pendiente",IF(AN50<=15,"Bajo",IF(AN50<=21,"Medio","Alto"))) -> Bajo | AQ50: soloc uando servicio.tipoConsulta = '1' se consume url de bus soporte, se descarta el bus soporte | AR50: =VLOOKUP(A50,#REF!,2,FALSE) -> #REF! | AS50: https://s.icepanel.io/wJSECZOwwNkkW8/UdN1 | AT50: https://dev.azure.com/BancoPichinchaEC/adi-especificaciones-tecnicas/_git/adi-doc-tecspec-tribu-integracion-apis?path=/sp%20-%20Soporte/tnd-msa-sp-wsclientes0030 | AU50: https://dev.azure.com/BancoPichinchaEC/tpl-bus-omnicanal/_git/sqb-msa-wsclientes0030 | AV50: 1 | AW50: Revisar llama a bus soporte
A51: WSClientes0037 | B51: =CONCATENATE(LOWER(E51),"-msa-sp-",LOWER(A51)) -> tnd-msa-sp-wsclientes0037 | C51: [ConsultarClienteRegistroCivil01] Servicio para consultar detalle del cliente del registro civil | D51: TRIBU SEGMENTOS Y NEGOCIOS DIGITALES | E51: =VLOOKUP(D51,Tribus!$A$1:$B$33,2,FALSE) -> tnd | F51: Bus Omnicanalidad | G51: WS | H51: Completado | I51: A Desarrollo | J51: UMPClientes0043 (ConsultarRegistroCivilCliente01) -> WSRegistroCivil002 - Consultar detalle del cliente del registro civil URL WSRegistroCivil002: http://datapowertest.bp.bpichincha.com:7180/IntegrationBus/soap/WSRegistroCivil002 UMPClientes0145 (ConsultarRegistroCivilCodigoDactilar01) -> WSRegistroCivil004 Consultar el Registro Civil del Codigo Dactilar URL WSRegistroCivil004: http://datapowertest.bp.bpichincha.com:7180/IntegrationBus/soap/WSRegistroCivil004 | K51: BUS SOPORTE -> solo un metodo | L51: BDD REGISTRO CIVIL ONPREMISE ON-PREMISE | M51: 2 | N51: Media | O51: SOAP - 8934 | P51: 1 | Q51: Baja | R51: Ninguna | S51: 0 | T51: Baja | U51: Ninguna | W51: Baja | X51: 500 | Y51: 1.13 s | AB51: Media | AC51: Afecta algunos servicios | AD51: Media | AF51: ORQClientes0008 | AG51: N/A | AH51: 1 | AI51: Baja | AJ51: Ninguno | AK51: Baja | AL51: ConsultarClienteRegistroCivil01 ConsultarRegistroCivilCodigoDactilar02 ** deprecado | AM51: Media | AN51: =IFERROR(SUM(CHOOSE(MATCH(N51,{"Baja";"Media";"Alta"},0),1,2,3), CHOOSE(MATCH(Q51,{"Baja";"Media";"Alta"},0),1,2,3), CHOOSE(MATCH(T51,{"Baja";"Media";"Alta"},0),1,2,3), CHOOSE(MATCH(W51,{"Baja";"Media";"Alta"},0),1,2,3), CHOOSE(MATCH(AB51,{"Baja";"Media";"Alta"},0),1,2,3), CHOOSE(MATCH(AD51,{"Baja";"Media";"Alta"},0),1,2,3), CHOOSE(MATCH(AI51,{"Baja";"Media";"Alta"},0),1,2,3), CHOOSE(MATCH(AK51,{"Baja";"Media";"Alta"},0),1,2,3), CHOOSE(MATCH(AM51,{"Baja";"Media";"Alta"},0),1,2,3)),0) -> 13 | AO51: =IF(AN51=0,"Pendiente",IF(AN51<=15,"Bajo",IF(AN51<=21,"Medio","Alto"))) -> Bajo | AQ51: ConsultarRegistroCivilCodigoDactilar02 ** deprecado, el metodo ya no se consume, solo debe migrarse el wsregistrocivil002 | AR51: =VLOOKUP(A51,#REF!,2,FALSE) -> #REF! | AS51: https://app.icepanel.io/landscapes/w71QNHgfDvF79GrSuA3r/versions/latest/diagrams/editor?diagram=LaJkraN0Q6&model=xxjvq38yeak&overlay_tab=tags&x1=-693.6&y1=-88&x2=2445.7&y2=1520 | AT51: https://dev.azure.com/BancoPichinchaEC/adi-especificaciones-tecnicas/_git/adi-doc-tecspec-tribu-integracion-apis?path=/sp%20-%20Soporte/tnd-msa-sp-wsclientes0037 | AU51: https://dev.azure.com/BancoPichinchaEC/tpl-bus-omnicanal/_git/sqb-msa-wsclientes0037 | AV51: 1 | AW51: REVISAR VA A BUS SOPORTE
A52: WSClientes0038 | B52: =CONCATENATE(LOWER(E52),"-msa-sp-",LOWER(A52)) -> tnd-msa-sp-wsclientes0038 | C52: Consultar detalles adicionales y economicos del cliente | D52: TRIBU SEGMENTOS Y NEGOCIOS DIGITALES | E52: =VLOOKUP(D52,Tribus!$A$1:$B$33,2,FALSE) -> tnd | F52: Bus Omnicanalidad | G52: WS | H52: Completado | I52: A Desarrollo | J52: UMPClientes0020 --> ConsultaInformacionCliente01 --> TX067050 (opc 1, 5, 15, 21) UMPClientes0061 --> ActualizarInfAdicionalCliente31 --> TX067118 UMPClientes0057 --> ActualizarInformacionCliente31 --> TX067116 | K52: TXT Bancs | L52: ON-PREMISE | M52: 3 | N52: Media | O52: SOAP | P52: 1 | Q52: Baja | R52: Ninguna | S52: 0 | T52: Baja | U52: Ninguna | W52: Baja | X52: 268K | Y52: 57ms | AB52: Media | AC52: Afecta algunos servicios | AD52: Media | AF52: ORQClientes0071 ORQClientes0048 ORQClientes0008 ORQClientes0017 ORQClientes0016 ORQClientes0019 ORQClientes0035 ORQClientes0036 ORQClientes0054 ORQClientes0038 ORQProductos0019 ORQProductos0068 ORQProductos0064 | AH52: 13 | AI52: Alta | AJ52: Ninguno | AK52: Baja | AL52: ConsultarDetalleAdicionalesCliente01 OperacionEconomicosCliente52 OperacionEconomicosCliente53 | AM52: Media | AN52: =IFERROR(SUM(CHOOSE(MATCH(N52,{"Baja";"Media";"Alta"},0),1,2,3), CHOOSE(MATCH(Q52,{"Baja";"Media";"Alta"},0),1,2,3), CHOOSE(MATCH(T52,{"Baja";"Media";"Alta"},0),1,2,3), CHOOSE(MATCH(W52,{"Baja";"Media";"Alta"},0),1,2,3), CHOOSE(MATCH(AB52,{"Baja";"Media";"Alta"},0),1,2,3), CHOOSE(MATCH(AD52,{"Baja";"Media";"Alta"},0),1,2,3), CHOOSE(MATCH(AI52,{"Baja";"Media";"Alta"},0),1,2,3), CHOOSE(MATCH(AK52,{"Baja";"Media";"Alta"},0),1,2,3), CHOOSE(MATCH(AM52,{"Baja";"Media";"Alta"},0),1,2,3)),0) -> 15 | AO52: =IF(AN52=0,"Pendiente",IF(AN52<=15,"Bajo",IF(AN52<=21,"Medio","Alto"))) -> Bajo | AR52: =VLOOKUP(A52,#REF!,2,FALSE) -> #REF! | AS52: https://s.icepanel.io/wJSECZOwwNkkW8/ZZ0C | AT52: https://dev.azure.com/BancoPichinchaEC/adi-especificaciones-tecnicas/_git/adi-doc-tecspec-tribu-integracion-apis?path=/sp%20-%20Soporte/tnd-msa-sp-wsclientes0038 | AU52: sqb-msa-wsclientes0038 - Repos | AV52: 1 | AW52: https://pichincha.atlassian.net/browse/PCBG-389
A53: WSClientes0046 | B53: =CONCATENATE(LOWER(E53),"-msa-sp-",LOWER(A53)) -> tnd-msa-sp-wsclientes0046 | C53: Consulta Cliente Virtual | D53: TRIBU SEGMENTOS Y NEGOCIOS DIGITALES | E53: =VLOOKUP(D53,Tribus!$A$1:$B$33,2,FALSE) -> tnd | F53: Bus Omnicanalidad | G53: WS | H53: Completado | I53: A Desarrollo | J53: UMPClientes0020 -> ConsultaInformacionCliente01 -> 067050 UMPClientes0029 -> ConsultarInformacionAsesor01 -> 009600 | K53: TXT BANCS | L53: ON-PREMISE | M53: 2 | N53: Media | O53: SOAP | P53: 1 | Q53: Baja | R53: Ninguna | S53: 0 | T53: Baja | U53: Ninguna | W53: Baja | X53: 210K | Y53: 25.6 ms | AB53: Media | AC53: Independiente | AD53: Media | AE53: AREA MICROFINANZAS | AF53: ORQClientes0022 | AG53: 0 | AH53: 1 | AI53: Baja | AJ53: Ninguno | AK53: Baja | AL53: ConsultarClienteVirtual01 | AM53: Baja | AN53: =IFERROR(SUM(CHOOSE(MATCH(N53,{"Baja";"Media";"Alta"},0),1,2,3), CHOOSE(MATCH(Q53,{"Baja";"Media";"Alta"},0),1,2,3), CHOOSE(MATCH(T53,{"Baja";"Media";"Alta"},0),1,2,3), CHOOSE(MATCH(W53,{"Baja";"Media";"Alta"},0),1,2,3), CHOOSE(MATCH(AB53,{"Baja";"Media";"Alta"},0),1,2,3), CHOOSE(MATCH(AD53,{"Baja";"Media";"Alta"},0),1,2,3), CHOOSE(MATCH(AI53,{"Baja";"Media";"Alta"},0),1,2,3), CHOOSE(MATCH(AK53,{"Baja";"Media";"Alta"},0),1,2,3), CHOOSE(MATCH(AM53,{"Baja";"Media";"Alta"},0),1,2,3)),0) -> 12 | AO53: =IF(AN53=0,"Pendiente",IF(AN53<=15,"Bajo",IF(AN53<=21,"Medio","Alto"))) -> Bajo | AR53: =VLOOKUP(A53,#REF!,2,FALSE) -> #REF! | AS53: https://s.icepanel.io/wJSECZOwwNkkW8/1cIC | AT53: https://dev.azure.com/BancoPichinchaEC/adi-especificaciones-tecnicas/_git/adi-doc-tecspec-tribu-integracion-apis?path=/sp%20-%20Soporte/tnd-msa-sp-wsclientes0046 | AU53: https://dev.azure.com/BancoPichinchaEC/tpl-bus-omnicanal/_git/sqb-msa-wsclientes0046 | AV53: 1 | AW53: https://pichincha.atlassian.net/browse/PCBG-478
A54: WSClientes0055 | B54: =CONCATENATE(LOWER(E54),"-msa-sp-",LOWER(A54)) -> tnd-msa-sp-wsclientes0055 | C54: Consulta , Crear , Actualiza la actividad economica de un cliente | D54: TRIBU SEGMENTOS Y NEGOCIOS DIGITALES | E54: =VLOOKUP(D54,Tribus!$A$1:$B$33,2,FALSE) -> tnd | F54: Bus Omnicanalidad | G54: WS | H54: Completado | I54: A Desarrollo | J54: UMPClientes0069 -> Consulta actividad economica -> TX67196 UMPClientes0066 -> Consulta Correspondencia (localizacion) -> TX062120 | K54: TXT BANCS | L54: ON-PREMISE | M54: 2 | N54: Media | O54: SOAP - 8934 | P54: 1 | Q54: Baja | R54: NO | S54: 0 | T54: Baja | U54: Ninguna | W54: Baja | X54: 263TPM - 116K/Diario | Y54: 89ms | AB54: Media | AC54: ORQClientes0071 ORQClientes0048 ORQClientes0063 ORQClientes0038 ORQClientes0016 ORQCLientes0054 ORQClientes0035 | AD54: Media | AE54: Tribu Canales Físicos Tribu Retail Tribu Negocios digitales | AF54: ORQClientes0071 ORQClientes0048 ORQClientes0063 ORQClientes0038 ORQClientes0016 ORQCLientes0054 ORQClientes0035 | AH54: 7 | AI54: Alta | AJ54: NO | AK54: Baja | AL54: OperacionActividadEconomicaCliente51 OperacionActividadEconomicaCliente52 | AM54: Media | AN54: =IFERROR(SUM(CHOOSE(MATCH(N54,{"Baja";"Media";"Alta"},0),1,2,3), CHOOSE(MATCH(Q54,{"Baja";"Media";"Alta"},0),1,2,3), CHOOSE(MATCH(T54,{"Baja";"Media";"Alta"},0),1,2,3), CHOOSE(MATCH(W54,{"Baja";"Media";"Alta"},0),1,2,3), CHOOSE(MATCH(AB54,{"Baja";"Media";"Alta"},0),1,2,3), CHOOSE(MATCH(AD54,{"Baja";"Media";"Alta"},0),1,2,3), CHOOSE(MATCH(AI54,{"Baja";"Media";"Alta"},0),1,2,3), CHOOSE(MATCH(AK54,{"Baja";"Media";"Alta"},0),1,2,3), CHOOSE(MATCH(AM54,{"Baja";"Media";"Alta"},0),1,2,3)),0) -> 15 | AO54: =IF(AN54=0,"Pendiente",IF(AN54<=15,"Bajo",IF(AN54<=21,"Medio","Alto"))) -> Bajo | AR54: =VLOOKUP(A54,#REF!,2,FALSE) -> #REF! | AS54: https://s.icepanel.io/wJSECZOwwNkkW8/Z5P6 | AT54: https://dev.azure.com/BancoPichinchaEC/adi-especificaciones-tecnicas/_git/adi-doc-tecspec-tribu-integracion-apis?path=/sp%20-%20Soporte/tnd-msa-sp-wsclientes0055 | AU54: https://dev.azure.com/BancoPichinchaEC/tpl-bus-omnicanal/_git/sqb-msa-wsclientes0055 | AV54: 1 | AW54: https://pichincha.atlassian.net/browse/PCBG-390
A55: WSClientes0060 | B55: tnd-msa-sp-bnc-wsclientes0060 | C55: Consulta informacion complementaria de un cliente | D55: TRIBU SEGMENTOS Y NEGOCIOS DIGITALES | E55: =VLOOKUP(D55,Tribus!$A$1:$B$33,2,FALSE) -> tnd | F55: Bus Omnicanalidad | G55: WS | H55: Completado | I55: A Desarrollo | J55: UMPClientes0075 ESQL -> TX067145 | K55: TXT BANCS | L55: ON-PREMISE | M55: 1 | N55: Baja | O55: SOAP -8934 | P55: 1 | Q55: Baja | R55: NO | S55: 0 | T55: Baja | U55: Ninguna | W55: Baja | X55: 100.2K | Y55: 38.3 ms | AB55: Media | AC55: ORQCLIENTES0048 ORQCLIENTES0038 ORQCLIENTES0016 ORQCLIENTES0059 | AD55: Media | AE55: Tribu Canales Fisicos Tribu Retail BPM | AF55: ORQCLIENTES0048 ORQCLIENTES0038 ORQCLIENTES0016 ORQCLIENTES0059 | AH55: 4 | AI55: Alta | AJ55: NO | AK55: Baja | AL55: OperacionDatosComplementariosCliente51 | AM55: Baja | AN55: =IFERROR(SUM(CHOOSE(MATCH(N55,{"Baja";"Media";"Alta"},0),1,2,3), CHOOSE(MATCH(Q55,{"Baja";"Media";"Alta"},0),1,2,3), CHOOSE(MATCH(T55,{"Baja";"Media";"Alta"},0),1,2,3), CHOOSE(MATCH(W55,{"Baja";"Media";"Alta"},0),1,2,3), CHOOSE(MATCH(AB55,{"Baja";"Media";"Alta"},0),1,2,3), CHOOSE(MATCH(AD55,{"Baja";"Media";"Alta"},0),1,2,3), CHOOSE(MATCH(AI55,{"Baja";"Media";"Alta"},0),1,2,3), CHOOSE(MATCH(AK55,{"Baja";"Media";"Alta"},0),1,2,3), CHOOSE(MATCH(AM55,{"Baja";"Media";"Alta"},0),1,2,3)),0) -> 13 | AO55: =IF(AN55=0,"Pendiente",IF(AN55<=15,"Bajo",IF(AN55<=21,"Medio","Alto"))) -> Bajo | AQ55: Considerar Existe el servicio en el WAS con el mismo nombre y usan el mismo nombre de ump para bus y was | AR55: =VLOOKUP(A55,#REF!,2,FALSE) -> #REF! | AS55: https://s.icepanel.io/wJSECZOwwNkkW8/04F1 | AT55: https://dev.azure.com/BancoPichinchaEC/adi-especificaciones-tecnicas/_git/adi-doc-tecspec-tribu-integracion-apis?version=GBmaster&path=/sp%20-%20Soporte/tnd-msa-sp-bnc-wsclientes0060 | AU55: https://dev.azure.com/BancoPichinchaEC/tpl-bus-omnicanal/_git/sqb-msa-wsclientes0060 | AV55: 1 | AW55: https://pichincha.atlassian.net/browse/PCBG-391
A56: WSClientes0061 | B56: =CONCATENATE(LOWER(E56),"-msa-sp-",LOWER(A56)) -> tnd-msa-sp-wsclientes0061 | C56: Obtiene datos demográficos de un cliente | D56: TRIBU SEGMENTOS Y NEGOCIOS DIGITALES | E56: =VLOOKUP(D56,Tribus!$A$1:$B$33,2,FALSE) -> tnd | F56: Bus Omnicanalidad | G56: WS | H56: Completado | I56: A Desarrollo | J56: UMPClientes0077 --> OperacionDemograficosCliente51 --> TX061406 | K56: TXT Bancs | L56: ON-PREMISE | M56: 1 | N56: Baja | O56: SOAP | P56: 1 | Q56: Baja | R56: Ninguna | S56: 0 | T56: Baja | U56: Ninguna | W56: Baja | X56: 98.8K | Y56: 29ms | AB56: Media | AC56: Afecta algunos servicios | AD56: Media | AF56: ORQClientes0048 ORQClientes0054 ORQClientes0035 ORQClientes0016 | AH56: 4 | AI56: Alta | AJ56: Ninguno | AK56: Baja | AL56: OperacionDemograficosCliente51 | AM56: Baja | AN56: =IFERROR(SUM(CHOOSE(MATCH(N56,{"Baja";"Media";"Alta"},0),1,2,3), CHOOSE(MATCH(Q56,{"Baja";"Media";"Alta"},0),1,2,3), CHOOSE(MATCH(T56,{"Baja";"Media";"Alta"},0),1,2,3), CHOOSE(MATCH(W56,{"Baja";"Media";"Alta"},0),1,2,3), CHOOSE(MATCH(AB56,{"Baja";"Media";"Alta"},0),1,2,3), CHOOSE(MATCH(AD56,{"Baja";"Media";"Alta"},0),1,2,3), CHOOSE(MATCH(AI56,{"Baja";"Media";"Alta"},0),1,2,3), CHOOSE(MATCH(AK56,{"Baja";"Media";"Alta"},0),1,2,3), CHOOSE(MATCH(AM56,{"Baja";"Media";"Alta"},0),1,2,3)),0) -> 13 | AO56: =IF(AN56=0,"Pendiente",IF(AN56<=15,"Bajo",IF(AN56<=21,"Medio","Alto"))) -> Bajo | AR56: =VLOOKUP(A56,#REF!,2,FALSE) -> #REF! | AS56: https://s.icepanel.io/wJSECZOwwNkkW8/oA39 | AT56: https://dev.azure.com/BancoPichinchaEC/adi-especificaciones-tecnicas/_git/adi-doc-tecspec-tribu-integracion-apis?path=/sp%20-%20Soporte/tnd-msa-sp-wsclientes0061 | AU56: sqb-msa-wsclientes0061 - Repos | AV56: 1 | AW56: https://pichincha.atlassian.net/browse/PCBG-392
A57: WSClientes0062 | B57: =CONCATENATE(LOWER(E57),"-msa-sp-",LOWER(A57)) -> tnd-msa-sp-wsclientes0062 | C57: Microservicio que consulta la información básica del cliente | D57: TRIBU SEGMENTOS Y NEGOCIOS DIGITALES | E57: =VLOOKUP(D57,Tribus!$A$1:$B$33,2,FALSE) -> tnd | F57: Bus Omnicanalidad | G57: WS | H57: Completado | I57: A Desarrollo | J57: UMPClientes0078 -> OperacionIdentificacionCliente51 -> TX067153 -> Consulta información de identificación del cliente | K57: TXT BANCS | L57: ON-PREMISE | M57: 1 | N57: Baja | O57: SOAP - 8934 | P57: 1 | Q57: Baja | R57: Ninguna | S57: 0 | T57: Baja | U57: Ninguna | W57: Baja | X57: 424k | Y57: 33.5ms | AB57: Media | AC57: Afecta algunos servicios | AD57: Media | AF57: ORQClientes0016 ORQClientes0035 ORQClientes0048 ORQClientes0071 ORQProductos0052 | AH57: 5 | AI57: Alta | AJ57: Ninguno | AK57: Baja | AL57: OperacionIdentificacionCliente51 | AM57: Baja | AN57: =IFERROR(SUM(CHOOSE(MATCH(N57,{"Baja";"Media";"Alta"},0),1,2,3), CHOOSE(MATCH(Q57,{"Baja";"Media";"Alta"},0),1,2,3), CHOOSE(MATCH(T57,{"Baja";"Media";"Alta"},0),1,2,3), CHOOSE(MATCH(W57,{"Baja";"Media";"Alta"},0),1,2,3), CHOOSE(MATCH(AB57,{"Baja";"Media";"Alta"},0),1,2,3), CHOOSE(MATCH(AD57,{"Baja";"Media";"Alta"},0),1,2,3), CHOOSE(MATCH(AI57,{"Baja";"Media";"Alta"},0),1,2,3), CHOOSE(MATCH(AK57,{"Baja";"Media";"Alta"},0),1,2,3), CHOOSE(MATCH(AM57,{"Baja";"Media";"Alta"},0),1,2,3)),0) -> 13 | AO57: =IF(AN57=0,"Pendiente",IF(AN57<=15,"Bajo",IF(AN57<=21,"Medio","Alto"))) -> Bajo | AR57: =VLOOKUP(A57,#REF!,2,FALSE) -> #REF! | AS57: https://app.icepanel.io/landscapes/w71QNHgfDvF79GrSuA3r/versions/latest/diagrams/editor?diagram=XwmII61i74&model=v3xbgfajwj&overlay_tab=tags&x1=-1207.1&y1=-56&x2=2239.1&y2=1472 | AT57: https://dev.azure.com/BancoPichinchaEC/adi-especificaciones-tecnicas/_git/adi-doc-tecspec-tribu-integracion-apis?path=/sp%20-%20Soporte/tnd-msa-sp-wsclientes0062 | AU57: https://dev.azure.com/BancoPichinchaEC/tpl-bus-omnicanal/_git/sqb-msa-wsclientes0062 | AV57: 1 | AW57: https://pichincha.atlassian.net/browse/PCBG-393
A58: WSClientes0063 | B58: =CONCATENATE(LOWER(E58),"-msa-sp-",LOWER(A58)) -> tnd-msa-sp-wsclientes0063 | C58: Consulta , Crear , Actualiza la referencias de un cliente | D58: TRIBU SEGMENTOS Y NEGOCIOS DIGITALES | E58: =VLOOKUP(D58,Tribus!$A$1:$B$33,2,FALSE) -> tnd | F58: Bus Omnicanalidad | G58: WS | H58: Completado | I58: A Desarrollo | J58: UMPClientes0067 ESQL -> 67216 -> 67217 | K58: TXT BANCS | L58: ON-PREMISE | M58: 1 | N58: Baja | O58: SOAP | P58: 1 | Q58: Baja | R58: NO | S58: 0 | T58: Baja | U58: Ninguna | W58: Baja | X58: 200Mensual | Y58: 60ms | AB58: Baja | AC58: ORQClientes0035 | AD58: Media | AF58: ORQClientes0035 | AH58: 1 | AI58: Baja | AJ58: NO | AK58: Baja | AL58: OperacionReferenciasCliente51 | AM58: Baja | AN58: =IFERROR(SUM(CHOOSE(MATCH(N58,{"Baja";"Media";"Alta"},0),1,2,3), CHOOSE(MATCH(Q58,{"Baja";"Media";"Alta"},0),1,2,3), CHOOSE(MATCH(T58,{"Baja";"Media";"Alta"},0),1,2,3), CHOOSE(MATCH(W58,{"Baja";"Media";"Alta"},0),1,2,3), CHOOSE(MATCH(AB58,{"Baja";"Media";"Alta"},0),1,2,3), CHOOSE(MATCH(AD58,{"Baja";"Media";"Alta"},0),1,2,3), CHOOSE(MATCH(AI58,{"Baja";"Media";"Alta"},0),1,2,3), CHOOSE(MATCH(AK58,{"Baja";"Media";"Alta"},0),1,2,3), CHOOSE(MATCH(AM58,{"Baja";"Media";"Alta"},0),1,2,3)),0) -> 10 | AO58: =IF(AN58=0,"Pendiente",IF(AN58<=15,"Bajo",IF(AN58<=21,"Medio","Alto"))) -> Bajo | AR58: =VLOOKUP(A58,#REF!,2,FALSE) -> #REF! | AS58: https://s.icepanel.io/wJSECZOwwNkkW8/X6Zx | AT58: https://dev.azure.com/BancoPichinchaEC/adi-especificaciones-tecnicas/_git/adi-doc-tecspec-tribu-integracion-apis?path=/sp%20-%20Soporte/tnd-msa-sp-wsclientes0063 | AU58: https://dev.azure.com/BancoPichinchaEC/tpl-bus-omnicanal/_git/sqb-msa-wsclientes0063 | AV58: 1 | AW58: https://pichincha.atlassian.net/browse/PCBG-479
A59: WSClientes0067 | B59: =CONCATENATE(LOWER(E59),"-msa-sp-",LOWER(A59)) -> tnd-msa-sp-wsclientes0067 | C59: Consultar las cuentas de un cliente. | D59: TRIBU SEGMENTOS Y NEGOCIOS DIGITALES | E59: =VLOOKUP(D59,Tribus!$A$1:$B$33,2,FALSE) -> tnd | F59: Bus Omnicanalidad | G59: WS | H59: Completado | I59: A Desarrollo | J59: UMPClientes0082 --> ConsultarCuentasClientes01 --> TX060453 UMPClientes0082 --> ConsultarCuentasClientes01 --> TX060452 | K59: TXT Bancs | L59: ON-PREMISE | M59: 2 | N59: Media | O59: SOAP | P59: 1 | Q59: Baja | R59: Ninguna | S59: 0 | T59: Baja | U59: Ninguna | W59: Baja | X59: 141.8K | Y59: 43ms | AB59: Media | AC59: Afecta algunos servicios | AD59: Media | AE59: TRIBU EMPRESAS TRIBU PRODUCTOS TRIBU MEDIOS DE PAGO | AF59: ORQClientes0017 ORQClientes0048 ORQClientes0053 ORQProductos0062 ORQClientes0065.API - /api/v1/InformacionProductos/ConsultarInformacionProductos01 WSClientes0179.API - /api/v1/ValidarCuentas/ValidarCuentas01 bbe-msa-bs-investment - /business/business-banking/v1/investments cta-msa-customers - /getCustomerAccounts trv-msa-sp-customer-account - /support/transversales/v1/customer-accounts crd-msa-account-integration - /findAccounts tdd-msa-bs-customer-account - /business/tarjetas-de-debito/v1/customer-accounts tre-msa-account - /api/v1/retail/tre-msa-account/accounts | AG59: BIZAGI_IAAS https://autogestiontd.bpichincha.com/ | AH59: 13 | AI59: Alta | AJ59: Ninguno | AK59: Baja | AL59: ConsultarCuentasClientes01 | AM59: Baja | AN59: =IFERROR(SUM(CHOOSE(MATCH(N59,{"Baja";"Media";"Alta"},0),1,2,3), CHOOSE(MATCH(Q59,{"Baja";"Media";"Alta"},0),1,2,3), CHOOSE(MATCH(T59,{"Baja";"Media";"Alta"},0),1,2,3), CHOOSE(MATCH(W59,{"Baja";"Media";"Alta"},0),1,2,3), CHOOSE(MATCH(AB59,{"Baja";"Media";"Alta"},0),1,2,3), CHOOSE(MATCH(AD59,{"Baja";"Media";"Alta"},0),1,2,3), CHOOSE(MATCH(AI59,{"Baja";"Media";"Alta"},0),1,2,3), CHOOSE(MATCH(AK59,{"Baja";"Media";"Alta"},0),1,2,3), CHOOSE(MATCH(AM59,{"Baja";"Media";"Alta"},0),1,2,3)),0) -> 14 | AO59: =IF(AN59=0,"Pendiente",IF(AN59<=15,"Bajo",IF(AN59<=21,"Medio","Alto"))) -> Bajo | AR59: =VLOOKUP(A59,#REF!,2,FALSE) -> #REF! | AS59: https://s.icepanel.io/wJSECZOwwNkkW8/9teK | AT59: https://dev.azure.com/BancoPichinchaEC/adi-especificaciones-tecnicas/_git/adi-doc-tecspec-tribu-integracion-apis?path=/sp%20-%20Soporte/tnd-msa-sp-wsclientes0067 | AU59: sqb-msa-wsclientes0067 - Repos | AV59: 1 | AW59: https://pichincha.atlassian.net/browse/PCBG-394
A60: WSClientes0071 | B60: =CONCATENATE(LOWER(E60),"-msa-sp-",LOWER(A60)) -> tnd-msa-sp-wsclientes0071 | C60: Actualiza datos de bienes económicos del cliente | D60: TRIBU SEGMENTOS Y NEGOCIOS DIGITALES | E60: =VLOOKUP(D60,Tribus!$A$1:$B$33,2,FALSE) -> tnd | F60: Bus Omnicanalidad | G60: WS | H60: Completado | I60: A Desarrollo | J60: UMPClientes0016 --> ActualizarDatosBienes31 --> TX067050 (opc 20) UMPClientes0016 --> ActualizarDatosBienes31 --> TX067118 | K60: TXT Bancs | L60: ON-PREMISE | M60: 2 | N60: Media | O60: SOAP | P60: 1 | Q60: Baja | R60: Ninguna | S60: 0 | T60: Baja | U60: Ninguna | W60: Baja | X60: 574 | Y60: 34ms | AB60: Baja | AC60: Afecta un servicio | AD60: Media | AF60: ORQClientes0019 | AH60: 1 | AI60: Baja | AJ60: Ninguno | AK60: Baja | AL60: AsignarInformacionBienes01 | AM60: Baja | AN60: =IFERROR(SUM(CHOOSE(MATCH(N60,{"Baja";"Media";"Alta"},0),1,2,3), CHOOSE(MATCH(Q60,{"Baja";"Media";"Alta"},0),1,2,3), CHOOSE(MATCH(T60,{"Baja";"Media";"Alta"},0),1,2,3), CHOOSE(MATCH(W60,{"Baja";"Media";"Alta"},0),1,2,3), CHOOSE(MATCH(AB60,{"Baja";"Media";"Alta"},0),1,2,3), CHOOSE(MATCH(AD60,{"Baja";"Media";"Alta"},0),1,2,3), CHOOSE(MATCH(AI60,{"Baja";"Media";"Alta"},0),1,2,3), CHOOSE(MATCH(AK60,{"Baja";"Media";"Alta"},0),1,2,3), CHOOSE(MATCH(AM60,{"Baja";"Media";"Alta"},0),1,2,3)),0) -> 11 | AO60: =IF(AN60=0,"Pendiente",IF(AN60<=15,"Bajo",IF(AN60<=21,"Medio","Alto"))) -> Bajo | AR60: =VLOOKUP(A60,#REF!,2,FALSE) -> #REF! | AS60: https://s.icepanel.io/wJSECZOwwNkkW8/O8qO | AT60: https://dev.azure.com/BancoPichinchaEC/adi-especificaciones-tecnicas/_git/adi-doc-tecspec-tribu-integracion-apis?path=/sp%20-%20Soporte/tnd-msa-sp-wsclientes0071 | AU60: sqb-msa-wsclientes0071 - Repos | AV60: 1 | AW60: https://pichincha.atlassian.net/browse/PCBG-480
A61: WSClientes0072 | B61: =CONCATENATE(LOWER(E61),"-msa-sp-",LOWER(A61)) -> tnd-msa-sp-wsclientes0072 | C61: Consulta informacion economica del cliente basica del cliente | D61: TRIBU SEGMENTOS Y NEGOCIOS DIGITALES | E61: =VLOOKUP(D61,Tribus!$A$1:$B$33,2,FALSE) -> tnd | F61: Bus Omnicanalidad | G61: WS | H61: Completado | I61: A Desarrollo | J61: UMPClientes0017 -> Servicio de consulta de detalle adicionales del clientes TX067218 -> Retorna cantidad contatos tiene para esa referencias TX067210 -> obtiene las referencia exacta Orquesta las transacciones de referencias. TX067212 opc 1 -> TX067215 opc 2 -> TX067214 opc 3 -> TX067216 opc 4 -> TX067217 opc 5 -> TX067213 opc 6 -> TX067211 opc 7 -> | K61: TXT BANCS | L61: ON-PREMISE | M61: 9 | N61: Alta | O61: SOAP - 8934 | P61: 1 | Q61: Baja | R61: Ninguna | S61: 0 | T61: Baja | U61: Ninguna | W61: Baja | X61: 98.8K | Y61: 145 ms | AB61: Media | AD61: Media | AF61: ORQClientes0019 ORQClientes0038 ORQClientes0048 | AH61: 3 | AI61: Media | AJ61: N/A | AK61: Baja | AL61: ActualizarDatosReferencias31 | AM61: Baja | AN61: =IFERROR(SUM(CHOOSE(MATCH(N61,{"Baja";"Media";"Alta"},0),1,2,3), CHOOSE(MATCH(Q61,{"Baja";"Media";"Alta"},0),1,2,3), CHOOSE(MATCH(T61,{"Baja";"Media";"Alta"},0),1,2,3), CHOOSE(MATCH(W61,{"Baja";"Media";"Alta"},0),1,2,3), CHOOSE(MATCH(AB61,{"Baja";"Media";"Alta"},0),1,2,3), CHOOSE(MATCH(AD61,{"Baja";"Media";"Alta"},0),1,2,3), CHOOSE(MATCH(AI61,{"Baja";"Media";"Alta"},0),1,2,3), CHOOSE(MATCH(AK61,{"Baja";"Media";"Alta"},0),1,2,3), CHOOSE(MATCH(AM61,{"Baja";"Media";"Alta"},0),1,2,3)),0) -> 14 | AO61: =IF(AN61=0,"Pendiente",IF(AN61<=15,"Bajo",IF(AN61<=21,"Medio","Alto"))) -> Bajo | AQ61: Validar las descripciones de las tx. | AR61: =VLOOKUP(A61,#REF!,2,FALSE) -> #REF! | AS61: https://s.icepanel.io/wJSECZOwwNkkW8/sjJK | AT61: https://dev.azure.com/BancoPichinchaEC/adi-especificaciones-tecnicas/_git/adi-doc-tecspec-tribu-integracion-apis?path=/sp%20-%20Soporte/tnd-msa-sp-wsclientes0072 | AU61: sqb-msa-wsclientes0072 - Repos | AV61: 1 | AW61: https://pichincha.atlassian.net/browse/PCBG-395
A62: WSClientes0074 | B62: =CONCATENATE(LOWER(E62),"-msa-sp-",LOWER(A62)) -> tnd-msa-sp-wsclientes0074 | C62: Consulta informacion economica basica del cliente. | D62: TRIBU SEGMENTOS Y NEGOCIOS DIGITALES | E62: =VLOOKUP(D62,Tribus!$A$1:$B$33,2,FALSE) -> tnd | F62: Bus Omnicanalidad | G62: WS | H62: Completado | I62: A Desarrollo | J62: UMPClientes0019 -> ActualizarDatosActividadEconomica31 -> TX067196 -> TX062120 -> Consulta actividad económica del cliente | K62: TXT BANCS | L62: ON-PREMISE | M62: 1 | N62: Baja | O62: SOAP - 8934 | P62: 1 | Q62: Baja | R62: Ninguna | S62: 0 | T62: Baja | U62: Ninguna | W62: Baja | X62: 1,144K | Y62: 51.1ms | AB62: Baja | AC62: Afecta a un servicio | AD62: Media | AF62: ORQClientes0019 | AH62: 1 | AI62: Baja | AJ62: Ninguno | AK62: Baja | AL62: ActualizarDatosActividadEconomica31 | AM62: Baja | AN62: =IFERROR(SUM(CHOOSE(MATCH(N62,{"Baja";"Media";"Alta"},0),1,2,3), CHOOSE(MATCH(Q62,{"Baja";"Media";"Alta"},0),1,2,3), CHOOSE(MATCH(T62,{"Baja";"Media";"Alta"},0),1,2,3), CHOOSE(MATCH(W62,{"Baja";"Media";"Alta"},0),1,2,3), CHOOSE(MATCH(AB62,{"Baja";"Media";"Alta"},0),1,2,3), CHOOSE(MATCH(AD62,{"Baja";"Media";"Alta"},0),1,2,3), CHOOSE(MATCH(AI62,{"Baja";"Media";"Alta"},0),1,2,3), CHOOSE(MATCH(AK62,{"Baja";"Media";"Alta"},0),1,2,3), CHOOSE(MATCH(AM62,{"Baja";"Media";"Alta"},0),1,2,3)),0) -> 10 | AO62: =IF(AN62=0,"Pendiente",IF(AN62<=15,"Bajo",IF(AN62<=21,"Medio","Alto"))) -> Bajo | AR62: =VLOOKUP(A62,#REF!,2,FALSE) -> #REF! | AS62: https://app.icepanel.io/landscapes/w71QNHgfDvF79GrSuA3r/versions/latest/diagrams/editor?diagram=fIFTG1H5Gh&model=RhYlSxnwCl&overlay_tab=tags&x1=-665.6&y1=-56&x2=2491.9&y2=1344 | AT62: https://dev.azure.com/BancoPichinchaEC/adi-especificaciones-tecnicas/_git/adi-doc-tecspec-tribu-integracion-apis?path=/sp%20-%20Soporte/tnd-msa-sp-wsclientes0074 | AU62: https://dev.azure.com/BancoPichinchaEC/tpl-bus-omnicanal/_git/sqb-msa-wsclientes0074 | AV62: 1 | AW62: https://pichincha.atlassian.net/browse/PCBG-481
A63: WSClientes0075 | B63: =CONCATENATE(LOWER(E63),"-msa-sp-",LOWER(A63)) -> tpr-msa-sp-wsclientes0075 | C63: Consulta el detalle corto de una cuenta del cliente | D63: TRIBU PRODUCTOS | E63: =VLOOKUP(D63,Tribus!$A$1:$B$33,2,FALSE) -> tpr | F63: Bus Omnicanalidad | G63: WS | H63: Completado | I63: A Desarrollo | J63: UMPProductos0007 -> ConsultarDetalleCortoCuenta01 -> TX000400 -> Consulta el detalle corto de una cuenta del cliente | K63: TXT BANCS | L63: ON-PREMISE | M63: 1 | N63: Baja | O63: SOAP - 8934 | P63: 1 | Q63: Baja | R63: Ninguna | S63: 0 | T63: Baja | U63: Ninguna | W63: Baja | X63: 37k | Y63: 29.7ms | AB63: Baja | AC63: Afecta algunos servicios | AD63: Media | AF63: ORQClientes0024 | AG63: Default Web Site:443,8043 (/BPMPichinchaAD) | AH63: 2 | AI63: Media | AJ63: Ninguno | AK63: Baja | AL63: ConsultarSaldosCuenta01 | AM63: Baja | AN63: =IFERROR(SUM(CHOOSE(MATCH(N63,{"Baja";"Media";"Alta"},0),1,2,3), CHOOSE(MATCH(Q63,{"Baja";"Media";"Alta"},0),1,2,3), CHOOSE(MATCH(T63,{"Baja";"Media";"Alta"},0),1,2,3), CHOOSE(MATCH(W63,{"Baja";"Media";"Alta"},0),1,2,3), CHOOSE(MATCH(AB63,{"Baja";"Media";"Alta"},0),1,2,3), CHOOSE(MATCH(AD63,{"Baja";"Media";"Alta"},0),1,2,3), CHOOSE(MATCH(AI63,{"Baja";"Media";"Alta"},0),1,2,3), CHOOSE(MATCH(AK63,{"Baja";"Media";"Alta"},0),1,2,3), CHOOSE(MATCH(AM63,{"Baja";"Media";"Alta"},0),1,2,3)),0) -> 11 | AO63: =IF(AN63=0,"Pendiente",IF(AN63<=15,"Bajo",IF(AN63<=21,"Medio","Alto"))) -> Bajo | AR63: =VLOOKUP(A63,#REF!,2,FALSE) -> #REF! | AS63: https://app.icepanel.io/landscapes/w71QNHgfDvF79GrSuA3r/versions/latest/diagrams/editor?diagram=FQF00gICx0&model=ffdxmqzw1dp&overlay_tab=tags&x1=-1170&y1=-56&x2=2186&y2=1432 | AT63: https://dev.azure.com/BancoPichinchaEC/adi-especificaciones-tecnicas/_git/adi-doc-tecspec-tribu-integracion-apis?path=/sp%20-%20Soporte/tpr-msa-sp-wsclientes0075 | AU63: https://dev.azure.com/BancoPichinchaEC/tpl-bus-omnicanal/_git/sqb-msa-wsclientes0075 | AV63: 1 | AW63: https://pichincha.atlassian.net/browse/PCBG-482
A64: WSClientes0077 | B64: =CONCATENATE(LOWER(E64),"-msa-sp-",LOWER(A64)) -> tnd-msa-sp-wsclientes0077 | C64: Consulta basica clientes | D64: TRIBU SEGMENTOS Y NEGOCIOS DIGITALES | E64: =VLOOKUP(D64,Tribus!$A$1:$B$33,2,FALSE) -> tnd | F64: Bus Omnicanalidad | G64: WS | H64: Completado | I64: A Desarrollo | J64: UMPClientes0020-> ConsultaInformacionCliente01-> TX067050-> Consulta información basica del cliente | K64: TXT BANCS | L64: ON-PREMISE | M64: 1 | N64: Baja | O64: SOAP - 8934 REST- 8937 | P64: 2 | Q64: Media | R64: Ninguna | S64: 0 | T64: Baja | U64: Ninguna | W64: Baja | X64: 143.2K | Y64: 54.5ms | AB64: Media | AC64: Afecta algunos servicios | AD64: Media | AE64: COE DE TRANSFORMACIÓN DE PROCESOS Y AUTOMATIZACION | AF64: ORQClientes0071 ORQClientes0029 ORQClientes0064.API;deployment-bmn-msa-bs-orqclientes*-* | AH64: 3 | AI64: Media | AJ64: Ninguna | AK64: Baja | AL64: ConsultarDatoBasicoCliente01 | AM64: Baja | AN64: =IFERROR(SUM(CHOOSE(MATCH(N64,{"Baja";"Media";"Alta"},0),1,2,3), CHOOSE(MATCH(Q64,{"Baja";"Media";"Alta"},0),1,2,3), CHOOSE(MATCH(T64,{"Baja";"Media";"Alta"},0),1,2,3), CHOOSE(MATCH(W64,{"Baja";"Media";"Alta"},0),1,2,3), CHOOSE(MATCH(AB64,{"Baja";"Media";"Alta"},0),1,2,3), CHOOSE(MATCH(AD64,{"Baja";"Media";"Alta"},0),1,2,3), CHOOSE(MATCH(AI64,{"Baja";"Media";"Alta"},0),1,2,3), CHOOSE(MATCH(AK64,{"Baja";"Media";"Alta"},0),1,2,3), CHOOSE(MATCH(AM64,{"Baja";"Media";"Alta"},0),1,2,3)),0) -> 13 | AO64: =IF(AN64=0,"Pendiente",IF(AN64<=15,"Bajo",IF(AN64<=21,"Medio","Alto"))) -> Bajo | AR64: =VLOOKUP(A64,#REF!,2,FALSE) -> #REF! | AS64: https://s.icepanel.io/wJSECZOwwNkkW8/J3jw | AT64: https://dev.azure.com/BancoPichinchaEC/adi-especificaciones-tecnicas/_git/adi-doc-tecspec-tribu-integracion-apis?path=/sp%20-%20Soporte/tnd-msa-sp-wsclientes0077 | AU64: https://dev.azure.com/BancoPichinchaEC/tpl-bus-omnicanal/_git/sqb-msa-wsclientes0077 | AV64: 1 | AW64: https://pichincha.atlassian.net/browse/PCBG-396
A65: WSClientes0078 | B65: =CONCATENATE(LOWER(E65),"-msa-sp-",LOWER(A65)) -> tpr-msa-sp-wsclientes0078 | C65: Consulta la información de un cliente SAR | D65: TRIBU PRODUCTOS | E65: =VLOOKUP(D65,Tribus!$A$1:$B$33,2,FALSE) -> tpr | F65: Bus Omnicanalidad | G65: WS | H65: Completado | I65: A Desarrollo | J65: UMPClientes0023 -> ConsultarClientesSar -> http://10.60.144.57:9443/clientesSARWS/ClienteSARWSService | K65: Was Internexo | L65: ON-PREMISE | M65: 1 | N65: Baja | O65: SOAP - 8934 REST - 8937 | P65: 2 | Q65: Media | R65: Ninguna | S65: 0 | T65: Baja | U65: Ninguna | W65: Baja | X65: 19.4k | Y65: 33.1ms | AB65: Baja | AC65: Afecta algunos servicios | AD65: Media | AE65: COE DE TRANSFORMACIÓN DE PROCESOS Y AUTOMATIZACION | AF65: ORQClientes0023 ORQClientes0029 ORQClientes0064.API;deployment-bmn-msa-bs-orqclientes*-* | AH65: 3 | AI65: Media | AJ65: Ninguna | AK65: Baja | AL65: consultarClienteSAR | AM65: Baja | AN65: =IFERROR(SUM(CHOOSE(MATCH(N65,{"Baja";"Media";"Alta"},0),1,2,3), CHOOSE(MATCH(Q65,{"Baja";"Media";"Alta"},0),1,2,3), CHOOSE(MATCH(T65,{"Baja";"Media";"Alta"},0),1,2,3), CHOOSE(MATCH(W65,{"Baja";"Media";"Alta"},0),1,2,3), CHOOSE(MATCH(AB65,{"Baja";"Media";"Alta"},0),1,2,3), CHOOSE(MATCH(AD65,{"Baja";"Media";"Alta"},0),1,2,3), CHOOSE(MATCH(AI65,{"Baja";"Media";"Alta"},0),1,2,3), CHOOSE(MATCH(AK65,{"Baja";"Media";"Alta"},0),1,2,3), CHOOSE(MATCH(AM65,{"Baja";"Media";"Alta"},0),1,2,3)),0) -> 12 | AO65: =IF(AN65=0,"Pendiente",IF(AN65<=15,"Bajo",IF(AN65<=21,"Medio","Alto"))) -> Bajo | AR65: =VLOOKUP(A65,#REF!,2,FALSE) -> #REF! | AS65: https://s.icepanel.io/wJSECZOwwNkkW8/DIza | AT65: https://dev.azure.com/BancoPichinchaEC/adi-especificaciones-tecnicas/_git/adi-doc-tecspec-tribu-integracion-apis?path=/sp%20-%20Soporte/tpr-msa-sp-wsclientes0078 | AU65: https://dev.azure.com/BancoPichinchaEC/tpl-bus-omnicanal/_git/sqb-msa-wsclientes0078 | AV65: 1 | AW65: Revisar consume was internexo
A66: WSClientes0080 | B66: =CONCATENATE(LOWER(E66),"-msa-sp-",LOWER(A66)) -> tpr-msa-sp-wsclientes0080 | C66: Consulta garantias SAR del cliente | D66: TRIBU PRODUCTOS | E66: =VLOOKUP(D66,Tribus!$A$1:$B$33,2,FALSE) -> tpr | F66: Bus Omnicanalidad | G66: WS | H66: Completado | I66: A Desarrollo | J66: UMPClientes0085 -> ConsultarGarantiasSAR01 -> http://10.60.144.57:9443/consultaGarantiasSARWS/GarantiasSARWSService | K66: Was intenerxo TXT BANCS | L66: ON-PREMISE | M66: 1 | N66: Baja | O66: SOAP | P66: 1 | Q66: Baja | R66: Ninguna | S66: 0 | T66: Baja | U66: Ninguna | W66: Baja | X66: 2.94K | Y66: 84.3 ms | AB66: Baja | AC66: Independiente | AD66: Media | AE66: AREA MICROFINANZAS | AF66: ORQClientes0017 | AG66: 0 | AH66: 1 | AI66: Baja | AJ66: Ninguno | AK66: Baja | AL66: ConsultarGarantiasSAR01 | AM66: Baja | AN66: =IFERROR(SUM(CHOOSE(MATCH(N66,{"Baja";"Media";"Alta"},0),1,2,3), CHOOSE(MATCH(Q66,{"Baja";"Media";"Alta"},0),1,2,3), CHOOSE(MATCH(T66,{"Baja";"Media";"Alta"},0),1,2,3), CHOOSE(MATCH(W66,{"Baja";"Media";"Alta"},0),1,2,3), CHOOSE(MATCH(AB66,{"Baja";"Media";"Alta"},0),1,2,3), CHOOSE(MATCH(AD66,{"Baja";"Media";"Alta"},0),1,2,3), CHOOSE(MATCH(AI66,{"Baja";"Media";"Alta"},0),1,2,3), CHOOSE(MATCH(AK66,{"Baja";"Media";"Alta"},0),1,2,3), CHOOSE(MATCH(AM66,{"Baja";"Media";"Alta"},0),1,2,3)),0) -> 10 | AO66: =IF(AN66=0,"Pendiente",IF(AN66<=15,"Bajo",IF(AN66<=21,"Medio","Alto"))) -> Bajo | AR66: =VLOOKUP(A66,#REF!,2,FALSE) -> #REF! | AS66: https://s.icepanel.io/wJSECZOwwNkkW8/EtER | AT66: https://dev.azure.com/BancoPichinchaEC/adi-especificaciones-tecnicas/_git/adi-doc-tecspec-tribu-integracion-apis?version=GBmaster&path=/sp%20-%20Soporte/tpr-msa-sp-wsclientes0080 | AU66: https://dev.azure.com/BancoPichinchaEC/tpl-bus-omnicanal/_git/sqb-msa-wsclientes0080 | AV66: 1 | AW66: Revisar consume was internexo
A67: WSClientes0081 | B67: =CONCATENATE(LOWER(E67),"-msa-sp-",LOWER(A67)) -> tnd-msa-sp-wsclientes0081 | C67: Consulta las firmas autorizadas de un cliente -cuenta | D67: TRIBU SEGMENTOS Y NEGOCIOS DIGITALES | E67: =VLOOKUP(D67,Tribus!$A$1:$B$33,2,FALSE) -> tnd | F67: Bus Omnicanalidad | G67: WS | H67: Completado | I67: A Desarrollo | J67: UMPProductos0028->ConsultarCuentas0028->TX060457 | K67: TXT BANCS | L67: ON-PREMISE | M67: 1 | N67: Baja | O67: SOAP | P67: 1 | Q67: Baja | R67: NO | S67: 0 | T67: Baja | U67: Ninguna | W67: Baja | X67: 12k/Diario | Y67: 50ms | AB67: Baja | AC67: ORQClientes0024 | AD67: Media | AE67: BPM Tribu Retail | AF67: ORQClientes0024 | AH67: 1 | AI67: Baja | AJ67: NO | AK67: Baja | AL67: ConsultarCuentasFirmaAutorizada01 | AM67: Baja | AN67: =IFERROR(SUM(CHOOSE(MATCH(N67,{"Baja";"Media";"Alta"},0),1,2,3), CHOOSE(MATCH(Q67,{"Baja";"Media";"Alta"},0),1,2,3), CHOOSE(MATCH(T67,{"Baja";"Media";"Alta"},0),1,2,3), CHOOSE(MATCH(W67,{"Baja";"Media";"Alta"},0),1,2,3), CHOOSE(MATCH(AB67,{"Baja";"Media";"Alta"},0),1,2,3), CHOOSE(MATCH(AD67,{"Baja";"Media";"Alta"},0),1,2,3), CHOOSE(MATCH(AI67,{"Baja";"Media";"Alta"},0),1,2,3), CHOOSE(MATCH(AK67,{"Baja";"Media";"Alta"},0),1,2,3), CHOOSE(MATCH(AM67,{"Baja";"Media";"Alta"},0),1,2,3)),0) -> 10 | AO67: =IF(AN67=0,"Pendiente",IF(AN67<=15,"Bajo",IF(AN67<=21,"Medio","Alto"))) -> Bajo | AR67: =VLOOKUP(A67,#REF!,2,FALSE) -> #REF! | AS67: https://s.icepanel.io/wJSECZOwwNkkW8/Rdmx | AT67: https://dev.azure.com/BancoPichinchaEC/adi-especificaciones-tecnicas/_git/adi-doc-tecspec-tribu-integracion-apis?path=/sp%20-%20Soporte/tnd-msa-sp-wsclientes0081 | AU67: https://dev.azure.com/BancoPichinchaEC/tpl-bus-omnicanal/_git/sqb-msa-wsclientes0081 | AV67: 1 | AW67: https://pichincha.atlassian.net/browse/PCBG-484
A68: WSClientes0082 | B68: =CONCATENATE(LOWER(E68),"-msa-sp-",LOWER(A68)) -> tnd-msa-sp-wsclientes0082 | C68: Servicio de consulta de productos del cliente | D68: TRIBU SEGMENTOS Y NEGOCIOS DIGITALES | E68: =VLOOKUP(D68,Tribus!$A$1:$B$33,2,FALSE) -> tnd | F68: Bus Omnicanalidad | G68: WS | H68: Completado | I68: A Desarrollo | J68: UMPProductos0021 (ConsultarCuentas21) -> Consulta de Cuentas del cliente en Bancs TX060453 -> TX060452 -> TX de consulta cuentas en Bancs | K68: TXT BANCS | L68: ON-PREMISE | M68: 2 | N68: Media | O68: SOAP - 8934 | P68: 1 | Q68: Baja | R68: Ninguna | S68: 0 | T68: Baja | U68: Ninguna | W68: Baja | X68: 24.6K | Y68: 37.9 ms | AB68: Baja | AD68: Media | AF68: ORQClientes0024 ORQClientes0025 ORQClientes0026 | AH68: 3 | AI68: Media | AJ68: N/A | AK68: Baja | AL68: ConsultarCuentasTipoEstado01 | AM68: Baja | AN68: =IFERROR(SUM(CHOOSE(MATCH(N68,{"Baja";"Media";"Alta"},0),1,2,3), CHOOSE(MATCH(Q68,{"Baja";"Media";"Alta"},0),1,2,3), CHOOSE(MATCH(T68,{"Baja";"Media";"Alta"},0),1,2,3), CHOOSE(MATCH(W68,{"Baja";"Media";"Alta"},0),1,2,3), CHOOSE(MATCH(AB68,{"Baja";"Media";"Alta"},0),1,2,3), CHOOSE(MATCH(AD68,{"Baja";"Media";"Alta"},0),1,2,3), CHOOSE(MATCH(AI68,{"Baja";"Media";"Alta"},0),1,2,3), CHOOSE(MATCH(AK68,{"Baja";"Media";"Alta"},0),1,2,3), CHOOSE(MATCH(AM68,{"Baja";"Media";"Alta"},0),1,2,3)),0) -> 12 | AO68: =IF(AN68=0,"Pendiente",IF(AN68<=15,"Bajo",IF(AN68<=21,"Medio","Alto"))) -> Bajo | AQ68: Uso de servicio Configurable en WS y Ump | AR68: =VLOOKUP(A68,#REF!,2,FALSE) -> #REF! | AS68: https://s.icepanel.io/wJSECZOwwNkkW8/AHFQ | AT68: https://dev.azure.com/BancoPichinchaEC/adi-especificaciones-tecnicas/_git/adi-doc-tecspec-tribu-integracion-apis?path=/sp%20-%20Soporte/tnd-msa-sp-wsclientes0082 | AU68: sqb-msa-wsclientes0082 - Repos | AV68: 1 | AW68: https://pichincha.atlassian.net/browse/PCBG-398
A69: WSClientes0096 | B69: =CONCATENATE(LOWER(E69),"-msa-sp-",LOWER(A69)) -> tnd-msa-sp-wsclientes0096 | C69: Procedimiento que realiza la operacion de creacion de prospecto del cliente | D69: TRIBU SEGMENTOS Y NEGOCIOS DIGITALES | E69: =VLOOKUP(D69,Tribus!$A$1:$B$33,2,FALSE) -> tnd | F69: Bus Omnicanalidad | G69: WS | H69: Completado | I69: A Desarrollo | J69: UMPClientes0098 -> 062001 | K69: BANCS | L69: ON-PREMISE | M69: 1 | N69: Baja | O69: SOAP | P69: 1 | Q69: Baja | R69: Ninguna | S69: 0 | T69: Baja | U69: Ninguna | V69: No aplica | W69: Baja | X69: 38 | Y69: 144 ms | AB69: Baja | AC69: Afecta un servicio | AD69: Media | AE69: TRIBU SEGMENTOS Y NEGOCIOS DIGITALES | AF69: CustoimerController → - ach-msa-customer - ExpressApplicationController - ach-msa-mortgage-back - Netty - ach-msa-bff-loan-application ORQClientes0035 | AG69: no aplica | AH69: 2 | AI69: Media | AJ69: 0 | AK69: Baja | AL69: CrearProspecto21 | AM69: Baja | AN69: =IFERROR(SUM(CHOOSE(MATCH(N69,{"Baja";"Media";"Alta"},0),1,2,3), CHOOSE(MATCH(Q69,{"Baja";"Media";"Alta"},0),1,2,3), CHOOSE(MATCH(T69,{"Baja";"Media";"Alta"},0),1,2,3), CHOOSE(MATCH(W69,{"Baja";"Media";"Alta"},0),1,2,3), CHOOSE(MATCH(AB69,{"Baja";"Media";"Alta"},0),1,2,3), CHOOSE(MATCH(AD69,{"Baja";"Media";"Alta"},0),1,2,3), CHOOSE(MATCH(AI69,{"Baja";"Media";"Alta"},0),1,2,3), CHOOSE(MATCH(AK69,{"Baja";"Media";"Alta"},0),1,2,3), CHOOSE(MATCH(AM69,{"Baja";"Media";"Alta"},0),1,2,3)),0) -> 11 | AO69: =IF(AN69=0,"Pendiente",IF(AN69<=15,"Bajo",IF(AN69<=21,"Medio","Alto"))) -> Bajo | AR69: =VLOOKUP(A69,#REF!,2,FALSE) -> #REF! | AS69: https://dev.azure.com/BancoPichinchaEC/tpl-bus-omnicanal/_git/sqb-msa-wsclientes0096 | AT69: https://dev.azure.com/BancoPichinchaEC/adi-especificaciones-tecnicas/_git/adi-doc-tecspec-tribu-integracion-apis?path=/sp%20-%20Soporte/tnd-msa-sp-wsclientes0096 | AU69: https://dev.azure.com/BancoPichinchaEC/tpl-bus-omnicanal/_git/sqb-msa-wsclientes0096 | AV69: 1 | AW69: https://pichincha.atlassian.net/browse/PCBG-743
A70: WSClientes0099 | B70: =CONCATENATE(LOWER(E70),"-msa-sp-",LOWER(A70)) -> tnd-msa-sp-wsclientes0099 | C70: Permite actualizar la información de localización de un cliente en Bancs | D70: TRIBU SEGMENTOS Y NEGOCIOS DIGITALES | E70: =VLOOKUP(D70,Tribus!$A$1:$B$33,2,FALSE) -> tnd | F70: Bus Omnicanalidad | G70: WS | H70: Completado | I70: A Desarrollo | J70: UMPClientes0064 (OperacionLocalizacion51) : Consulta la localizacion de un cliente -> TX061404 - Consulta la direccion de un cliente UMPClientes0065 - OperacionGeolocalizacion51 - TX062130 - Consulta la geolocalizacion de un cliente | K70: TXT BANCS | L70: ON-PREMISE | M70: 2 | N70: Media | O70: 8934 - SOAP | P70: 1 | Q70: Baja | R70: Ninguna | S70: 0 | T70: Baja | U70: Ninguna | W70: Baja | X70: 100k | Y70: 68.5 ms | AB70: Baja | AC70: Afecta algunos servicios | AD70: Media | AF70: ORQClientes0016 ORQClientes0035 ORQClientes0038 ORQClientes0048 ORQClientes0054 ORQProductos0068 ORQProductos0072 | AG70: Default Web Site:443,8043 (/BPMPichinchaOC) | AH70: 8 | AI70: Alta | AJ70: Ninguno | AK70: Baja | AL70: OperacionLocalizacion51 | AM70: Baja | AN70: =IFERROR(SUM(CHOOSE(MATCH(N70,{"Baja";"Media";"Alta"},0),1,2,3), CHOOSE(MATCH(Q70,{"Baja";"Media";"Alta"},0),1,2,3), CHOOSE(MATCH(T70,{"Baja";"Media";"Alta"},0),1,2,3), CHOOSE(MATCH(W70,{"Baja";"Media";"Alta"},0),1,2,3), CHOOSE(MATCH(AB70,{"Baja";"Media";"Alta"},0),1,2,3), CHOOSE(MATCH(AD70,{"Baja";"Media";"Alta"},0),1,2,3), CHOOSE(MATCH(AI70,{"Baja";"Media";"Alta"},0),1,2,3), CHOOSE(MATCH(AK70,{"Baja";"Media";"Alta"},0),1,2,3), CHOOSE(MATCH(AM70,{"Baja";"Media";"Alta"},0),1,2,3)),0) -> 13 | AO70: =IF(AN70=0,"Pendiente",IF(AN70<=15,"Bajo",IF(AN70<=21,"Medio","Alto"))) -> Bajo | AR70: =VLOOKUP(A70,#REF!,2,FALSE) -> #REF! | AS70: https://app.icepanel.io/landscapes/w71QNHgfDvF79GrSuA3r/versions/latest/diagrams/editor?diagram=QVLh3yXSvL&model=e9y69eff6aw&overlay_tab=tags&x1=-804.7&y1=-344&x2=2381.5&y2=1288 | AT70: https://dev.azure.com/BancoPichinchaEC/adi-especificaciones-tecnicas/_git/adi-doc-tecspec-tribu-integracion-apis?path=/sp%20-%20Soporte/tnd-msa-sp-wsclientes0099 | AU70: https://dev.azure.com/BancoPichinchaEC/tpl-bus-omnicanal/_git/sqb-msa-wsclientes0099 | AV70: 1 | AW70: https://pichincha.atlassian.net/browse/PCBG-399
A71: WSClientes0101 | B71: =CONCATENATE(LOWER(E71),"-msa-sp-",LOWER(A71)) -> tnd-msa-sp-wsclientes0101 | C71: Obtiene informacion de relacion del cliente | D71: TRIBU SEGMENTOS Y NEGOCIOS DIGITALES | E71: =VLOOKUP(D71,Tribus!$A$1:$B$33,2,FALSE) -> tnd | F71: Bus Omnicanalidad | G71: WS | H71: Completado | I71: A Desarrollo | J71: UMPClientes0076 -> OperacionInformacionComplementariaRelaciones51 -> 067151 -> Consultar informacion complementaria de referencia del cliente | K71: TXT BANCS | L71: ON-PREMISE | M71: 1 | N71: Baja | O71: SOAP | P71: 1 | Q71: Baja | R71: Ninguna | S71: 0 | T71: Baja | U71: Ninguna | W71: Baja | X71: 88.2K | Y71: 27.3ms | AB71: Media | AC71: Afecta algunos servicios | AD71: Media | AE71: TRIBU CANALES TRIBU PRODUCTOS AREA MICROFINANZAS COE_TRANSFORMACION_PROCESOS | AF71: ORQClientes0035 ORQClientes0036 ORQClientes0038 ORQClientes0048 ORQClientes0059 | AH71: 5 | AI71: Alta | AJ71: Ninguno | AK71: Baja | AL71: OperacionRelacionesCliente51 | AM71: Baja | AN71: =IFERROR(SUM(CHOOSE(MATCH(N71,{"Baja";"Media";"Alta"},0),1,2,3), CHOOSE(MATCH(Q71,{"Baja";"Media";"Alta"},0),1,2,3), CHOOSE(MATCH(T71,{"Baja";"Media";"Alta"},0),1,2,3), CHOOSE(MATCH(W71,{"Baja";"Media";"Alta"},0),1,2,3), CHOOSE(MATCH(AB71,{"Baja";"Media";"Alta"},0),1,2,3), CHOOSE(MATCH(AD71,{"Baja";"Media";"Alta"},0),1,2,3), CHOOSE(MATCH(AI71,{"Baja";"Media";"Alta"},0),1,2,3), CHOOSE(MATCH(AK71,{"Baja";"Media";"Alta"},0),1,2,3), CHOOSE(MATCH(AM71,{"Baja";"Media";"Alta"},0),1,2,3)),0) -> 13 | AO71: =IF(AN71=0,"Pendiente",IF(AN71<=15,"Bajo",IF(AN71<=21,"Medio","Alto"))) -> Bajo | AR71: =VLOOKUP(A71,#REF!,2,FALSE) -> #REF! | AS71: https://s.icepanel.io/wJSECZOwwNkkW8/xPql | AT71: https://dev.azure.com/BancoPichinchaEC/adi-especificaciones-tecnicas/_git/adi-doc-tecspec-tribu-integracion-apis?path=/sp%20-%20Soporte/tnd-msa-sp-wsclientes0101 | AU71: https://dev.azure.com/BancoPichinchaEC/tpl-bus-omnicanal/_git/sqb-msa-wsclientes0101 | AV71: 1 | AW71: https://pichincha.atlassian.net/browse/PCBG-400
A72: WSClientes0102 | B72: =CONCATENATE(LOWER(E72),"-msa-sp-",LOWER(A72)) -> tnd-msa-sp-wsclientes0102 | C72: Segmenta al cliente | D72: TRIBU SEGMENTOS Y NEGOCIOS DIGITALES | E72: =VLOOKUP(D72,Tribus!$A$1:$B$33,2,FALSE) -> tnd | F72: Bus Omnicanalidad | G72: WS | H72: Completado | I72: A Desarrollo | J72: UMPClientes0103 -> SegmentacionEntradaFija01-> Segmenta al cliente -> http://10.0.134.224/WebSrvSegmentacion/ServiceSegmentacion.asmx | K72: WEBSERVICE ANTIGUO | L72: ON-PREMISE | M72: 3 | N72: Media | O72: SOAP - 8934 | P72: 1 | Q72: Baja | R72: Ninguna | S72: 0 | T72: Baja | U72: Ninguna | W72: Baja | X72: 0.036k | Y72: 1140ms | AB72: Baja | AC72: Afecta a un servicio | AD72: Media | AF72: ORQClientes0035 | AH72: 1 | AI72: Baja | AJ72: Ninguno | AK72: Baja | AL72: SegmentacionEntradaFija01 | AM72: Baja | AN72: =IFERROR(SUM(CHOOSE(MATCH(N72,{"Baja";"Media";"Alta"},0),1,2,3), CHOOSE(MATCH(Q72,{"Baja";"Media";"Alta"},0),1,2,3), CHOOSE(MATCH(T72,{"Baja";"Media";"Alta"},0),1,2,3), CHOOSE(MATCH(W72,{"Baja";"Media";"Alta"},0),1,2,3), CHOOSE(MATCH(AB72,{"Baja";"Media";"Alta"},0),1,2,3), CHOOSE(MATCH(AD72,{"Baja";"Media";"Alta"},0),1,2,3), CHOOSE(MATCH(AI72,{"Baja";"Media";"Alta"},0),1,2,3), CHOOSE(MATCH(AK72,{"Baja";"Media";"Alta"},0),1,2,3), CHOOSE(MATCH(AM72,{"Baja";"Media";"Alta"},0),1,2,3)),0) -> 11 | AO72: =IF(AN72=0,"Pendiente",IF(AN72<=15,"Bajo",IF(AN72<=21,"Medio","Alto"))) -> Bajo | AR72: =VLOOKUP(A72,#REF!,2,FALSE) -> #REF! | AS72: https://app.icepanel.io/landscapes/w71QNHgfDvF79GrSuA3r/versions/latest/diagrams/editor?diagram=TL4LSX3Rai&model=DzImGA4TxF&overlay_tab=tags&x1=-1164.9&y1=-56&x2=2100.9&y2=1392 | AT72: https://dev.azure.com/BancoPichinchaEC/adi-especificaciones-tecnicas/_git/adi-doc-tecspec-tribu-integracion-apis?path=/sp%20-%20Soporte/tnd-msa-sp-wsclientes0102 | AU72: https://dev.azure.com/BancoPichinchaEC/tpl-bus-omnicanal/_git/sqb-msa-wsclientes0102 | AV72: 1 | AW72: arle doble check
A73: WSClientes0103 | B73: =CONCATENATE(LOWER(E73),"-msa-sp-",LOWER(A73)) -> tnd-msa-sp-wsclientes0103 | C73: Servicio que permite actualizar la informacion de un cliente | D73: TRIBU SEGMENTOS Y NEGOCIOS DIGITALES | E73: =VLOOKUP(D73,Tribus!$A$1:$B$33,2,FALSE) -> tnd | F73: Bus Omnicanalidad | G73: WS | H73: Completado | I73: A Desarrollo | J73: umpclientes0102 -> Actualizacion del cliente en bancs TX067510 -> Procedimiento que realiza la operacion de actualizacion del cliente | K73: TXT BANCS | L73: ON-PREMISE | M73: 1 | N73: Baja | O73: SOAP - 8934 | P73: 1 | Q73: Baja | R73: Ninguna | S73: 0 | T73: Baja | U73: Ninguna | W73: Baja | X73: 2.48k | Y73: 83.2 ms | AB73: Baja | AC73: Afecta algunos servicios | AD73: Media | AF73: ORQClientes0036 | AG73: N/A | AH73: 1 | AI73: Baja | AJ73: Ninguno | AK73: Baja | AL73: ActualizarInformacionCliente31 | AM73: Baja | AN73: =IFERROR(SUM(CHOOSE(MATCH(N73,{"Baja";"Media";"Alta"},0),1,2,3), CHOOSE(MATCH(Q73,{"Baja";"Media";"Alta"},0),1,2,3), CHOOSE(MATCH(T73,{"Baja";"Media";"Alta"},0),1,2,3), CHOOSE(MATCH(W73,{"Baja";"Media";"Alta"},0),1,2,3), CHOOSE(MATCH(AB73,{"Baja";"Media";"Alta"},0),1,2,3), CHOOSE(MATCH(AD73,{"Baja";"Media";"Alta"},0),1,2,3), CHOOSE(MATCH(AI73,{"Baja";"Media";"Alta"},0),1,2,3), CHOOSE(MATCH(AK73,{"Baja";"Media";"Alta"},0),1,2,3), CHOOSE(MATCH(AM73,{"Baja";"Media";"Alta"},0),1,2,3)),0) -> 10 | AO73: =IF(AN73=0,"Pendiente",IF(AN73<=15,"Bajo",IF(AN73<=21,"Medio","Alto"))) -> Bajo | AR73: =VLOOKUP(A73,#REF!,2,FALSE) -> #REF! | AS73: https://app.icepanel.io/landscapes/w71QNHgfDvF79GrSuA3r/versions/latest/diagrams/editor?diagram=lqKeQ1cgD9&model=fyjGEaNzjk&overlay_tab=tags&x1=-790.4&y1=-24&x2=2380.2&y2=1600 | AT73: https://dev.azure.com/BancoPichinchaEC/adi-especificaciones-tecnicas/_git/adi-doc-tecspec-tribu-integracion-apis?path=/sp%20-%20Soporte/tnd-msa-sp-wsclientes0103 | AU73: https://dev.azure.com/BancoPichinchaEC/tpl-bus-omnicanal/_git/sqb-msa-wsclientes0103 | AV73: 1 | AW73: https://pichincha.atlassian.net/browse/PCBG-487
A74: WSClientes0104 | B74: =CONCATENATE(LOWER(E74),"-msa-sp-",LOWER(A74)) -> tnd-msa-sp-wsclientes0104 | C74: Crea Prospecto Cliente | D74: TRIBU SEGMENTOS Y NEGOCIOS DIGITALES | E74: =VLOOKUP(D74,Tribus!$A$1:$B$33,2,FALSE) -> tnd | F74: Bus Omnicanalidad | G74: WS | H74: Completado | I74: A Desarrollo | J74: UMPClientes0109 -> crearProspectoCliente22 -> 062001 UMPClientes0117 -> actualizarCliente36 -> 067159 | K74: TXT BANCS | L74: ON-PREMISE | M74: 2 | N74: Media | O74: SOAP | P74: 1 | Q74: Baja | R74: Ninguna | S74: 0 | T74: Baja | U74: Ninguna | W74: Baja | X74: 2.82K | Y74: 286 ms | AB74: Baja | AC74: Independiente | AD74: Media | AE74: TRIBU PRODUCTOS | AF74: ORQClientes0038 | AG74: 0 | AH74: 1 | AI74: Baja | AJ74: Ninguno | AK74: Baja | AL74: crearProspectoCliente21 | AM74: Baja | AN74: =IFERROR(SUM(CHOOSE(MATCH(N74,{"Baja";"Media";"Alta"},0),1,2,3), CHOOSE(MATCH(Q74,{"Baja";"Media";"Alta"},0),1,2,3), CHOOSE(MATCH(T74,{"Baja";"Media";"Alta"},0),1,2,3), CHOOSE(MATCH(W74,{"Baja";"Media";"Alta"},0),1,2,3), CHOOSE(MATCH(AB74,{"Baja";"Media";"Alta"},0),1,2,3), CHOOSE(MATCH(AD74,{"Baja";"Media";"Alta"},0),1,2,3), CHOOSE(MATCH(AI74,{"Baja";"Media";"Alta"},0),1,2,3), CHOOSE(MATCH(AK74,{"Baja";"Media";"Alta"},0),1,2,3), CHOOSE(MATCH(AM74,{"Baja";"Media";"Alta"},0),1,2,3)),0) -> 11 | AO74: =IF(AN74=0,"Pendiente",IF(AN74<=15,"Bajo",IF(AN74<=21,"Medio","Alto"))) -> Bajo | AR74: =VLOOKUP(A74,#REF!,2,FALSE) -> #REF! | AS74: https://s.icepanel.io/wJSECZOwwNkkW8/O5Tt | AT74: https://dev.azure.com/BancoPichinchaEC/adi-especificaciones-tecnicas/_git/adi-doc-tecspec-tribu-integracion-apis?version=GBmaster&path=/sp%20-%20Soporte/tnd-msa-sp-wsclientes0104 | AU74: https://dev.azure.com/BancoPichinchaEC/tpl-bus-omnicanal/_git/sqb-msa-wsclientes0104 | AV74: 1 | AW74: https://pichincha.atlassian.net/browse/PCBG-488
A75: WSClientes0108 | B75: =CONCATENATE(LOWER(E75),"-msa-sp-",LOWER(A75)) -> tnd-msa-sp-wsclientes0108 | C75: Creacion de Clientes | D75: TRIBU SEGMENTOS Y NEGOCIOS DIGITALES | E75: =VLOOKUP(D75,Tribus!$A$1:$B$33,2,FALSE) -> tnd | F75: Bus Omnicanalidad | G75: WS | H75: Completado | I75: A Desarrollo | J75: UMPClientes0110->crearDetallesCliente21->consultarDetallesClienteTX67050() OP1 ,067000 UMPClientes0111->crearDetallePersonalesCliente21-> TX067050 OP5, 067101 UMPClientes0112->crearDetallesAdicionalesCliente21-> crearDetallesAdicionalesCliente21 TX067050op21 , ConsultarDetallesAdi TX67050 UMPClientes0013->ActualizarDatosIdentificacion31-> Consultar informacion de identificacion del cliente ConsultarTX067153 ,Modificar TX067153OP02 ,ConsultarTX067050OP21 ,ActualizarTX067116( ) UMPClientes0066-> OperacionCorrespondenciaLocalizacion51 , Consulta correspondencia 062120 | K75: TXT BANCS | L75: ON-PREMISE | M75: 1 | N75: Baja | O75: SOAP | P75: 1 | Q75: Baja | R75: NO | S75: 0 | T75: Baja | U75: Ninguna | W75: Baja | X75: 1.3k/Diario | Y75: 280ms | AB75: Baja | AC75: ORQClientes0038 | AD75: Media | AE75: Tribu Retail | AF75: ORQClientes0038 | AH75: 1 | AI75: Baja | AJ75: NO | AK75: Baja | AL75: crearCliente24 | AM75: Baja | AN75: =IFERROR(SUM(CHOOSE(MATCH(N75,{"Baja";"Media";"Alta"},0),1,2,3), CHOOSE(MATCH(Q75,{"Baja";"Media";"Alta"},0),1,2,3), CHOOSE(MATCH(T75,{"Baja";"Media";"Alta"},0),1,2,3), CHOOSE(MATCH(W75,{"Baja";"Media";"Alta"},0),1,2,3), CHOOSE(MATCH(AB75,{"Baja";"Media";"Alta"},0),1,2,3), CHOOSE(MATCH(AD75,{"Baja";"Media";"Alta"},0),1,2,3), CHOOSE(MATCH(AI75,{"Baja";"Media";"Alta"},0),1,2,3), CHOOSE(MATCH(AK75,{"Baja";"Media";"Alta"},0),1,2,3), CHOOSE(MATCH(AM75,{"Baja";"Media";"Alta"},0),1,2,3)),0) -> 10 | AO75: =IF(AN75=0,"Pendiente",IF(AN75<=15,"Bajo",IF(AN75<=21,"Medio","Alto"))) -> Bajo | AR75: =VLOOKUP(A75,#REF!,2,FALSE) -> #REF! | AS75: https://s.icepanel.io/wJSECZOwwNkkW8/Jruh | AT75: https://dev.azure.com/BancoPichinchaEC/adi-especificaciones-tecnicas/_git/adi-doc-tecspec-tribu-integracion-apis?path=/sp%20-%20Soporte/tnd-msa-sp-wsclientes0108 | AU75: https://dev.azure.com/BancoPichinchaEC/tpl-bus-omnicanal/_git/sqb-msa-wsclientes0108 | AV75: 1 | AW75: https://pichincha.atlassian.net/browse/PCBG-489
A76: WSClientes0111 | B76: =CONCATENATE(LOWER(E76),"-msa-sp-",LOWER(A76)) -> tnd-msa-sp-wsclientes0111 | C76: Microservicio que permite consultar, actualizar y crear datos de residencia fiscal de un cliente | D76: TRIBU SEGMENTOS Y NEGOCIOS DIGITALES | E76: =VLOOKUP(D76,Tribus!$A$1:$B$33,2,FALSE) -> tnd | F76: Bus Omnicanalidad | G76: WS | H76: Completado | I76: A Desarrollo | J76: UMPClientes0119 -> ActualizarResidenciaFiscal32 -> TX062123 -> Actualiza los datos de recidencia fiscal: DETALLE RESIDENCIA FISCAL y DETALLE ACCIONISTA. UMPClientes0002 -> ConsultarInformacionBasica01 -> TX060480 -> Consulta datos de contacto para cliente de BEP e información básica UMPClientes0142 -> ConsultarResidenciaFiscalIdentificacion01 -> TX062124 -> Consultar los datos de residencia fiscal por el tipo de identificación y la identificación UMPClientes0020 -> ConsultaInformacionCliente01 -> TX067050 -> Consulta información basica del cliente UMPClientes0116 -> CrearResidenciaFiscal23 -> TX062123 -> Crear los datos de recidencia fiscal por el CustId, Opt y AddrInstance: DETALLE RESIDENCIA FISCAL y DETALLE ACCIONISTA. | K76: TXT BANCS | L76: ON-PREMISE | M76: 5 | N76: Alta | O76: SOAP - 8934 REST -8912 | P76: 2 | Q76: Media | R76: Ninguna | S76: 0 | T76: Baja | U76: Ninguna | W76: Baja | X76: 118,20K | Y76: 45.1ms | AB76: Media | AC76: Afecta algunos servicios | AD76: Media | AE76: TRIBU PRODUCTOS TRIBU CANALES *TRIBU SEGMENTOS Y NEGOCIOS DIGITALES* | AF76: Netty on 0:0:0:0:0:0:0:0:*; onb-msa-tax-residence Netty on 0:0:0:0:0:0:0:0:*; deployment-one-msa-sp-customer-v* ORQClientes0040 ORQClientes0045 ORQProductos0065 ORQProductos1002 ResidenciaFiscalController; deployment-cta-msa-residencia-fiscal-* https://serviciosexternos.pichincha.com/api/ResidenciaFiscal | AG76: Default Web Site:443,8043 (/BPMPichinchaCTA) Default Web Site:443,8043 (/BPMPichinchaSG) Default Web Site:8080,8443 (/Nxt_4.0.9168.396) IAutomatizacionProcesosServices https://serviciosexternos.pichincha.com/api/ResidenciaFiscal | AH76: 10 | AI76: Media | AJ76: Ninguno | AK76: Baja | AL76: ActualizarResidenciaFiscal32 ConsultarInformacionBasica01 ConsultarResidenciaFiscalIdentificacion01 ConsultaInformacionCliente01 CrearResidenciaFiscal23 | AM76: Alta | AN76: =IFERROR(SUM(CHOOSE(MATCH(N76,{"Baja";"Media";"Alta"},0),1,2,3), CHOOSE(MATCH(Q76,{"Baja";"Media";"Alta"},0),1,2,3), CHOOSE(MATCH(T76,{"Baja";"Media";"Alta"},0),1,2,3), CHOOSE(MATCH(W76,{"Baja";"Media";"Alta"},0),1,2,3), CHOOSE(MATCH(AB76,{"Baja";"Media";"Alta"},0),1,2,3), CHOOSE(MATCH(AD76,{"Baja";"Media";"Alta"},0),1,2,3), CHOOSE(MATCH(AI76,{"Baja";"Media";"Alta"},0),1,2,3), CHOOSE(MATCH(AK76,{"Baja";"Media";"Alta"},0),1,2,3), CHOOSE(MATCH(AM76,{"Baja";"Media";"Alta"},0),1,2,3)),0) -> 17 | AO76: =IF(AN76=0,"Pendiente",IF(AN76<=15,"Bajo",IF(AN76<=21,"Medio","Alto"))) -> Medio | AQ76: Considerar que el servicio se va a reutilizar por temas regulatorios. Coordinar pruebas con Carolina Campuzano/ Enrique Marquez El microservicio se está consumiendo por datapower externo usando la url https://serviciosexternos.pichincha.com/api/ResidenciaFiscal | AR76: =VLOOKUP(A76,#REF!,2,FALSE) -> #REF! | AS76: https://app.icepanel.io/landscapes/w71QNHgfDvF79GrSuA3r/versions/latest/diagrams/editor?diagram=rwZXVIVRx1&model=j4cx7gpdiv8&overlay_tab=tags&x1=-1551.4&y1=-232&x2=2183.4&y2=1424 | AT76: https://dev.azure.com/BancoPichinchaEC/adi-especificaciones-tecnicas/_git/adi-doc-tecspec-tribu-integracion-apis?path=/sp%20-%20Soporte/tnd-msa-sp-wsclientes0111 | AU76: https://dev.azure.com/BancoPichinchaEC/tpl-bus-omnicanal/_git/sqb-msa-wsclientes0111 | AV76: 1 | AW76: https://pichincha.atlassian.net/browse/PCBG-401
A77: WSClientes0114 | B77: =CONCATENATE(LOWER(E77),"-msa-sp-",LOWER(A77)) -> tnd-msa-sp-wsclientes0114 | C77: Servicio que consulta cuentas activas del cliente incluyendo cupo por canal. | D77: TRIBU SEGMENTOS Y NEGOCIOS DIGITALES | E77: =VLOOKUP(D77,Tribus!$A$1:$B$33,2,FALSE) -> tnd | F77: Bus Omnicanalidad | G77: WS | H77: Completado | I77: A Desarrollo | J77: UMPProductos0049 --> ConsultarPosicionConsolidadaCliente01 --> TX060450 UMPProductos0033 --> ConsultarCondicionFirma01 --> TX064014 UMPProductos0005 --> ConsultarCanalTransaccionCuenta01 --> TX079007 UMPClientes0002 --> ConsultarInformacionBasica01 --> TX060480 UMPProductos0001 --> ConsultarCuentas01 --> TX060453 UMPProductos0001 --> ConsultarCuentas01 --> TX060452 | K77: TXT Bancs | L77: ON-PREMISE | M77: 6 | N77: Alta | O77: SOAP | P77: 1 | Q77: Baja | R77: Ninguna | S77: 0 | T77: Baja | U77: Ninguna | W77: Baja | X77: 5.62M | Y77: 80ms | AB77: Alta | AC77: Afecta algunos servicios | AD77: Media | AE77: TRIBU PRODUCTOS | AF77: ORQClientes0003 ORQClientes0007 WSClientes0179.API - /api/v1/ValidarCuentas/ValidarCuentas01 | AH77: 3 | AI77: Media | AJ77: Ninguno | AK77: Baja | AL77: ConsultaCuentasCliente02 ConsultarCuentasActivasCliente01 | AM77: Media | AN77: =IFERROR(SUM(CHOOSE(MATCH(N77,{"Baja";"Media";"Alta"},0),1,2,3), CHOOSE(MATCH(Q77,{"Baja";"Media";"Alta"},0),1,2,3), CHOOSE(MATCH(T77,{"Baja";"Media";"Alta"},0),1,2,3), CHOOSE(MATCH(W77,{"Baja";"Media";"Alta"},0),1,2,3), CHOOSE(MATCH(AB77,{"Baja";"Media";"Alta"},0),1,2,3), CHOOSE(MATCH(AD77,{"Baja";"Media";"Alta"},0),1,2,3), CHOOSE(MATCH(AI77,{"Baja";"Media";"Alta"},0),1,2,3), CHOOSE(MATCH(AK77,{"Baja";"Media";"Alta"},0),1,2,3), CHOOSE(MATCH(AM77,{"Baja";"Media";"Alta"},0),1,2,3)),0) -> 16 | AO77: =IF(AN77=0,"Pendiente",IF(AN77<=15,"Bajo",IF(AN77<=21,"Medio","Alto"))) -> Medio | AR77: =VLOOKUP(A77,#REF!,2,FALSE) -> #REF! | AS77: https://s.icepanel.io/wJSECZOwwNkkW8/UC2g | AT77: https://dev.azure.com/BancoPichinchaEC/adi-especificaciones-tecnicas/_git/adi-doc-tecspec-tribu-integracion-apis?path=/sp%20-%20Soporte/tnd-msa-sp-wsclientes0114 | AU77: sqb-msa-wsclientes0114 - Repos | AV77: 1 | AW77: https://pichincha.atlassian.net/browse/PCBG-402
A78: WSClientes0122 | B78: =CONCATENATE(LOWER(E78),"-msa-sp-",LOWER(A78)) -> tnd-msa-sp-wsclientes0122 | C78: Servicio que consulta las relaciones asociadas a un cliente como garantes, codeudores, etc. | D78: TRIBU SEGMENTOS Y NEGOCIOS DIGITALES | E78: =VLOOKUP(D78,Tribus!$A$1:$B$33,2,FALSE) -> tnd | F78: Bus Omnicanalidad | G78: WS | H78: Completado | I78: A Desarrollo | J78: UMPClientes0177 --> ConsultaRelacionesCliente04 --> TX060430 | K78: TXT Bancs | L78: ON-PREMISE | M78: 1 | N78: Baja | O78: SOAP | P78: 1 | Q78: Baja | R78: Ninguna | S78: 0 | T78: Baja | U78: Ninguna | W78: Baja | X78: 179 | Y78: 26ms | AB78: Baja | AC78: Afecta un servicio | AD78: Media | AF78: ORQClientes0059 | AH78: 1 | AI78: Baja | AJ78: Ninguno | AK78: Baja | AL78: ConsultarRelacionesCliente01 ModificarRelacionCliente33 | AM78: Media | AN78: =IFERROR(SUM(CHOOSE(MATCH(N78,{"Baja";"Media";"Alta"},0),1,2,3), CHOOSE(MATCH(Q78,{"Baja";"Media";"Alta"},0),1,2,3), CHOOSE(MATCH(T78,{"Baja";"Media";"Alta"},0),1,2,3), CHOOSE(MATCH(W78,{"Baja";"Media";"Alta"},0),1,2,3), CHOOSE(MATCH(AB78,{"Baja";"Media";"Alta"},0),1,2,3), CHOOSE(MATCH(AD78,{"Baja";"Media";"Alta"},0),1,2,3), CHOOSE(MATCH(AI78,{"Baja";"Media";"Alta"},0),1,2,3), CHOOSE(MATCH(AK78,{"Baja";"Media";"Alta"},0),1,2,3), CHOOSE(MATCH(AM78,{"Baja";"Media";"Alta"},0),1,2,3)),0) -> 11 | AO78: =IF(AN78=0,"Pendiente",IF(AN78<=15,"Bajo",IF(AN78<=21,"Medio","Alto"))) -> Bajo | AR78: =VLOOKUP(A78,#REF!,2,FALSE) -> #REF! | AS78: https://s.icepanel.io/wJSECZOwwNkkW8/DDBi | AT78: https://dev.azure.com/BancoPichinchaEC/adi-especificaciones-tecnicas/_git/adi-doc-tecspec-tribu-integracion-apis?path=/sp%20-%20Soporte/tnd-msa-sp-wsclientes0122 | AU78: sqb-msa-wsclientes0122 - Repos | AV78: 1 | AW78: https://pichincha.atlassian.net/browse/PCBG-490
A79: WSClientes0153 | B79: =CONCATENATE(LOWER(E79),"-msa-sp-",LOWER(A79)) -> tnd-msa-sp-wsclientes0153 | C79: Consulta y Actualiza detalles adicionales del cliente en Bancs | D79: TRIBU SEGMENTOS Y NEGOCIOS DIGITALES | E79: =VLOOKUP(D79,Tribus!$A$1:$B$33,2,FALSE) -> tnd | F79: Bus Omnicanalidad | G79: WS | H79: Completado | I79: A Desarrollo | J79: UMPClientes0020 --> ConsultaInformacionCliente01 --> TX067050 opc 21 UMPClientes0180 --> ProcesarDatosAdicionalesCliente53 --> TX067116 | K79: TXT Bancs | L79: ON-PREMISE | M79: 2 | N79: Media | O79: 8934 - SOAP | P79: 1 | Q79: Baja | R79: Ninguna | S79: 0 | T79: Baja | U79: Ninguna | W79: Baja | X79: 835 | Y79: 30ms | AB79: Baja | AC79: Afecta un servicio | AD79: Media | AF79: ORQClientes0056 | AH79: 1 | AI79: Baja | AJ79: Ninguno | AK79: Baja | AL79: ConsultarDatosAdicionalesCliente01 ProcesarDatosAdicionalesCliente52 | AM79: Media | AN79: =IFERROR(SUM(CHOOSE(MATCH(N79,{"Baja";"Media";"Alta"},0),1,2,3), CHOOSE(MATCH(Q79,{"Baja";"Media";"Alta"},0),1,2,3), CHOOSE(MATCH(T79,{"Baja";"Media";"Alta"},0),1,2,3), CHOOSE(MATCH(W79,{"Baja";"Media";"Alta"},0),1,2,3), CHOOSE(MATCH(AB79,{"Baja";"Media";"Alta"},0),1,2,3), CHOOSE(MATCH(AD79,{"Baja";"Media";"Alta"},0),1,2,3), CHOOSE(MATCH(AI79,{"Baja";"Media";"Alta"},0),1,2,3), CHOOSE(MATCH(AK79,{"Baja";"Media";"Alta"},0),1,2,3), CHOOSE(MATCH(AM79,{"Baja";"Media";"Alta"},0),1,2,3)),0) -> 12 | AO79: =IF(AN79=0,"Pendiente",IF(AN79<=15,"Bajo",IF(AN79<=21,"Medio","Alto"))) -> Bajo | AR79: =VLOOKUP(A79,#REF!,2,FALSE) -> #REF! | AS79: https://s.icepanel.io/wJSECZOwwNkkW8/3UvV | AT79: https://dev.azure.com/BancoPichinchaEC/adi-especificaciones-tecnicas/_git/adi-doc-tecspec-tribu-integracion-apis?path=/sp%20-%20Soporte/tnd-msa-sp-wsclientes0153 | AU79: sqb-msa-wsclientes0153 - Repos | AV79: 1 | AW79: https://pichincha.atlassian.net/browse/PCBG-491
A80: WSClientes0156 | B80: =CONCATENATE(LOWER(E80),"-msa-sp-",LOWER(A80)) -> tnd-msa-sp-wsclientes0156 | C80: Actualiza Oficial Cliente - PCBG-492 | D80: TRIBU SEGMENTOS Y NEGOCIOS DIGITALES | E80: =VLOOKUP(D80,Tribus!$A$1:$B$33,2,FALSE) -> tnd | F80: Bus Omnicanalidad | G80: WS | H80: Completado | I80: A Desarrollo | J80: UMPClientes0057 -> ActualizarInformacionCliente31 -> 067116 | K80: TXT BANCS | L80: ON-PREMISE | M80: 1 | N80: Baja | O80: SOAP | P80: 1 | Q80: Baja | R80: Ninguna | S80: 0 | T80: Baja | U80: Ninguna | W80: Baja | X80: 1.096K | Y80: 30.3 ms | AB80: Baja | AC80: Independiente | AD80: Media | AE80: TRIBU SEGMENTOS Y NEGOCIOS DIGITALES | AF80: ORQClientes0056 | AG80: 0 | AH80: 1 | AI80: Baja | AJ80: Ninguno | AK80: Baja | AL80: ActualizarOficialCliente31 | AM80: Baja | AN80: =IFERROR(SUM(CHOOSE(MATCH(N80,{"Baja";"Media";"Alta"},0),1,2,3), CHOOSE(MATCH(Q80,{"Baja";"Media";"Alta"},0),1,2,3), CHOOSE(MATCH(T80,{"Baja";"Media";"Alta"},0),1,2,3), CHOOSE(MATCH(W80,{"Baja";"Media";"Alta"},0),1,2,3), CHOOSE(MATCH(AB80,{"Baja";"Media";"Alta"},0),1,2,3), CHOOSE(MATCH(AD80,{"Baja";"Media";"Alta"},0),1,2,3), CHOOSE(MATCH(AI80,{"Baja";"Media";"Alta"},0),1,2,3), CHOOSE(MATCH(AK80,{"Baja";"Media";"Alta"},0),1,2,3), CHOOSE(MATCH(AM80,{"Baja";"Media";"Alta"},0),1,2,3)),0) -> 10 | AO80: =IF(AN80=0,"Pendiente",IF(AN80<=15,"Bajo",IF(AN80<=21,"Medio","Alto"))) -> Bajo | AR80: =VLOOKUP(A80,#REF!,2,FALSE) -> #REF! | AS80: https://s.icepanel.io/wJSECZOwwNkkW8/IHiD | AT80: https://dev.azure.com/BancoPichinchaEC/adi-especificaciones-tecnicas/_git/adi-doc-tecspec-tribu-integracion-apis?path=/sp%20-%20Soporte/tnd-msa-sp-wsclientes0156 | AU80: https://dev.azure.com/BancoPichinchaEC/tpl-bus-omnicanal/_git/sqb-msa-wsclientes0156 | AV80: 1 | AW80: https://pichincha.atlassian.net/browse/PCBG-492
A81: WSProductos0009 | B81: =CONCATENATE(LOWER(E81),"-msa-sp-",LOWER(A81)) -> tct-msa-sp-wsproductos0009 | C81: Actualiza el monto maximo de transferencias | D81: TRIBU CORES Y TRANSACCIONES | E81: =VLOOKUP(D81,Tribus!$A$1:$B$33,2,FALSE) -> tct | F81: Bus Omnicanalidad | G81: WS | H81: Completado | I81: A Desarrollo | J81: UMPProductos0013 -> ActivarCupoCuentaTransferencia51 007070(Activa) 007071 (Procesa TX Salida ), UMPProductos0005 -> ConsultarCanalTransaccionCuenta01 , ConsultarTX060665() | K81: TXT BANCS | L81: ON-PREMISE | M81: 1 | N81: Baja | O81: SOAP , REST | P81: 2 | Q81: Media | R81: NO | S81: 0 | T81: Baja | U81: Ninguna | W81: Baja | X81: 30K | Y81: 123ms | AB81: Baja | AC81: ORQProductos0040 ORQClientes0007 | AD81: Media | AE81: Tribu Retail Tribu Canales Digitales COE Seguridad | AF81: ORQProductos0040 ORQClientes0007 | AG81: onb-msa-sp-setting-channel | AH81: 3 | AI81: Media | AJ81: NO | AK81: Baja | AL81: ActualizarMontoTransferenciaCuenta31 | AM81: Baja | AN81: =IFERROR(SUM(CHOOSE(MATCH(N81,{"Baja";"Media";"Alta"},0),1,2,3), CHOOSE(MATCH(Q81,{"Baja";"Media";"Alta"},0),1,2,3), CHOOSE(MATCH(T81,{"Baja";"Media";"Alta"},0),1,2,3), CHOOSE(MATCH(W81,{"Baja";"Media";"Alta"},0),1,2,3), CHOOSE(MATCH(AB81,{"Baja";"Media";"Alta"},0),1,2,3), CHOOSE(MATCH(AD81,{"Baja";"Media";"Alta"},0),1,2,3), CHOOSE(MATCH(AI81,{"Baja";"Media";"Alta"},0),1,2,3), CHOOSE(MATCH(AK81,{"Baja";"Media";"Alta"},0),1,2,3), CHOOSE(MATCH(AM81,{"Baja";"Media";"Alta"},0),1,2,3)),0) -> 12 | AO81: =IF(AN81=0,"Pendiente",IF(AN81<=15,"Bajo",IF(AN81<=21,"Medio","Alto"))) -> Bajo | AP81: Makensi | AR81: =VLOOKUP(A81,#REF!,2,FALSE) -> #REF! | AS81: https://s.icepanel.io/wJSECZOwwNkkW8/b9xY | AT81: https://dev.azure.com/BancoPichinchaEC/adi-especificaciones-tecnicas/_git/adi-doc-tecspec-tribu-integracion-apis?path=/sp%20-%20Soporte/tct-msa-sp-wsproductos0009 | AU81: https://dev.azure.com/BancoPichinchaEC/tpl-bus-omnicanal/_git/sqb-msa-wsproductos0009 | AV81: 1 | AW81: https://pichincha.atlassian.net/browse/PCBG-493
A82: WSProductos0016 | B82: =CONCATENATE(LOWER(E82),"-msa-sp-",LOWER(A82)) -> tpr-msa-sp-wsproductos0016 | C82: Consulta y ata cotitulares a la cuenta de un cliente | D82: TRIBU PRODUCTOS | E82: =VLOOKUP(D82,Tribus!$A$1:$B$33,2,FALSE) -> tpr | F82: Bus Omnicanalidad | G82: WS | H82: Completado | I82: A Desarrollo | J82: UMPProductos0036 --> ConsultarCotitularesCuenta01 --> TX 060602 UMPProductos0042 --> AtarCotitularesCuenta21 --> TX 060605 | K82: TXT Bancs | L82: ON-PREMISE | M82: 2 | N82: Media | O82: 8934 - SOAP | P82: 1 | Q82: Baja | R82: Ninguna | S82: 0 | T82: Baja | U82: Ninguna | W82: Baja | X82: 786 | Y82: 40ms | AB82: Baja | AC82: Afecta algunos servicios | AD82: Media | AF82: ORQProductos0074 ORQProductos0003 ORQClientes0024 | AH82: 3 | AI82: Media | AJ82: Ninguno | AK82: Baja | AL82: ConsultarCotitularesCuenta02 AtarCotitularesCuenta21 | AM82: Media | AN82: =IFERROR(SUM(CHOOSE(MATCH(N82,{"Baja";"Media";"Alta"},0),1,2,3), CHOOSE(MATCH(Q82,{"Baja";"Media";"Alta"},0),1,2,3), CHOOSE(MATCH(T82,{"Baja";"Media";"Alta"},0),1,2,3), CHOOSE(MATCH(W82,{"Baja";"Media";"Alta"},0),1,2,3), CHOOSE(MATCH(AB82,{"Baja";"Media";"Alta"},0),1,2,3), CHOOSE(MATCH(AD82,{"Baja";"Media";"Alta"},0),1,2,3), CHOOSE(MATCH(AI82,{"Baja";"Media";"Alta"},0),1,2,3), CHOOSE(MATCH(AK82,{"Baja";"Media";"Alta"},0),1,2,3), CHOOSE(MATCH(AM82,{"Baja";"Media";"Alta"},0),1,2,3)),0) -> 13 | AO82: =IF(AN82=0,"Pendiente",IF(AN82<=15,"Bajo",IF(AN82<=21,"Medio","Alto"))) -> Bajo | AP82: Makensi | AR82: =VLOOKUP(A82,#REF!,2,FALSE) -> #REF! | AS82: https://s.icepanel.io/wJSECZOwwNkkW8/5ZQY | AT82: https://dev.azure.com/BancoPichinchaEC/adi-especificaciones-tecnicas/_git/adi-doc-tecspec-tribu-integracion-apis?path=/sp%20-%20Soporte/tpr-msa-sp-wsproductos0016 | AU82: sqb-msa-wsproductos0016 - Repos | AV82: 1
A83: WSProductos0130 | B83: =CONCATENATE(LOWER(E83),"-msa-sp-",LOWER(A83)) -> tpr-msa-sp-wsproductos0130 | C83: Movimientos de cuenta | D83: TRIBU PRODUCTOS | E83: =VLOOKUP(D83,Tribus!$A$1:$B$33,2,FALSE) -> tpr | F83: Bus Omnicanalidad | G83: WS | H83: Completado | I83: A Desarrollo | J83: UMPProductos0173 -> ConsultarConsolidadoMovimientosCuenta01 -> TX007075() | K83: TXT BANCS | L83: ON-PREMISE | M83: 1 | N83: Baja | O83: SOAP | P83: 1 | Q83: Baja | R83: NO | S83: 0 | T83: Baja | U83: Ninguna | W83: Baja | X83: 850/Diarios | Y83: 150 ms | AB83: Baja | AC83: ORQClientes0026 | AD83: Media | AE83: BPM Tribu Retail, | AF83: ORQClientes0026 | AH83: 1 | AI83: Baja | AJ83: NO | AK83: Baja | AL83: ConsultarConsolidadoMovimientosCuenta01 | AM83: Baja | AN83: =IFERROR(SUM(CHOOSE(MATCH(N83,{"Baja";"Media";"Alta"},0),1,2,3), CHOOSE(MATCH(Q83,{"Baja";"Media";"Alta"},0),1,2,3), CHOOSE(MATCH(T83,{"Baja";"Media";"Alta"},0),1,2,3), CHOOSE(MATCH(W83,{"Baja";"Media";"Alta"},0),1,2,3), CHOOSE(MATCH(AB83,{"Baja";"Media";"Alta"},0),1,2,3), CHOOSE(MATCH(AD83,{"Baja";"Media";"Alta"},0),1,2,3), CHOOSE(MATCH(AI83,{"Baja";"Media";"Alta"},0),1,2,3), CHOOSE(MATCH(AK83,{"Baja";"Media";"Alta"},0),1,2,3), CHOOSE(MATCH(AM83,{"Baja";"Media";"Alta"},0),1,2,3)),0) -> 10 | AO83: =IF(AN83=0,"Pendiente",IF(AN83<=15,"Bajo",IF(AN83<=21,"Medio","Alto"))) -> Bajo | AR83: =VLOOKUP(A83,#REF!,2,FALSE) -> #REF! | AS83: https://s.icepanel.io/wJSECZOwwNkkW8/onY2 | AT83: https://dev.azure.com/BancoPichinchaEC/adi-especificaciones-tecnicas/_git/adi-doc-tecspec-tribu-integracion-apis?path=/sp%20-%20Soporte/tpr-msa-sp-wsproductos0130 | AU83: https://dev.azure.com/BancoPichinchaEC/tpl-bus-omnicanal/_git/sqb-msa-wsproductos0130 | AV83: 1 | AW83: https://pichincha.atlassian.net/browse/PCBG-495
A84: WSProductos0189 | B84: =CONCATENATE(LOWER(E84),"-msa-sp-",LOWER(A84)) -> tnd-msa-sp-wsproductos0189 | C84: Consulta de retenciones judiciales | D84: TRIBU SEGMENTOS Y NEGOCIOS DIGITALES | E84: =VLOOKUP(D84,Tribus!$A$1:$B$33,2,FALSE) -> tnd | F84: Bus Omnicanalidad | G84: WS | H84: Completado | I84: A Desarrollo | J84: UMPProductos0070 --> ConsultarRetencionesJudiciales01 --> TX067225 UMPProductos0223 --> ConsultarRetencionJudicialPorCuenta02 --> TX067228 | K84: TXT Bancs | L84: ON-PREMISE | M84: 2 | N84: Media | O84: SOAP | P84: 1 | Q84: Baja | R84: Ninguna | S84: 0 | T84: Baja | U84: Ninguna | W84: Baja | X84: 8.46k | Y84: 25ms | AB84: Baja | AC84: Afecta un servicio | AD84: Media | AF84: ORQClientes0053 | AH84: 1 | AI84: Baja | AJ84: Ninguno | AK84: Baja | AL84: consultarRetencionJudicialId01 consultarRetencionJudicialCuenta02 | AM84: Media | AN84: =IFERROR(SUM(CHOOSE(MATCH(N84,{"Baja";"Media";"Alta"},0),1,2,3), CHOOSE(MATCH(Q84,{"Baja";"Media";"Alta"},0),1,2,3), CHOOSE(MATCH(T84,{"Baja";"Media";"Alta"},0),1,2,3), CHOOSE(MATCH(W84,{"Baja";"Media";"Alta"},0),1,2,3), CHOOSE(MATCH(AB84,{"Baja";"Media";"Alta"},0),1,2,3), CHOOSE(MATCH(AD84,{"Baja";"Media";"Alta"},0),1,2,3), CHOOSE(MATCH(AI84,{"Baja";"Media";"Alta"},0),1,2,3), CHOOSE(MATCH(AK84,{"Baja";"Media";"Alta"},0),1,2,3), CHOOSE(MATCH(AM84,{"Baja";"Media";"Alta"},0),1,2,3)),0) -> 12 | AO84: =IF(AN84=0,"Pendiente",IF(AN84<=15,"Bajo",IF(AN84<=21,"Medio","Alto"))) -> Bajo | AR84: =VLOOKUP(A84,#REF!,2,FALSE) -> #REF! | AS84: https://s.icepanel.io/wJSECZOwwNkkW8/RS68 | AT84: https://dev.azure.com/BancoPichinchaEC/adi-especificaciones-tecnicas/_git/adi-doc-tecspec-tribu-integracion-apis?path=/sp%20-%20Soporte/tnd-msa-sp-wsproductos0189 | AU84: sqb-msa-wsproductos0189 - Repos | AV84: 1 | AW84: https://pichincha.atlassian.net/browse/PCBG-496
A85: WSReglas0004 | B85: =CONCATENATE(LOWER(E85),"-msa-sp-",LOWER(A85)) -> csg-msa-sp-wsreglas0004 | C85: Consulta regla de seguridad de ODM para delay | D85: COE CIBERSEGURIDAD | E85: =VLOOKUP(D85,Tribus!$A$1:$B$33,2,FALSE) -> csg | F85: Bus Omnicanalidad | G85: WS | H85: Completado | I85: A Desarrollo | J85: ODM --> /DecisionService/ws/DespliegueTecnicosDelay/OperacionTecnicosDelay/v75 | K85: ODM | L85: ON-PREMISE | M85: 1 | N85: Baja | O85: SOAP | P85: 1 | Q85: Baja | R85: Ninguna | S85: 0 | T85: Baja | U85: Ninguna | V85: Ninguna | W85: Baja | X85: 4.8K | Y85: 21.2 ms | AB85: Baja | AC85: Independiente | AD85: Media | AF85: ORQClientes0050 | AG85: 1 | AH85: 1 | AI85: Baja | AJ85: Ninguno | AK85: Baja | AL85: ConsultarTransaccionDelay01 | AM85: Baja | AN85: =IFERROR(SUM(CHOOSE(MATCH(N85,{"Baja";"Media";"Alta"},0),1,2,3), CHOOSE(MATCH(Q85,{"Baja";"Media";"Alta"},0),1,2,3), CHOOSE(MATCH(T85,{"Baja";"Media";"Alta"},0),1,2,3), CHOOSE(MATCH(W85,{"Baja";"Media";"Alta"},0),1,2,3), CHOOSE(MATCH(AB85,{"Baja";"Media";"Alta"},0),1,2,3), CHOOSE(MATCH(AD85,{"Baja";"Media";"Alta"},0),1,2,3), CHOOSE(MATCH(AI85,{"Baja";"Media";"Alta"},0),1,2,3), CHOOSE(MATCH(AK85,{"Baja";"Media";"Alta"},0),1,2,3), CHOOSE(MATCH(AM85,{"Baja";"Media";"Alta"},0),1,2,3)),0) -> 10 | AO85: =IF(AN85=0,"Pendiente",IF(AN85<=15,"Bajo",IF(AN85<=21,"Medio","Alto"))) -> Bajo | AQ85: En un inicio este servicio era utilizado para consulta de acciones de seguridad como el tiempo de espera, en servicios como transferencias directas o interbancarias, pero al momento solo se encuentra en uso por el servicio de actualización de contacto transaccional | AR85: =VLOOKUP(A85,#REF!,2,FALSE) -> #REF! | AS85: https://s.icepanel.io/wJSECZOwwNkkW8/9kNS | AT85: https://dev.azure.com/BancoPichinchaEC/adi-especificaciones-tecnicas/_git/adi-doc-tecspec-tribu-integracion-apis?version=GBmaster&path=/sp%20-%20Soporte/csg-msa-sp-wsreglas0004 | AU85: https://dev.azure.com/BancoPichinchaEC/tpl-bus-omnicanal/_git/sqb-msa-wsreglas0004 | AV85: 1 | AW85: https://pichincha.atlassian.net/browse/PCBG-497
